Workbook

Sheet 源数据
A1: 2018年度酒便利平台泸州老窖销量占比情况
A2: 全国酒便利周明细—河南 | J2: 国窖进2154；国窖出2161。（箱）
A3: 序号 | B3: 商品编码 | C3: 商品名称 | D3: 规格 | E3: 单价 | F3: 全年计划总量(瓶) | G3: 全年计划采购总金额 | H3: 成交价 | I3: 20171101-20181031 | K3: 20170501-20171031 | M3: 20180501-20181031 | R3: 本品情况 | W3: 竞品情况
I4: 出库数量 | J4: 出库金额 | K4: 出库数量 | L4: 出库金额 | M4: 出库数量 | N4: 出库金额 | Q4: 酒便利各公司白酒销售额（元） | R4: 酒便利各区域白酒销售总金额（元） | S4: 我司白酒在各区域销售额（元） | T4: 占比 | U4: 国窖销售额 | V4: 国窖占比 | W4: 普五销售额 | X4: 普五占比 | Y4: 普剑销售额 | Z4: 普剑占比 | AA4: 52海之蓝销售额 | AB4: 海之蓝占比
A5: 1 | B5: 101010397 | C5: 38°国窖1573 500ml | D5: 500ml*6 | E5: 530 | F5: 0 | G5: 0 | Q5: 河南酒便利白酒销售额 | R5: 4.3349845e+08 | S5: 24735880 | T5: =S5/R5 -> 0.057061057 | U5: 9710280 | V5: =U5/R5 -> 0.022399803 | W5: 55255963 | X5: =W5/R5 -> 0.12746519 | Y5: 55386699 | Z5: =Y5/R5 -> 0.12776677 | AA5: 15423160 | AB5: =AA5/R5 -> 0.03557835
A6: 2 | B6: 101010099 | C6: 52°国窖1573 500ml | D6: 500ml*6 | E6: 740 | F6: 15600 | G6: 11544000 | H6: 830.06 | I6: 13122 | J6: 10892047 | K6: 5289 | L6: 4390187.3 | M6: 4995 | N6: 4146149.7 | Q6: 北京酒便利白酒销售额 | R6: 1.1555258e+08 | S6: 8470335.2 | T6: =S6/R6 -> 0.073302863 | U6: 5311904.6 | V6: =U6/R6 -> 0.045969587 | W6: 9755379 | X6: =W6/R6 -> 0.08442372 | Y6: 3324629.5 | Z6: =Y6/R6 -> 0.028771573
A7: 3 | B7: 101010114 | C7: *52°百年泸州老窖酒窖龄30年500ml | D7: 500ml*6 | E7: 165 | F7: 7812 | G7: 1288980 | H7: 210.82 | I7: 2770 | J7: 583971.4 | K7: 1131 | L7: 238437.42 | M7: 1269 | N7: 267530.58 | Q7: 西安酒便利白酒销售额 | R7: 33470167 | S7: 3585472.7 | T7: =S7/R7 -> 0.10712443 | U7: 2712408.9 | V7: =U7/R7 -> 0.0810396 | W7: 4432500 | X7: =W7/R7 -> 0.13243137 | Y7: 1414867.5 | Z7: =Y7/R7 -> 0.042272496
A8: 4 | B8: 101010115 | C8: 52°百年泸州老窖酒窖龄60年500ml | D8: 500ml*6 | E8: 200 | F8: 15612 | G8: 3122400 | H8: 264.02 | I8: 5498 | J8: 1451582 | K8: 2544 | L8: 671666.88 | M8: 2334 | N8: 616222.68 | Q8: 徐州酒便利白酒销售额 | R8: 4535723.1 | S8: 139923.1 | T8: =S8/R8 -> 0.030849127 | U8: 94002.44 | V8: =U8/R8 -> 0.020724907 | W8: 428653.68 | X8: =W8/R8 -> 0.094506139 | Y8: 64774.29 | Z8: =Y8/R8 -> 0.014280918
A9: 5 | B9: 101010294 | C9: 38°泸州老窖泸州百年30年窖龄500ml | D9: 500ml*6 | E9: 145 | F9: 0 | G9: 0 | Q9: 总计 | R9: =SUM(R5:R8) -> 5.8705693e+08 | S9: =SUM(S5:S8) -> 36931611 | T9: =SUM(T5:T8) -> 0.26833748 | U9: =SUM(U5:U8) -> 17828596 | V9: =SUM(V5:V8) -> 0.1701339 | W9: =SUM(W5:W8) -> 69872496 | X9: =SUM(X5:X8) -> 0.43882642 | Y9: =SUM(Y5:Y8) -> 60190970 | Z9: =SUM(Z5:Z8) -> 0.21309176
A10: 6 | B10: 101010297 | C10: 38°泸州老窖百年60年窖龄500ml | D10: 500ml*6 | E10: 180 | F10: 0 | G10: 0
A11: 7 | B11: 101010036 | C11: 52°泸州老窖特曲500ml | D11: 500ml*6 | E11: 168 | F11: 85020 | G11: 14283360 | H11: 203.03 | I11: 46072 | J11: 9353998.2 | K11: 21635 | L11: 4392554 | M11: 21280 | N11: 4320478.4 | Q11: 酒便利各公司葡萄酒销售额（元） | R11: 酒便利各区域葡萄酒销售总金额（元） | S11: 我司葡萄酒在各区域销售额（元） | T11: 占比 | U11: 舒富销售额 | V11: 舒富占比
A12: 8 | B12: 101010024 | C12: 52°泸州老窖头曲500ml | D12: 500ml*6 | E12: 37.87 | F12: 39000 | G12: 1476930 | H12: 60.09 | I12: 21460 | J12: 1289531.4 | K12: 7817 | L12: 469723.53 | M12: 9236 | N12: 554991.24 | Q12: 河南酒便利葡萄酒销售额 | R12: 44379852 | S12: 3716238.3 | T12: =S12/R12 -> 0.083737061 | U12: 2314892.3 | V12: =U12/R12 -> 0.052160885
A13: 9 | B13: 101010503 | C13: 52°泸州老窖精品头曲D9 500ml | D13: 500ml*6 | E13: 75 | F13: 7962 | G13: 597150 | H13: 144.86 | I13: 2772 | J13: 401551.92 | K13: 1804 | L13: 261327.44 | M13: 1505 | N13: 218014.3 | Q13: 北京酒便利葡萄酒销售额 | R13: 32833504 | S13: 890240.86 | T13: =S13/R13 -> 0.027113794 | U13: 762937.84 | V13: =U13/R13 -> 0.023236565
A14: 10 | B14: 101010502 | C14: 52°泸州老窖精品头曲D6 500ml | D14: 500ml*6 | E14: 63 | F14: 15606 | G14: 983178 | H14: 94.45 | I14: 2731 | J14: 257942.95 | K14: 718 | L14: 67815.1 | M14: 1235 | N14: 116645.75 | Q14: 西安酒便利葡萄酒销售额 | R14: 4024733 | S14: 486809.32 | T14: =S14/R14 -> 0.12095444 | U14: 360249.09 | V14: =U14/R14 -> 0.089508817
A15: 11 | B15: 101010501 | C15: *42°泸小二FOR ME（彩色）酒125ml | D15: 125ml*24 | E15: 11 | F15: 0 | G15: 0 | H15: 11.93 | I15: 6343 | J15: 75671.99 | K15: 3600 | L15: 42948 | M15: 1564 | N15: 18658.52 | Q15: 徐州酒便利葡萄酒销售额 | R15: 962149.5 | S15: 40479.3 | T15: =S15/R15 -> 0.042071736 | U15: 40479.3 | V15: =U15/R15 -> 0.042071736
A16: 12 | B16: 101010504 | C16: 42°泸州老窖二曲白酒蓝瓶装 500ml | D16: 500ml*6 | E16: 12 | F16: 0 | G16: 0 | H16: 19.93 | I16: 1986 | J16: 39580.98 | K16: 743 | L16: 14807.99 | M16: 767 | N16: 15286.31 | Q16: 总计 | R16: =SUM(R12:R15) -> 82200238 | S16: =SUM(S12:S15) -> 5133767.8 | T16: =SUM(T12:T15) -> 0.27387703 | U16: =SUM(U12:U15) -> 3478558.6 | V16: =SUM(V12:V15) -> 0.206978
A17: 13 | B17: 101010521 | C17: 52°国窖1573曾娜大师鉴藏版500ml | D17: 500ml*6 | E17: 740 | F17: 0 | G17: 0 | H17: 928.61 | I17: 201 | J17: 186650.61 | M17: 82 | N17: 76146.02
A18: 14 | B18: 101010525 | C18: 52°泸州老窖2018农历戊戌年金狗佑财1.088L | D18: 1.088L*3 | E18: 468 | F18: 0 | G18: 0 | H18: 408.05 | I18: 112 | J18: 45701.6 | M18: 25 | N18: 10201.25 | Q18: 区域 | R18: 白酒销量（瓶） | U18: 葡萄酒销量（瓶）
A19: 15 | B19: 101020055 | C19: 52°泸州老窖中秋丁酉年节庆酒1L | D19: 1L*3 | E19: 268 | F19: 0 | G19: 0 | H19: 88.85 | I19: 261 | J19: 23189.85 | K19: 769 | L19: 68325.65 | M19: 46 | N19: 4087.1 | R19: 2017.5.1-2017.10.31 | S19: 2018.5.1-2018.10.31 | T19: 同比 | U19: 2017.5.1-2017.10.31 | V19: 2018.5.1-2018.10.31 | W19: 同比
A20: 16 | B20: 101020063 | C20: 53°国窖国韵1L | D20: 1L*1 | E20: 2220 | F20: 0 | G20: 0 | H20: 2536.98 | I20: 53 | J20: 134459.94 | M20: 49 | N20: 124312.02 | Q20: 河南酒便利 | R20: 46050 | S20: 44387 | T20: =(S20-R20)/R20 -> -0.036112921 | U20: 5524 | V20: 31235 | W20: =(V20-U20)/U20 -> 4.6544171
A21: 17 | B21: 103090047 | C21: *22°桃花醉配制酒（时尚版）500ml | D21: 500ml*6 | E21: 85 | F21: 0 | G21: 0 | Q21: 北京酒便利 | R21: 7163 | S21: 10368 | T21: =(S21-R21)/R21 -> 0.44743822 | U21: 225 | V21: 4799 | W21: =(V21-U21)/U21 -> 20.328889
A22: 18 | B22: 103090048 | C22: *22°桃花醉配制酒（仙侠版）500ml | D22: 500ml*6 | E22: 85 | F22: 0 | G22: 0 | Q22: 西安酒便利 | R22: 2063 | S22: 5377 | T22: =(S22-R22)/R22 -> 1.6063984 | U22: 44 | V22: 3239 | W22: =(V22-U22)/U22 -> 72.613636
A23: 老窖白酒合计 | I23: =SUM(I6:I20) -> 103381 | J23: =SUM(J6:J20) -> 24735880 | K23: =SUM(K6:K20) -> 46050 | L23: =SUM(L6:L20) -> 10617793 | M23: =SUM(M6:M20) -> 44387 | N23: =SUM(N6:N20) -> 10488724 | Q23: 徐州酒便利 | R23: 1 | S23: 287 | T23: =(S23-R23)/R23 -> 286 | U23: 0 | V23: 351 | W23: =(V23-U23)/U23 -> #DIV/0!
A24: 河南酒便利平台白酒合计 | I24: 1869244 | J24: 4.3349845e+08 | Q24: 总计 | R24: =SUM(R20:R23) -> 55277 | S24: =SUM(S20:S23) -> 60419 | T24: =(S24-R24)/R24 -> 0.093022414 | U24: =SUM(U20:U23) -> 5793 | V24: =SUM(V20:V23) -> 39624 | W24: =(V24-U24)/U24 -> 5.8399793
A25: 老窖白酒在河南酒便利占比 | I25: =I23/I24 -> 0.055306316 | J25: =J23/J24 -> 0.057061057
C26: 52°国窖1573 500ml | D26: 500ml*6 | H26: 740 | I26: 13122 | J26: =H26*I26 -> 9710280 | Q26: 区域 | R26: 52°五粮液普装500ml（瓶） | U26: 52°剑南春普装500ml（瓶）
J27: =J26/J24 -> 0.022399803 | R27: 2017.5.1-2017.10.31 | S27: 2018.5.1-2018.10.31 | T27: 同比 | U27: 2017.5.1-2017.10.31 | V27: 2018.5.1-2018.10.31 | W27: 同比
C28: 52°泸州老窖特曲500ml | D28: 500ml*6 | H28: 168 | I28: 46072 | J28: =H28*I28 -> 7740096 | Q28: 河南酒便利 | R28: 29753 | S28: 27101 | T28: =(S28-R28)/R28 -> -0.089133869 | U28: 64698 | V28: 66934 | W28: =(V28-U28)/U28 -> 0.034560574
J29: =J28/J24 -> 0.017854956 | Q29: 北京酒便利 | R29: 3578 | S29: 5622 | T29: =(S29-R29)/R29 -> 0.57126887 | U29: 3662 | V29: 4481 | W29: =(V29-U29)/U29 -> 0.22364828
A30: 竞品信息 | B30: 101010002 | C30: 52°剑南春普装500ml | D30: 500ml*6 | H30: =VLOOKUP(B30,河南!G:I,3,0) -> 379.66 | I30: 145885 | J30: =H30*I30 -> 55386699 | K30: 64698 | L30: 24563243 | M30: 66934 | N30: 25412162 | Q30: 西安酒便利 | R30: 961 | S30: 2603 | T30: =(S30-R30)/R30 -> 1.7086368 | U30: 1089 | V30: 1685 | W30: =(V30-U30)/U30 -> 0.54729109
J31: =J30/J24 -> 0.12776677 | Q31: 徐州酒便利 | R31: 8 | S31: 333 | T31: =(S31-R31)/R31 -> 40.625 | U31: 0 | V31: 100 | W31: =(V31-U31)/U31 -> #DIV/0!
A32: 竞品信息 | B32: 101010001 | C32: 52°五粮液普装500ml | D32: 500ml*6 | H32: =VLOOKUP(B32,河南!G:I,3,0) -> 879.83 | I32: 62803 | J32: =H32*I32 -> 55255963 | K32: 29753 | L32: 26177582 | M32: 27101 | N32: 23844273 | Q32: 总计 | R32: =SUM(R28:R31) -> 34300 | S32: =SUM(S28:S31) -> 35659 | T32: =SUM(T28:T31) -> 42.815772 | U32: =SUM(U28:U31) -> 69449 | V32: =SUM(V28:V31) -> 73200 | W32: =(V32-U32)/U32 -> 0.054010857
J33: =J32/J24 -> 0.12746519
A34: 竞品信息 | B34: 101010004 | C34: 52°洋河天之蓝480ml | D34: 480ml*6 | H34: =VLOOKUP(B34,河南!G:I,3,0) -> 346.05 | I34: 15225 | J34: =H34*I34 -> 5268611.2 | K34: 6887 | L34: 2383246.4 | M34: 7096 | N34: 2455570.8
J35: =J34/J24 -> 0.012153703
A36: 竞品信息 | B36: 101010098 | C36: 52°洋河海之蓝480ml | D36: 480ml*6 | H36: =VLOOKUP(B36,河南!G:I,3,0) -> 145.4 | I36: 106074 | J36: =H36*I36 -> 15423160 | K36: 50409 | L36: =H36*K36 -> 7329468.6 | M36: 47800 | N36: =H36*M36 -> 6950120
J37: =J36/J24 -> 0.03557835
A38: 1 | B38: 104020590 | C38: 舒富红葡萄酒750ml | D38: 750ml*6 | E38: 40.91 | F38: 53298 | G38: 2398410 | H38: 90.42 | I38: 56585 | J38: =E38*I38 -> 2314892.3 | K38: 3133 | L38: 283285.86 | M38: 19866 | N38: 1796283.7
A39: 2 | B39: 104020591 | C39: 希拉谷西拉红葡萄酒750ml | D39: 750ml*6 | E39: 90 | F39: 10008 | G39: 900720 | H39: 161.46 | I39: 14256 | J39: =E39*I39 -> 1283040 | K39: 1601 | L39: 258497.46 | M39: 10846 | N39: 1751195.2
A40: 3 | B40: 104020592 | C40: 希拉谷庄园西拉红葡萄酒750ml | D40: 750ml*6 | E40: 149 | F40: 7800 | G40: 1162200 | H40: 381.29 | I40: 794 | J40: =E40*I40 -> 118306 | K40: 790 | L40: 301219.1 | M40: 523 | N40: 199414.67
A41: 优选葡萄酒合计 | I41: =SUM(I38:I40) -> 71635 | J41: =SUM(J38:J40) -> 3716238.3 | K41: =SUM(K38:K40) -> 5524 | L41: =SUM(L38:L40) -> 843002.42 | M41: =SUM(M38:M40) -> 31235 | N41: =SUM(N38:N40) -> 3746893.5
A42: 酒便利平台葡萄酒合计 | I42: 455885 | J42: 44379852
A43: 优选葡萄酒在酒便利河南占比 | I43: =I41/I42 -> 0.15713393 | J43: =J41/J42 -> 0.083737061
I44: 总计 | J44: =J6+J17+J26 -> 20788978
A45: 全国酒便利周明细—北京
A46: 序号 | B46: 商品编码 | C46: 商品名称 | D46: 规格 | E46: 单价 | F46: 全年计划总量(瓶) | G46: 全年计划采购总金额 | H46: 成交价 | I46: 20171101-20181031 | K46: 20170501-20171031 | M46: 20180501-20181031
I47: 出库数量 | J47: 出库金额 | K47: 出库数量 | L47: 出库金额 | M47: 出库数量 | N47: 出库金额
A48: 1 | B48: 101010397 | C48: 38°国窖1573 500ml | D48: 500ml*6 | E48: 530 | F48: 2880 | G48: 1526400 | H48: 654.03 | I48: 1628 | J48: 1064760.8 | K48: 1174 | L48: 767831.22 | M48: 1121 | N48: 733167.63
A49: 2 | B49: 101010099 | C49: 52°国窖1573 500ml | D49: 500ml*6 | E49: 740 | F49: 4890 | G49: 3618600 | H49: 824.19 | I49: 6445 | J49: 5311904.6 | K49: 1976 | L49: 1628599.4 | M49: 3602 | N49: 2968732.4
A50: 3 | B50: 101010114 | C50: *52°百年泸州老窖酒窖龄30年500ml | D50: 500ml*6 | E50: 165 | F50: 1140 | G50: 188100 | H50: 224.39 | I50: 1115 | J50: 250194.85 | K50: 241 | L50: 54077.99 | M50: 656 | N50: 147199.84
A51: 4 | B51: 101010115 | C51: 52°百年泸州老窖酒窖龄60年500ml | D51: 500ml*6 | E51: 200 | F51: 2640 | G51: 528000 | H51: 260.79 | I51: 2949 | J51: 769069.71 | K51: 782 | L51: 203937.78 | M51: 1387 | N51: 361715.73
A52: 5 | B52: 101010294 | C52: 38°泸州老窖泸州百年30年窖龄500ml | D52: 500ml*6 | E52: 145 | F52: 780 | G52: 113100 | H52: 200.19 | I52: 616 | J52: 123317.04 | K52: 353 | L52: 70667.07 | M52: 329 | N52: 65862.51
A53: 6 | B53: 101010297 | C53: 38°泸州老窖百年60年窖龄500ml | D53: 500ml*6 | E53: 180 | F53: 750 | G53: 135000 | H53: 240.7 | I53: 900 | J53: 216630 | K53: 359 | L53: 86411.3 | M53: 442 | N53: 106389.4
A54: 7 | B54: 101010036 | C54: 52°泸州老窖特曲500ml | D54: 500ml*6 | E54: 168 | F54: 3180 | G54: 534240 | H54: 210.81 | I54: 2451 | J54: 516695.31 | K54: 824 | L54: 173707.44 | M54: 1270 | N54: 267728.7
A55: 8 | B55: 101010024 | C55: 52°泸州老窖头曲500ml | D55: 500ml*6 | E55: 37.87 | F55: 1860 | G55: 70438.2 | H55: 61.43 | I55: 2092 | J55: 128511.56 | K55: 685 | L55: 42079.55 | M55: 1034 | N55: 63518.62
A56: 9 | B56: 101010503 | C56: 52°泸州老窖精品头曲D9 500ml | D56: 500ml*6 | E56: 75 | F56: 300 | G56: 22500
A57: 10 | B57: 101010502 | C57: 52°泸州老窖精品头曲D6 500ml | D57: 500ml*6 | E57: 63 | F57: 240 | G57: 15120
A58: 11 | B58: 101010501 | C58: *42°泸小二FOR ME（彩色）酒125ml | D58: 125ml*24 | E58: 11 | F58: 0 | G58: 0 | H58: 23.48 | I58: 1009 | J58: 23691.32 | K58: 526 | L58: 12350.48 | M58: 446 | N58: 10472.08
A59: 12 | B59: 101010504 | C59: 42°泸州老窖二曲白酒蓝瓶装 500ml | D59: 500ml*6 | E59: 12 | F59: 0 | G59: 0 | K59: 2 | L59: 0 | M59: 17 | N59: 0
A60: 13 | B60: 101010521 | C60: 52°国窖1573曾娜大师鉴藏版500ml | D60: 500ml*6 | E60: 740 | F60: 0 | G60: 0 | H60: 952.33 | I60: 47 | J60: 44759.51 | M60: 47 | N60: 44759.51
A61: 14 | B61: 101010525 | C61: 52°泸州老窖2018农历戊戌年金狗佑财1.088L | D61: 1.088L*3 | E61: 468 | F61: 0 | G61: 0
A62: 15 | B62: 101020055 | C62: 52°泸州老窖中秋丁酉年节庆酒1L | D62: 1L*3 | E62: 268 | F62: 0 | G62: 0 | H62: 376.39 | I62: 32 | J62: 12044.48 | K62: 241 | L62: 90709.99 | M62: 14 | N62: 5269.46
A63: 16 | B63: 101020063 | C63: 53°国窖国韵1L | D63: 1L*1 | E63: 2220 | F63: 0 | G63: 0 | H63: 2918.67 | I63: 3 | J63: 8756.01 | M63: 3 | N63: 8756.01
A64: 17 | B64: 103090047 | C64: *22°桃花醉配制酒（时尚版）500ml | D64: 500ml*6 | E64: 85 | F64: 0 | G64: 0
A65: 18 | B65: 103090048 | C65: *22°桃花醉配制酒（仙侠版）500ml | D65: 500ml*6 | E65: 85 | F65: 0 | G65: 0
A66: 老窖白酒合计 | I66: =SUM(I48:I65) -> 19287 | J66: =SUM(J48:J65) -> 8470335.2 | K66: =SUM(K48:K65) -> 7163 | L66: =SUM(L48:L65) -> 3130372.3 | M66: =SUM(M48:M65) -> 10368 | N66: =SUM(N48:N65) -> 4783571.9
A67: 北京酒便利平台白酒合计 | I67: 520493 | J67: 1.1555258e+08
A68: 老窖白酒北京酒便利占比 | I68: =I66/I67 -> 0.037055253 | J68: =J66/J67 -> 0.073302863
C69: 52°国窖1573 500ml | D69: 500ml*6 | H69: 824.19 | I69: 6445 | J69: =H69*I69 -> 5311904.6
J70: =J69/J67 -> 0.045969587
C71: 52°泸州老窖特曲500ml | D71: 500ml*6 | H71: 210.81 | I71: 2451 | J71: =H71*I71 -> 516695.31
J72: =J71/J67 -> 0.0044715167
A73: 竞品信息 | B73: 101010001 | C73: 52°五粮液普装500ml | D73: 500ml*6 | H73: 920.84 | I73: 10594 | J73: 9755379 | K73: 3578 | L73: 3294765.5 | M73: 5622 | N73: 5176962.5
J74: =J73/J67 -> 0.08442372
A75: 竞品信息 | B75: 101010002 | C75: 52°剑南春普装500ml | D75: 500ml*6 | H75: 405.69 | I75: 8195 | J75: 3324629.5 | K75: 3662 | L75: 1485636.8 | M75: 4481 | N75: 1817896.9
J76: =J75/J67 -> 0.028771573
A77: 竞品信息 | B77: 101010004 | C77: 52°洋河天之蓝480ml | D77: 480ml*6 | H77: 359 | I77: 286 | J77: 102674 | M77: 286 | N77: 102674
J78: =J77/J67 -> 0.00088854786
A79: 1 | B79: 104020590 | C79: 舒富红葡萄酒750ml | D79: 750ml*6 | E79: 40.91 | F79: 2400 | G79: 108000 | H79: 98.98 | I79: 7708 | J79: 762937.84 | K79: 200 | L79: 19796 | M79: 4509 | N79: 446300.82
A80: 2 | B80: 104020591 | C80: 希拉谷西拉红葡萄酒750ml | D80: 750ml*6 | E80: 90 | F80: 780 | G80: 70200 | H80: 230 | I80: 357 | J80: 82110 | K80: 15 | L80: 3450 | M80: 215 | N80: 49450
A81: 3 | B81: 104020592 | C81: 希拉谷庄园西拉红葡萄酒750ml | D81: 750ml*6 | E81: 149 | F81: 480 | G81: 71520 | H81: 396.43 | I81: 114 | J81: 45193.02 | K81: 10 | L81: 3964.3 | M81: 75 | N81: 29732.25
A82: 优选葡萄酒合计 | I82: =SUM(I79:I81) -> 8179 | J82: =SUM(J79:J81) -> 890240.86 | K82: =SUM(K79:K81) -> 225 | L82: =SUM(L79:L81) -> 27210.3 | M82: =SUM(M79:M81) -> 4799 | N82: =SUM(N79:N81) -> 525483.07
A83: 酒便利平台葡萄酒合计 | I83: 279176 | J83: 32833504
A84: 优选葡萄酒在酒便利北京占比 | I84: =I82/I83 -> 0.029296931 | J84: =J82/J83 -> 0.027113794
A86: 全国酒便利周明细—西安
A87: 序号 | B87: 商品编码 | C87: 商品名称 | D87: 规格 | E87: 单价 | F87: 全年计划总量(瓶) | G87: 全年计划采购总金额 | H87: 成交价 | I87: 20171101-20181031 | K87: 20170501-20171031 | M87: 20180501-20181031
I88: 出库数量 | J88: 出库金额 | K88: 出库数量 | L88: 出库金额 | M88: 出库数量 | N88: 出库金额
A89: 1 | B89: 101010397 | C89: 38°国窖1573 500ml | D89: 500ml*6 | E89: 530 | F89: 2880 | G89: 1526400
A90: 2 | B90: 101010099 | C90: 52°国窖1573 500ml | D90: 500ml*6 | E90: 740 | F90: 2760 | G90: 2042400 | H90: 822.69 | I90: 3297 | J90: =H90*I90 -> 2712408.9 | K90: 713 | L90: 586577.97 | M90: 1781 | N90: 1465210.9
A91: 3 | B91: 101010114 | C91: *52°百年泸州老窖酒窖龄30年500ml | D91: 500ml*6 | E91: 165 | F91: 1830 | G91: 301950 | H91: 204.38 | I91: 665 | J91: =H91*I91 -> 135912.7 | K91: 292 | L91: 59678.96 | M91: 313 | N91: 63970.94
A92: 4 | B92: 101010115 | C92: 52°百年泸州老窖酒窖龄60年500ml | D92: 500ml*6 | E92: 200 | F92: 1140 | G92: 228000 | H92: 273.45 | I92: 894 | J92: =H92*I92 -> 244464.3 | K92: 158 | L92: 43205.1 | M92: 404 | N92: 110473.8
A93: 5 | B93: 101010294 | C93: 38°泸州老窖泸州百年30年窖龄500ml | D93: 500ml*6 | E93: 145 | F93: 0 | G93: 0
A94: 6 | B94: 101010297 | C94: 38°泸州老窖百年60年窖龄500ml | D94: 500ml*6 | E94: 180 | F94: 0 | G94: 0
A95: 7 | B95: 101010036 | C95: 52°泸州老窖特曲500ml | D95: 500ml*6 | E95: 168 | F95: 1620 | G95: 272160 | H95: 200.27 | I95: 1581 | J95: =H95*I95 -> 316626.87 | K95: 368 | L95: 73699.36 | M95: 965 | N95: 193260.55
A96: 8 | B96: 101010024 | C96: 52°泸州老窖头曲500ml | D96: 500ml*6 | E96: 37.87 | F96: 990 | G96: 37491.3 | H96: 54.37 | I96: 1476 | J96: =H96*I96 -> 80250.12 | K96: 149 | L96: 8101.13 | M96: 1169 | N96: 63558.53
A97: 9 | B97: 101010503 | C97: 52°泸州老窖精品头曲D9 500ml | D97: 500ml*6 | E97: 75 | F97: 0 | G97: 0
A98: 10 | B98: 101010502 | C98: 52°泸州老窖精品头曲D6 500ml | D98: 500ml*6 | E98: 63 | F98: 0 | G98: 0
A99: 11 | B99: 101010501 | C99: *42°泸小二FOR ME（彩色）酒125ml | D99: 125ml*24 | E99: 11 | F99: 0 | G99: 0 | H99: 17.75 | I99: 1366 | J99: =H99*I99 -> 24246.5 | K99: 306 | L99: 5431.5 | M99: 660 | N99: 11715
A100: 12 | B100: 101010504 | C100: 42°泸州老窖二曲白酒蓝瓶装 500ml | D100: 500ml*6 | E100: 12 | F100: 0 | G100: 0 | H100: 25 | L100: 0 | M100: 17 | N100: 425
A101: 13 | B101: 101010521 | C101: 52°国窖1573曾娜大师鉴藏版500ml | D101: 500ml*6 | E101: 740 | F101: 0 | G101: 0 | H101: 967 | I101: 28 | J101: =H101*I101 -> 27076 | L101: 0 | M101: 28 | N101: 27076
...

Sheet 河南
B2: 商品大类 | C2: 商品类别 | D2: 商品名称 | E2: 规格 | F2: 单位 | G2: 商品编码 | H2: 数量 | I2: 成交均价 | J2: 销售额 | K2: 成本 | L2: 毛利 | M2: 毛利率 | N2: 单品客流量 | O2: 销售门店数
H3: 1821277 | I3: 231.50861 | J3: 4.216413e+08 | K3: 3.524861e+08 | L3: 69155200 | O3: 21350
B4: 白酒 | C4: 白酒-浓香型 | D4: 52°五粮液普装500ml | E4: 500ml*6 | F4: 瓶 | G4: 101010001 | H4: 61601 | I4: 879.83 | J4: 54198683 | K4: 49533919 | L4: 4664763.3 | M4: 0.086 | N4: 14296 | O4: 143
B5: 白酒 | C5: 白酒-浓香型 | D5: 52°剑南春普装500ml | E5: 500ml*6 | F5: 瓶 | G5: 101010002 | H5: 142696 | I5: 379.66 | J5: 54176228 | K5: 49042652 | L5: 5133576.1 | M5: 0.0947 | N5: 38898 | O5: 142
B6: 白酒 | C6: 白酒-酱香型 | D6: 53°飞天茅台酒500ml | E6: 500ml*6 | F6: 瓶 | G6: 101010134 | H6: 32602 | I6: 1479.4 | J6: 48231255 | K6: 45388988 | L6: 2842267.1 | M6: 0.0589 | N6: 5904 | O6: 140
B7: 白酒 | C7: 白酒-浓香型 | D7: 52°五粮液1618 500ml | E7: 500ml*6 | F7: 瓶 | G7: 101010117 | H7: 39916 | I7: 886.42 | J7: 35382307 | K7: 32427773 | L7: 2954533.8 | M7: 0.0835 | N7: 8946 | O7: 143
B8: 白酒 | C8: 白酒其它 | D8: 52°洋河海之蓝480ml | E8: 480ml*6 | F8: 瓶 | G8: 101010098 | H8: 103500 | I8: 145.4 | J8: 15048872 | K8: 12312296 | L8: 2736575.3 | M8: 0.1818 | N8: 41203 | O8: 143
B9: 白酒 | C9: 白酒其它 | D9: 46°+70°仰韶彩陶坊地利(450ml+50ml) | E9: (450ml+50ml)*6 | F9: 瓶 | G9: 101010104 | H9: 68420 | I9: 206.46 | J9: 14125983 | K9: 11402711 | L9: 2723271.7 | M9: 0.1927 | N9: 24179 | O9: 143
B10: 白酒 | C10: 白酒其它 | D10: 46°+70°仰韶彩陶坊人和(450m+50ml） | E10: (450ml+50ml)*6 | F10: 瓶 | G10: 101010105 | H10: 119189 | I10: 110.05 | J10: 13117253 | K10: 9512567.7 | L10: 3604684.9 | M10: 0.2748 | N10: 51819 | O10: 143
B11: 白酒 | C11: 白酒-浓香型 | D11: 52°国窖1573 500ml | E11: 500ml*6 | F11: 瓶 | G11: 101010099 | H11: 12787 | I11: 830.46 | J11: 10619033 | K11: 9380443.9 | L11: 1238589.1 | M11: 0.1166 | N11: 2425 | O11: 140
B12: 白酒 | C12: 白酒-浓香型 | D12: 52°舍得酒500ml（HN） | E12: 500ml*6 | F12: 瓶 | G12: 101010019 | H12: 23597 | I12: 417.53 | J12: 9852416.8 | K12: 8198524.1 | L12: 1653892.7 | M12: 0.1678 | N12: 8260 | O12: 141
B13: 白酒 | C13: 白酒-浓香型 | D13: 52°泸州老窖特曲500ml | E13: 500ml*6 | F13: 瓶 | G13: 101010036 | H13: 45184 | I13: 203.15 | J13: 9178914.9 | K13: 6983414.8 | L13: 2195500.1 | M13: 0.2391 | N13: 14702 | O13: 143
B14: 白酒 | C14: 白酒-酱香型 | D14: 43°飞天茅台500ml | E14: 500ml*6 | F14: 瓶 | G14: 101010158 | H14: 7003 | I14: 932.34 | J14: 6529143.5 | K14: 5084619.6 | L14: 1444523.9 | M14: 0.2212 | N14: 1860 | O14: 129
B15: 白酒 | C15: 白酒-浓香型 | D15: 52°洋河天之蓝480ml | E15: 480ml*6 | F15: 瓶 | G15: 101010004 | H15: 14957 | I15: 346.05 | J15: 5175829 | K15: 4187330.1 | L15: 988498.89 | M15: 0.1909 | N15: 5828 | O15: 143
... B77: 白酒 | C77: 白酒-浓香型 | D77: 52°小糊涂神500ml | E77: 500ml*12 | F77: 瓶 | G77: 101010097 | H77: 8548 | I77: 77.74 | J77: 664501.1 | K77: 494851.52 | L77: 169649.58 | M77: 0.2553 | N77: 4473 | O77: 141
B78: 白酒 | C78: 白酒-酱香型 | D78: 53°赖茅重沙500ml | F78: 瓶 | G78: 101010555 | H78: 2396 | I78: 273.18 | J78: 654542 | K78: 364429.23 | L78: 290112.77 | M78: 0.4432 | N78: 1125 | O78: 125
B79: 白酒 | C79: 白酒-酱香型 | D79: *53°飞天茅台三十年500ml | E79: 500ml*6 | F79: 瓶 | G79: 101010157 | H79: 55 | I79: 11735.73 | J79: 645465 | K79: 543145.5 | L79: 102319.5 | M79: 0.1585 | N79: 22 | O79: 13
B80: 白酒 | C80: 白酒其它 | D80: 40°江小白100ml | E80: 100ml*24 | F80: 瓶 | G80: 101010619 | H80: 33373 | I80: 17.95 | J80: 598911.3 | K80: 391094.31 | L80: 207816.99 | M80: 0.3469 | N80: 10959 | O80: 140
B81: 白酒 | C81: 白酒-浓香型 | D81: 52°百年泸州老窖酒窖龄30年500ml | E81: 500ml*6 | F81: 瓶 | G81: 101010111 | H81: 2715 | I81: 210.86 | J81: 572472.4 | K81: 440937.01 | L81: 131535.39 | M81: 0.2297 | N81: 944 | O81: 131
B82: 白酒 | C82: 白酒-浓香型 | D82: 52°剑南原浆酒500ml | E82: 500ml*6 | F82: 瓶 | G82: 101010561 | H82: 3783 | I82: 147.59 | J82: 558321 | K82: 359663.4 | L82: 198657.6 | M82: 0.3558 | N82: 2233 | O82: 132
B83: 白酒 | C83: 白酒-浓香型 | D83: 52°五粮液六和液盛典装500ml | E83: 500ml*6 | F83: 瓶 | G83: 101010116 | H83: 3954 | I83: 140.64 | J83: 556093 | K83: 424623.83 | L83: 131469.17 | M83: 0.2364 | N83: 1473 | O83: 121
B84: 白酒 | C84: 白酒-酱香型 | D84: 53°茅台王子酒（酱香经典）500ml | E84: 500ml*6 | F84: 瓶 | G84: 101010550 | H84: 2164 | I84: 252.69 | J84: 546831 | K84: 385414.78 | L84: 161416.22 | M84: 0.2951 | N84: 494 | O84: 75
B85: 白酒 | C85: 白酒-浓酱兼香型 | D85: 53°白云边四星陈酿500ml | E85: 500ml*6 | F85: 瓶 | G85: 101010124 | H85: 7221 | I85: 75.28 | J85: 543562.2 | K85: 395867.76 | L85: 147694.44 | M85: 0.2717 | N85: 3901 | O85: 136
B86: 白酒 | C86: 白酒-酱香型 | D86: 53°飞天茅台玫瑰金版500ml | E86: 500ml*6 | F86: 瓶 | G86: 101010544 | H86: 259 | I86: 2046.18 | J86: 529961 | K86: 482679.05 | L86: 47281.95 | M86: 0.0892 | N86: 48 | O86: 25
B87: 白酒 | C87: 白酒-浓香型 | D87: 46°赊店老酒明青花500ml | E87: 500ml*6 | F87: 瓶 | G87: 101010129 | H87: 5536 | I87: 95.72 | J87: 529883.6 | K87: 410560.82 | L87: 119322.78 | M87: 0.2251 | N87: 2778 | O87: 139
B88: 白酒 | C88: 白酒-浓香型 | D88: 52°牛栏山百年陈酿400ml | E88: 400ml*6 | F88: 瓶 | G88: 101010155 | H88: 3709 | I88: 142.48 | J88: 528457.2 | K88: 339330.69 | L88: 189126.51 | M88: 0.3578 | N88: 1801 | O88: 104
B89: 白酒 | C89: 白酒-浓酱兼香型 | D89: 50°白云边五星陈酿500ml | E89: 500ml*6 | F89: 瓶 | G89: 101010139 | H89: 3711 | I89: 135.71 | J89: 503631 | K89: 367438.21 | L89: 136192.79 | M89: 0.2704 | N89: 1831 | O89: 127
B90: 白酒 | C90: 白酒-浓香型 | D90: 52°五粮液戊戌（狗）年生肖纪念酒礼盒 | E90: 500ml*4*1 | F90: 盒 | G90: 101010513 | H90: 406 | I90: 1235.67 | J90: 501682 | K90: 299741.42 | L90: 201940.58 | M90: 0.4025 | N90: 299 | O90: 91
... B131: 白酒 | C131: 白酒-浓酱兼香型 | D131: 45°小郎酒100ml | E131: 100ml*24 | F131: 瓶 | G131: 101010612 | H131: 11313 | I131: 19.79 | J131: 223923.92 | K131: 153561.6 | L131: 70362.323 | M131: 0.3142 | N131: 3520 | O131: 125
B132: 白酒 | C132: 白酒-酱香型 | D132: *53°茅台王子酒（黑金）500ml | F132: 瓶 | G132: 101010568 | H132: 1193 | I132: 186.48 | J132: 222474 | K132: 166013.15 | L132: 56460.846 | M132: 0.2537 | N132: 534 | O132: 84
B133: 白酒 | C133: 白酒-清香型 | D133: 56°炸弹二锅头100ml | E133: 100ml*20 | F133: 瓶 | G133: 101010122 | H133: 33282 | I133: 6.53 | J133: 217248.91 | K133: 129167.7 | L133: 88081.206 | M133: 0.4054 | N133: 6327 | O133: 139
B134: 白酒 | C134: 白酒-浓香型 | D134: 50°五粮醇红淡雅500ml | E134: 500ml*6 | F134: 瓶 | G134: 101010108 | H134: 2900 | I134: 74.41 | J134: 215795 | K134: 173662.77 | L134: 42132.227 | M134: 0.1952 | N134: 1398 | O134: 129
B135: 白酒 | C135: 白酒-清香型 | D135: *43°红星蓝界酒500ml | E135: 500ml*12 | F135: 瓶 | G135: 101010601 | H135: 3188 | I135: 67.46 | J135: 215076 | K135: 124018.98 | L135: 91057.018 | M135: 0.4233 | N135: 1946 | O135: 131
B136: 白酒 | C136: 白酒-酱香型 | D136: 53°老珍酒500ml | E136: 500ml*6 | F136: 瓶 | G136: 101010558 | H136: 2087 | I136: 95.57 | J136: 199453 | K136: 125551.2 | L136: 73901.803 | M136: 0.3705 | N136: 1063 | O136: 75
B137: 白酒 | C137: 白酒其它 | D137: 45°竹叶青酒牧童475ml | E137: 475ml*6 | F137: 瓶 | G137: 101010618 | H137: 3679 | I137: 52.11 | J137: 191702 | K137: 139707.41 | L137: 51994.594 | M137: 0.2712 | N137: 2266 | O137: 134
B138: 白酒 | C138: 白酒-浓香型 | D138: 52°五粮特曲500ml | E138: 500ml*6 | F138: 瓶 | G138: 101010147 | H138: 1005 | I138: 187.38 | J138: 188318 | K138: 142333.74 | L138: 45984.26 | M138: 0.2441 | N138: 327 | O138: 92
B139: 白酒 | C139: 白酒-浓香型 | D139: 52°国窖1573曾娜大师鉴藏版500ml | F139: 瓶 | G139: 101010512 | H139: 200 | I139: 928.26 | J139: 185652 | K139: 148267.13 | L139: 37384.871 | M139: 0.2013 | N139: 29 | O139: 13
B140: 白酒 | C140: 白酒-清香型 | D140: 45°杏花村福酒五(225ml*2) | E140: 225ml*2*6 | F140: 盒 | G140: 101010072 | H140: 3082 | I140: 57.6 | J140: 177538 | K140: 107619.47 | L140: 69918.534 | M140: 0.3938 | N140: 2006 | O140: 132
B141: 白酒 | C141: 白酒-浓香型 | D141: 42°百泉春特制珍品长寿酒500ml | E141: 500ml*4 | F141: 瓶 | G141: 101010181 | H141: 1910 | I141: 84.96 | J141: 162270 | K141: 139822.62 | L141: 22447.38 | M141: 0.1383 | N141: 821 | O141: 9
B142: 白酒 | C142: 白酒-清香型 | D142: 50°汾阳王20年500ml | E142: 500ml*6 | F142: 瓶 | G142: 101010606 | H142: 1002 | I142: 159.65 | J142: 159965 | K142: 71585.4 | L142: 88379.6 | M142: 0.5524 | N142: 324 | O142: 90
B143: 白酒 | C143: 白酒其它 | D143: 52°酒鬼酒（无上妙品）500ml | E143: 500ml*6 | F143: 瓶 | G143: 101010631 | H143: 472 | I143: 336.91 | J143: 159020 | K143: 108266.52 | L143: 50753.484 | M143: 0.3191 | N143: 217 | O143: 63
B144: 白酒 | C144: 白酒-浓香型 | D144: *52°泸州窖酒窖之绵500ml | E144: 500ml*6 | F144: 瓶 | G144: 101010534 | H144: 1591 | I144: 97.71 | J144: 155458 | K144: 107898.05 | L144: 47559.955 | M144: 0.3059 | N144: 766 | O144: 121
B145: 白酒 | C145: 白酒-浓香型 | D145: 52°尖庄曲酒450ml*2双瓶礼盒 | E145: 450ml*2*6 | F145: 瓶 | G145: 101010179 | H145: 2479 | I145: 61.67 | J145: 152884 | K145: 103786.04 | L145: 49097.956 | M145: 0.3211 | N145: 1818 | O145: 130
B146: 白酒 | C146: 白酒-酱香型 | D146: *53°茅台王子酒酱品500ml | E146: 500ml*6 | F146: 瓶 | G146: 101010547 | H146: 720 | I146: 211.64 | J146: 152380 | K146: 81959.992 | L146: 70420.008 | M146: 0.4621 | N146: 360 | O146: 66
B147: 白酒 | C147: 白酒-清香型 | D147: 56°牛栏山裸瓶500ml | E147: 500ml*12 | F147: 瓶 | G147: 101010121 | H147: 12937 | I147: 11.5 | J147: 148751.5 | K147: 113048.31 | L147: 35703.19 | M147: 0.24 | N147: 5039 | O147: 140
B148: 白酒 | C148: 白酒-酱香型 | D148: 53°飞天茅台猴年500ml | F148: 瓶 | G148: 101010567 | H148: 30 | I148: 4866.47 | J148: 145994 | K148: 109290 | L148: 36704 | M148: 0.2514 | N148: 10 | O148: 10
B149: 白酒 | C149: 白酒-浓香型 | D149: 52°珍品级绵竹大曲蓝盒475ml | E149: 475ml*6 | F149: 瓶 | G149: 101010162 | H149: 2166 | I149: 65.5 | J149: 141874.2 | K149: 75256.971 | L149: 66617.228 | M149: 0.4695 | N149: 992 | O149: 132
B150: 白酒 | C150: 白酒-浓香型 | D150: 50°白云边九象6号500ml | E150: 500ml*6 | F150: 瓶 | G150: 101010533 | H150: 1659 | I150: 84.95 | J150: 140931 | K150: 85047.065 | L150: 55883.935 | M150: 0.3965 | N150: 978 | O150: 99
B151: 白酒 | C151: 白酒-浓香型 | D151: 52°金剑南鉴藏500ml | E151: 500ml*6 | F151: 瓶 | G151: 101010198 | H151: 632 | I151: 222.07 | J151: 140346 | K151: 99141.101 | L151: 41204.899 | M151: 0.2935 | N151: 239 | O151: 75
B152: 白酒 | C152: 白酒其它 | D152: 35°中国劲酒258ml | E152: 258ml*15 | F152: 瓶 | G152: 101010120 | H152: 6007 | I152: 23 | J152: 138149.3 | K152: 106421.7 | L152: 31727.603 | M152: 0.2296 | N152: 3613 | O152: 100
B153: 白酒 | C153: 白酒-酱香型 | D153: 53°茅台仁酒500ml | E153: 500ml*6 | F153: 瓶 | G153: 101010138 | H153: 408 | I153: 323.58 | J153: 132022 | K153: 89760 | L153: 42262 | M153: 0.3201 | N153: 192 | O153: 62
B154: 白酒 | C154: 白酒-酱香型 | D154: 53°珍酒珍十五500ml | F154: 瓶 | G154: 101010557 | H154: 223 | I154: 586.98 | J154: 130896 | K154: 81504.9 | L154: 49391.1 | M154: 0.3773 | N154: 106 | O154: 45
B155: 白酒 | C155: 白酒-清香型 | D155: 53°红星八年陈酿蓝瓶二锅头250ml | E155: 250ml*24 | F155: 瓶 | G155: 101010596 | H155: 8127 | I155: 15.99 | J155: 129961.2 | K155: 95301.865 | L155: 34659.335 | M155: 0.2666 | N155: 6652 | O155: 136
B156: 白酒 | C156: 白酒-清香型 | D156: 38°竹叶青酒金象500ml | E156: 500ml*6 | F156: 瓶 | G156: 101010075 | H156: 1465 | I156: 87.24 | J156: 127801.5 | K156: 87059.618 | L156: 40741.882 | M156: 0.3187 | N156: 787 | O156: 126
B157: 白酒 | C157: 白酒-浓香型 | D157: 50°五粮液五粮人家家酿500ml | E157: 500ml*6 | F157: 瓶 | G157: 101010161 | H157: 790 | I157: 161.51 | J157: 127593 | K157: 68392.501 | L157: 59200.499 | M157: 0.4639 | N157: 579 | O157: 75
B158: 白酒 | C158: 白酒-浓香型 | D158: 53°国窖国韵1L | F158: 瓶 | G158: 101010560 | H158: 50 | I158: 2551.2 | J158: 127560 | K158: 105627.37 | L158: 21932.635 | M158: 0.1719 | N158: 22 | O158: 15
B159: 白酒 | C159: 白酒-浓香型 | D159: 46°赊店15 元青花500ml | E159: 500ml*6 | F159: 瓶 | G159: 101010495 | H159: 356 | I159: 356.56 | J159: 126936 | K159: 88295.429 | L159: 38640.571 | M159: 0.3044 | N159: 86 | O159: 36
B160: 白酒 | C160: 白酒-浓香型 | D160: 50°五粮春500ml | E160: 500ml*6 | F160: 瓶 | G160: 101010492 | H160: 633 | I160: 191.52 | J160: 121232 | K160: 99729.435 | L160: 21502.565 | M160: 0.1773 | N160: 134 | O160: 12
B161: 白酒 | C161: 白酒其它 | D161: 54°湘泉盒优500ml | E161: 500ml*6 | F161: 瓶 | G161: 101010193 | H161: 3357 | I161: 34.63 | J161: 116268 | K161: 69604.514 | L161: 46663.486 | M161: 0.4013 | N161: 1645 | O161: 132
B162: 白酒 | C162: 白酒-浓香型 | D162: 52°五粮液丁酉（鸡）年生肖纪念酒礼盒 | E162: 500ml*4*1 | F162: 盒 | G162: 101010514 | H162: 101 | I162: 1135.16 | J162: 114651 | K162: 63905.907 | L162: 50745.093 | M162: 0.4426 | N162: 82 | O162: 48
B163: 白酒 | C163: 白酒-浓香型 | D163: 46°双沟大曲500ml | E163: 500ml*6 | F163: 瓶 | G163: 101010084 | H163: 2855 | I163: 40.07 | J163: 114389 | K163: 78309.553 | L163: 36079.448 | M163: 0.3154 | N163: 1579 | O163: 132
B164: 白酒 | C164: 白酒-浓香型 | D164: 52°洋河特曲（珠光金）500ml | E164: 500ml*6 | F164: 盒 | G164: 101010489 | H164: 683 | I164: 166.13 | J164: 113464 | K164: 87299.788 | L164: 26164.212 | M164: 0.2305 | N164: 376 | O164: 92
B165: 白酒 | C165: 白酒-酱香型 | D165: 53°茅台迎宾酒（中国红）500ml | E165: 500ml*6 | F165: 瓶 | G165: 101010576 | H165: 720 | I165: 150.06 | J165: 108041 | K165: 62732.937 | L165: 45308.063 | M165: 0.4193 | N165: 314 | O165: 69
B166: 白酒 | C166: 白酒-浓香型 | D166: 52°剑南春鸡年吉祥500ml | F166: 瓶 | G166: 101010508 | H166: 151 | I166: 684.58 | J166: 103372 | K166: 73382.436 | L166: 29989.564 | M166: 0.2901 | N166: 61 | O166: 45
B167: 白酒 | C167: 白酒-酱香型 | D167: 53°飞天茅台酒 50ml*2 | E167: 50ml*2*30 | F167: 盒 | G167: 101010538 | H167: 185 | I167: 546.73 | J167: 101145 | K167: 82060 | L167: 19085 | M167: 0.1886 | N167: 43 | O167: 28
B168: 白酒 | C168: 白酒-浓香型 | D168: 45°五粮春500ml | E168: 500ml*12 | F168: 瓶 | G168: 101010153 | H168: 628 | I168: 154.2 | J168: 96840 | K168: 86560.961 | L168: 10279.039 | M168: 0.1061 | N168: 141 | O168: 10
B169: 白酒 | C169: 白酒-浓香型 | D169: *52°剑南春珍藏级特酿500ml | E169: 500ml*6 | F169: 瓶 | G169: 101010148 | H169: 204 | I169: 471.76 | J169: 96240 | K169: 89270 | L169: 6970 | M169: 0.0724 | N169: 3 | O169: 1
B170: 白酒 | C170: 白酒-凤香型 | D170: 52°西凤凤香经典10年500ml | E170: 500ml*6 | F170: 瓶 | G170: 101010141 | H170: 294 | I170: 312.07 | J170: 91748 | K170: 61555.508 | L170: 30192.492 | M170: 0.329 | N170: 122 | O170: 53
B171: 白酒 | C171: 白酒-清香型 | D171: 52°牛栏山经典二锅头500ml | E171: 500ml*6 | F171: 瓶 | G171: 101010154 | H171: 223 | I171: 387.08 | J171: 86318 | K171: 70821.406 | L171: 15496.594 | M171: 0.1795 | N171: 70 | O171: 29
B172: 白酒 | C172: 白酒-浓香型 | D172: 52°尖庄曲酒300ml | E172: 300ml*20 | F172: 瓶 | G172: 101010183 | H172: 4168 | I172: 19.77 | J172: 82410.4 | K172: 54073.74 | L172: 28336.661 | M172: 0.3438 | N172: 3026 | O172: 124
B173: 白酒 | C173: 白酒-清香型 | D173: 46°天佑德青稞酒柔和R3 500ml | E173: 500ml*6 | F173: 瓶 | G173: 101010607 | H173: 559 | I173: 144.46 | J173: 80752 | K173: 57077.063 | L173: 23674.937 | M173: 0.2931 | N173: 234 | O173: 60
B174: 白酒 | C174: 白酒-浓香型 | D174: 52°文君礼盒套装500ml+100ml | E174: 500ml+100ml*6 | F174: 盒 | G174: 101010527 | H174: 154 | I174: 510.86 | J174: 78672 | K174: 63362.563 | L174: 15309.437 | M174: 0.1945 | N174: 84 | O174: 44
B175: 白酒 | C175: 白酒-酱香型 | D175: 53°茅台（飞天）迎宾酒500ml | E175: 500ml*6 | F175: 瓶 | G175: 101010584 | H175: 195 | I175: 400.57 | J175: 78111 | K175: 75660 | L175: 2451 | M175: 0.0313 | N175: 9 | O175: 5
B176: 白酒 | C176: 白酒-浓香型 | D176: 52°吴窖银樽酒500ml | E176: 500ml*6 | F176: 瓶 | G176: 101010511 | H176: 251 | I176: 308.77 | J176: 77502 | K176: 42959.797 | L176: 34542.203 | M176: 0.4456 | N176: 95 | O176: 45
B177: 白酒 | C177: 白酒-浓香型 | D177: *42°泸小二FOR ME（彩色）酒125ml | E177: 125ml*24 | F177: 瓶 | G177: 101010499 | H177: 6296 | I177: 11.89 | J177: 74872.5 | K177: 79020.867 | L177: -4148.367 | M177: -0.0554 | N177: 3934 | O177: 124
B178: 白酒 | C178: 白酒-酱香型 | D178: 53°仁酒·和天下 500ml | E178: 500ml*6 | F178: 瓶 | G178: 101010589 | H178: 200 | I178: 373.41 | J178: 74682 | K178: 43060 | L178: 31622 | M178: 0.4234 | N178: 54 | O178: 36
... B191: 白酒 | C191: 白酒-浓香型 | D191: 42°百泉春龙寿酒礼盒500ml*2 | E191: 1*1 | F191: 盒 | G191: 101010182 | H191: 128 | I191: 388 | J191: 49664 | K191: 42227.763 | L191: 7436.2367 | M191: 0.1497 | N191: 87 | O191: 8
B192: 白酒 | C192: 白酒-浓香型 | D192: 52°文君戊戌狗年纪念酒1.5L | F192: 瓶 | G192: 101010507 | H192: 130 | I192: 364.23 | J192: 47350 | K192: 84276.001 | L192: -36926.001 | M192: -0.7798 | N192: 105 | O192: 53
B193: 白酒 | C193: 白酒-酱香型 | D193: 53°贵州大曲酒（戊戌狗年）2.5L | E193: 2.5L*1 | F193: 瓶 | G193: 101010587 | H193: 31 | I193: 1524.26 | J193: 47252 | K193: 33172 | L193: 14080 | M193: 0.2979 | N193: 19 | O193: 14
B194: 白酒 | C194: 白酒-浓香型 | D194: 46°赊店小红檀500ml | E194: 500ml*6 | F194: 瓶 | G194: 101010497 | H194: 841 | I194: 55.75 | J194: 46886 | K194: 38152.861 | L194: 8733.139 | M194: 0.1862 | N194: 325 | O194: 11
B195: 白酒 | C195: 白酒-浓香型 | D195: 50°白云边九象3号500ml | E195: 500ml*6 | F195: 瓶 | G195: 101010532 | H195: 760 | I195: 61.06 | J195: 46405 | K195: 26389.532 | L195: 20015.468 | M195: 0.4313 | N195: 356 | O195: 103
B196: 白酒 | C196: 白酒-浓香型 | D196: 52°泸州老窖2018农历戊戌年金狗佑财1.088L | E196: 1.088L*3 | F196: 瓶 | G196: 101010515 | H196: 112 | I196: 408.05 | J196: 45702 | K196: 52767.556 | L196: -7065.5556 | M196: -0.1546 | N196: 54 | O196: 34
B197: 白酒 | C197: 白酒-浓香型 | D197: 46°赊店大红檀500ml | E197: 500ml*6 | F197: 瓶 | G197: 101010498 | H197: 568 | I197: 78.57 | J197: 44626 | K197: 35348.748 | L197: 9277.2523 | M197: 0.2078 | N197: 200 | O197: 12
B198: 白酒 | C198: 白酒-浓香型 | D198: 51.8°信阳名片酒480ml | E198: 480ml*6 | F198: 瓶 | G198: 101010504 | H198: 246 | I198: 180.39 | J198: 44376 | K198: 33096.923 | L198: 11279.077 | M198: 0.2541 | N198: 76 | O198: 7
B199: 白酒 | C199: 白酒其它 | D199: 42°毛铺苦荞酒125ml | E199: 125ml*24 | F199: 瓶 | G199: 101010630 | H199: 2476 | I199: 16.98 | J199: 42045 | K199: 23424.581 | L199: 18620.419 | M199: 0.4428 | N199: 1425 | O199: 113
B200: 白酒 | C200: 白酒-浓香型 | D200: 52°纯粮经典绵竹大曲（袋装）500ml | E200: 500ml*12 | F200: 瓶 | G200: 101010187 | H200: 2656 | I200: 15.73 | J200: 41771.4 | K200: 29132.115 | L200: 12639.285 | M200: 0.3025 | N200: 1107 | O200: 114
B201: 白酒 | C201: 白酒其它 | D201: 46°口子窖六年450ml | E201: 450ml *6 | F201: 瓶 | G201: 101010192 | H201: 294 | I201: 138.73 | J201: 40788 | K201: 33508.534 | L201: 7279.4658 | M201: 0.1784 | N201: 104 | O201: 8
B202: 白酒 | C202: 白酒 | D202: 52°仰韶窖香鸿运500ml | F202: 瓶 | G202: 101010566 | H202: 598 | I202: 67.63 | J202: 40440 | K202: 21954.207 | L202: 18485.793 | M202: 0.4571 | N202: 344 | O202: 89
B203: 白酒 | C203: 白酒-酱香型 | D203: 53°迎囍酒（金标）500ml | E203: 500ml*6 | F203: 瓶 | G203: 101010541 | H203: 410 | I203: 94.55 | J203: 38767 | K203: 26543.176 | L203: 12223.824 | M203: 0.3153 | N203: 69 | O203: 48
B204: 白酒 | C204: 白酒-浓香型 | D204: *42°泸州老窖二曲白酒蓝瓶装 500ml | E204: 500ml*6 | F204: 瓶 | G204: 101010502 | H204: 1887 | I204: 20.2 | J204: 38111 | K204: 24013.189 | L204: 14097.811 | M204: 0.3699 | N204: 1015 | O204: 110
B205: 白酒 | C205: 白酒 | D205: 52°仰韶窖香红瓷500ml | F205: 瓶 | G205: 101010565 | H205: 386 | I205: 97.67 | J205: 37702 | K205: 22148.921 | L205: 15553.079 | M205: 0.4125 | N205: 203 | O205: 73
B206: 白酒 | C206: 白酒-浓香型 | D206: *46°洋河海之蓝480ml | E206: 480ml*6 | F206: 瓶 | G206: 101010003 | H206: 272 | I206: 134.66 | J206: 36628 | K206: 30960.117 | L206: 5667.8835 | M206: 0.1547 | N206: 116 | O206: 11
B207: 白酒 | C207: 白酒-浓香型 | D207: 60°国窖1573酒国韵5L | F207: 瓶 | G207: 101010503 | H207: 2 | I207: 18000 | J207: 36000 | K207: 31000 | L207: 5000 | M207: 0.1388 | N207: 1 | O207: 1
B208: 白酒 | C208: 白酒-酱香型 | D208: 53°贵州茅台酒（澳门回归18年纪念）5L | E208: 5L*1 | F208: 盒 | G208: 101010591 | H208: 1 | I208: 36000 | J208: 36000 | K208: 33500 | L208: 2500 | M208: 0.0694 | N208: 1 | O208: 1
B209: 白酒 | C209: 白酒-酱香型 | D209: 53°贵州茅台酒（澳门回归18年纪念）陈酿5L | E209: 5L*1 | F209: 盒 | G209: 101010592 | H209: 1 | I209: 36000 | J209: 36000 | K209: 33500 | L209: 2500 | M209: 0.0694 | N209: 1 | O209: 1
B210: 白酒 | C210: 白酒-浓香型 | D210: 52°双沟君坊红2号500ml | E210: 500ml*6 | F210: 瓶 | G210: 101010165 | H210: 408 | I210: 86.29 | J210: 35207 | K210: 28214.936 | L210: 6992.0642 | M210: 0.1985 | N210: 241 | O210: 88
B211: 白酒 | C211: 白酒-清香型 | D211: 52°一同发财台湾高粱酒瓷瓶精装300ml | E211: 300ml*16 | F211: 瓶 | G211: 101010599 | H211: 202 | I211: 171.21 | J211: 34584 | K211: 23806.821 | L211: 10777.179 | M211: 0.3116 | N211: 66 | O211: 38
B212: 白酒 | C212: 白酒-浓香型 | D212: 50°古井贡酒红运H3 500ml | E212: 500ml*6 | F212: 瓶 | G212: 101010178 | H212: 407 | I212: 83.97 | J212: 34175 | K212: 20869.5 | L212: 13305.5 | M212: 0.3893 | N212: 191 | O212: 77
B213: 白酒 | C213: 白酒-清香型 | D213: 52°一同发财台湾高粱酒（大三元/一路发）礼盒300ml*3 | E213: 300ml*3*6 | F213: 盒 | G213: 101010604 | H213: 52 | I213: 657.15 | J213: 34172 | K213: 18642.581 | L213: 15529.419 | M213: 0.4544 | N213: 22 | O213: 13
B214: 白酒 | C214: 白酒-酱香型 | D214: 53°仁怀酱香酒-仁之义500ml | E214: 500ml*6 | F214: 瓶 | G214: 101010581 | H214: 68 | I214: 500.88 | J214: 34060 | K214: 12052 | L214: 22008 | M214: 0.6461 | N214: 17 | O214: 15
...

Sheet 北京
B2: 商品大类 | C2: 商品类别 | D2: 商品名称 | E2: 规格 | F2: 单位 | G2: 商品编码 | H2: 数量 | I2: 成交均价 | J2: 销售额 | K2: 成本 | L2: 毛利 | M2: 毛利率 | N2: 单品客流量 | O2: 销售门店数
H3: 507761 | I3: 222.73173 | J3: 1.1309449e+08 | K3: 95648860 | L3: 17445628 | O3: 11114
B4: 白酒 | C4: 白酒-酱香型 | D4: 53°飞天茅台酒500ml | E4: 500ml*6 | F4: 瓶 | G4: 101010185 | H4: 17566 | I4: 1487.71 | J4: 26133088 | K4: 24438514 | L4: 1694574.3 | M4: 0.0648 | N4: 4039 | O4: 69
B5: 白酒 | C5: 白酒-浓香型 | D5: 52°五粮液普装500ml | E5: 500ml*6 | F5: 瓶 | G5: 101010001 | H5: 10465 | I5: 920.84 | J5: 9636620 | K5: 8425480.9 | L5: 1211139.1 | M5: 0.1256 | N5: 3262 | O5: 81
B6: 白酒 | C6: 白酒-浓香型 | D6: 52°国窖1573 500ml | E6: 500ml*6 | F6: 瓶 | G6: 101010099 | H6: 6344 | I6: 824.19 | J6: 5228661 | K6: 4639409.3 | L6: 589251.69 | M6: 0.1126 | N6: 1714 | O6: 79
B7: 白酒 | C7: 白酒-浓香型 | D7: 52°牛栏山百年陈酿400ml | E7: 400ml*6 | F7: 瓶 | G7: 101010282 | H7: 42416 | I7: 104.26 | J7: 4422122 | K7: 3807479.9 | L7: 614642.06 | M7: 0.1389 | N7: 14594 | O7: 84
B8: 白酒 | C8: 白酒-浓香型 | D8: 36°牛栏山百年陈酿400ml | E8: 400ml*6 | F8: 瓶 | G8: 101010277 | H8: 36043 | I8: 97.14 | J8: 3501051 | K8: 3125683.7 | L8: 375367.27 | M8: 0.1072 | N8: 12034 | O8: 84
B9: 白酒 | C9: 白酒-浓香型 | D9: 52°五粮液1618 500ml | E9: 500ml*6 | F9: 瓶 | G9: 101010139 | H9: 3675 | I9: 918.27 | J9: 3374659 | K9: 2917462.7 | L9: 457196.34 | M9: 0.1354 | N9: 1245 | O9: 78
B10: 白酒 | C10: 白酒-浓香型 | D10: 52°剑南春普装500ml | E10: 500ml*6 | F10: 瓶 | G10: 101010002 | H10: 8040 | I10: 405.69 | J10: 3261717 | K10: 2752154.3 | L10: 509562.7 | M10: 0.1562 | N10: 3024 | O10: 81
B11: 白酒 | C11: 白酒-清香型 | D11: 52°牛栏山经典二锅头500ml | E11: 500ml*6 | F11: 瓶 | G11: 101010281 | H11: 7499 | I11: 389.57 | J11: 2921388 | K11: 2362765.7 | L11: 558622.33 | M11: 0.1912 | N11: 2313 | O11: 78
B12: 白酒 | C12: 白酒-清香型 | D12: 53°牛栏山三十年珍品二锅头500ml | E12: 500ml*6 | F12: 瓶 | G12: 101010278 | H12: 11702 | I12: 176.32 | J12: 2063246.8 | K12: 1847811 | L12: 215435.77 | M12: 0.1044 | N12: 4095 | O12: 79
B13: 白酒 | C13: 白酒-清香型 | D13: 53°汾酒20年青花500ml | E13: 500ml*6 | F13: 瓶 | G13: 101010192 | H13: 4773 | I13: 414.55 | J13: 1978671 | K13: 1656455.4 | L13: 322215.64 | M13: 0.1628 | N13: 1598 | O13: 80
B14: 白酒 | C14: 白酒-酱香型 | D14: 43°飞天茅台500ml | E14: 500ml*6 | F14: 瓶 | G14: 101010290 | H14: 2021 | I14: 939.09 | J14: 1897902 | K14: 1368711.4 | L14: 529190.59 | M14: 0.2788 | N14: 896 | O14: 72
B15: 白酒 | C15: 白酒-酱香型 | D15: 53°飞天茅台酒1L | E15: 1L*12 | F15: 瓶 | G15: 101020029 | H15: 480 | I15: 3950.84 | J15: 1896404 | K15: 1754282.4 | L15: 142121.61 | M15: 0.0749 | N15: 292 | O15: 51
... B45: 白酒 | C45: 白酒-浓香型 | D45: 52°泸州老窖特曲500ml | E45: 500ml*6 | F45: 瓶 | G45: 101010036 | H45: 2387 | I45: 210.81 | J45: 503192 | K45: 367065.15 | L45: 136126.85 | M45: 0.2705 | N45: 986 | O45: 76
B46: 白酒 | C46: 白酒-清香型 | D46: 43°红星蓝瓶八年陈酿750ml | F46: 瓶 | G46: 101030004 | H46: 13968 | I46: 35.42 | J46: 494797.5 | K46: 406611.46 | L46: 88186.044 | M46: 0.1782 | N46: 7839 | O46: 83
B47: 白酒 | C47: 白酒-浓香型 | D47: 52°小糊涂仙500ml | E47: 500ml*12 | F47: 瓶 | G47: 101010096 | H47: 2814 | I47: 165.53 | J47: 465808 | K47: 340599.48 | L47: 125208.52 | M47: 0.2687 | N47: 1502 | O47: 80
B48: 白酒 | C48: 白酒-浓香型 | D48: 38°剑南春500ml | E48: 500ml*6 | F48: 瓶 | G48: 101010306 | H48: 1195 | I48: 386.31 | J48: 461646 | K48: 345982.93 | L48: 115663.07 | M48: 0.2505 | N48: 452 | O48: 64
B49: 白酒 | C49: 白酒-浓香型 | D49: 39°五粮液1618 500ml | E49: 500ml*6 | F49: 瓶 | G49: 101010260 | H49: 685 | I49: 670.24 | J49: 459112 | K49: 352967.31 | L49: 106144.69 | M49: 0.2311 | N49: 239 | O49: 61
B50: 白酒 | C50: 白酒-清香型 | D50: 43°红星蓝瓶八年陈酿500ml | E50: 500ml*12 | F50: 瓶 | G50: 101010309 | H50: 16756 | I50: 25.36 | J50: 424880.4 | K50: 352161.96 | L50: 72718.442 | M50: 0.1711 | N50: 8667 | O50: 83
B51: 白酒 | C51: 白酒-酱香型 | D51: 53°习酒窖藏1988 500ml | E51: 500ml*6 | F51: 瓶 | G51: 101020053 | H51: 632 | I51: 639.18 | J51: 403964 | K51: 327866.02 | L51: 76097.977 | M51: 0.1883 | N51: 223 | O51: 60
B52: 白酒 | C52: 白酒-清香型 | D52: 53°老白汾酒封坛拾伍年475ml | E52: 475ml*6 | F52: 瓶 | G52: 101010113 | H52: 2093 | I52: 190.43 | J52: 398564 | K52: 277576.28 | L52: 120987.72 | M52: 0.3035 | N52: 967 | O52: 74
B53: 白酒 | C53: 白酒-浓香型 | D53: 52°舍得酒500ml（BJ） | E53: 500ml*6 | F53: 瓶 | G53: 101010263 | H53: 906 | I53: 411.83 | J53: 373120 | K53: 311003.71 | L53: 62116.289 | M53: 0.1664 | N53: 357 | O53: 63
B54: 白酒 | C54: 白酒-酱香型 | D54: 53°习酒银质500ml | E54: 500ml*6 | F54: 瓶 | G54: 101020010 | H54: 2516 | I54: 144.42 | J54: 363351 | K54: 242153.51 | L54: 121197.49 | M54: 0.3335 | N54: 1242 | O54: 78
B55: 白酒 | C55: 白酒其它 | D55: 40°江小白300ml | E55: 300ml*12 | F55: 瓶 | G55: 101990010 | H55: 8427 | I55: 42.55 | J55: 358594.3 | K55: 270239.72 | L55: 88354.579 | M55: 0.2463 | N55: 4306 | O55: 81
B56: 白酒 | C56: 白酒-清香型 | D56: 霸王醉典藏礼盒250ml*2 | E56: 250ml*2*5 | F56: 瓶 | G56: 101030026 | H56: 345 | I56: 1030.69 | J56: 355588 | K56: 326726.92 | L56: 28861.078 | M56: 0.0811 | N56: 29 | O56: 12
B57: 白酒 | C57: 白酒-酱香型 | D57: 53°茅台王子酒500ml | E57: 500ml*6 | F57: 瓶 | G57: 101010107 | H57: 2428 | I57: 143.79 | J57: 349122 | K57: 247993.97 | L57: 101128.03 | M57: 0.2896 | N57: 1320 | O57: 80
B58: 白酒 | C58: 白酒-浓香型 | D58: 38°牛栏山百年红十年500ml | E58: 500ml*6 | F58: 瓶 | G58: 101010272 | H58: 4710 | I58: 71.63 | J58: 337386 | K58: 310534.26 | L58: 26851.743 | M58: 0.0795 | N58: 1627 | O58: 80
... B62: 白酒 | C62: 白酒-清香型 | D62: 52°红星青花瓷珍品二锅头750ml | E62: 750ml*6 | F62: 瓶 | G62: 101010321 | H62: 1070 | I62: 281.96 | J62: 301695 | K62: 206347.77 | L62: 95347.234 | M62: 0.316 | N62: 506 | O62: 70
B63: 白酒 | C63: 白酒-酱香型 | D63: 53°飞天茅台狗年500ml | F63: 瓶 | G63: 101020101 | H63: 66 | I63: 4533.18 | J63: 299190 | K63: 266535.84 | L63: 32654.16 | M63: 0.1091 | N63: 29 | O63: 12
B64: 白酒 | C64: 白酒-清香型 | D64: 53°汾酒紫砂陶475ml | E64: 475ml*6 | F64: 瓶 | G64: 101010070 | H64: 2945 | I64: 98.27 | J64: 289394 | K64: 196298.74 | L64: 93095.257 | M64: 0.3216 | N64: 1452 | O64: 81
B65: 白酒 | C65: 白酒-酱香型 | D65: 53°赖茅重沙500ml | F65: 瓶 | G65: 101020056 | H65: 1107 | I65: 255.41 | J65: 282740 | K65: 170772.9 | L65: 111967.1 | M65: 0.396 | N65: 484 | O65: 68
B66: 白酒 | C66: 白酒-清香型 | D66: 45°牛栏山珍品二锅头400ml | E66: 400ml*6 | F66: 瓶 | G66: 101010270 | H66: 6086 | I66: 44.98 | J66: 273753.86 | K66: 221954.55 | L66: 51799.31 | M66: 0.1892 | N66: 2291 | O66: 82
B67: 白酒 | C67: 白酒-浓香型 | D67: 52°泸州窖酒陶坛老酒500ml | E67: 500ml*6 | F67: 瓶 | G67: 101010421 | H67: 1579 | I67: 168 | J67: 265272 | K67: 141815.9 | L67: 123456.1 | M67: 0.4653 | N67: 994 | O67: 77
B68: 白酒 | C68: 白酒-清香型 | D68: 53°清香至尊蓝瓷汾酒475ml | E68: 475ml*6 | F68: 瓶 | G68: 101010337 | H68: 2238 | I68: 118.02 | J68: 264124 | K68: 186458.82 | L68: 77665.176 | M68: 0.294 | N68: 983 | O68: 73
B69: 白酒 | C69: 白酒-清香型 | D69: 53°汾酒475ml | E69: 475ml*12 | F69: 瓶 | G69: 999010016 | H69: 5493 | I69: 45.84 | J69: 251803 | K69: 159221.39 | L69: 92581.608 | M69: 0.3676 | N69: 2979 | O69: 78
B70: 白酒 | C70: 白酒-清香型 | D70: 46°北京二锅头酒（土豪金版）500ml | E70: 500ml*6 | F70: 瓶 | G70: 101030043 | H70: 2246 | I70: 111.99 | J70: 251530 | K70: 131114.19 | L70: 120415.81 | M70: 0.4787 | N70: 1069 | O70: 77
B71: 白酒 | C71: 白酒其它 | D71: 52°洋河梦之蓝M6 500ml | E71: 500ml*4 | F71: 瓶 | G71: 101010193 | H71: 370 | I71: 666.83 | J71: 246726 | K71: 216540.35 | L71: 30185.647 | M71: 0.1223 | N71: 142 | O71: 53
B72: 白酒 | C72: 白酒-浓香型 | D72: 52°百年泸州老窖酒窖龄30年500ml | E72: 500ml*6 | F72: 瓶 | G72: 101010114 | H72: 1087 | I72: 224.39 | J72: 243910 | K72: 175117.95 | L72: 68792.053 | M72: 0.282 | N72: 378 | O72: 71
B73: 白酒 | C73: 白酒-酱香型 | D73: 53°飞天茅台酒1.3L | E73: 1.3L*4 | F73: 瓶 | G73: 101020048 | H73: 46 | I73: 4789 | J73: 220294 | K73: 160981.6 | L73: 59312.4 | M73: 0.2692 | N73: 33 | O73: 14
B74: 白酒 | C74: 白酒-酱香型 | D74: 53°飞天茅台鸡年500ml | E74: 500ml*6 | F74: 瓶 | G74: 101020079 | H74: 54 | I74: 4059.7 | J74: 219224 | K74: 161715.25 | L74: 57508.746 | M74: 0.2623 | N74: 18 | O74: 9
B75: 白酒 | C75: 白酒-清香型 | D75: 42°北京二锅头酒（出口型小方瓶）500ml | F75: 瓶 | G75: 101030036 | H75: 8550 | I75: 25.5 | J75: 218042 | K75: 150446.73 | L75: 67595.271 | M75: 0.31 | N75: 4095 | O75: 80
B76: 白酒 | C76: 白酒-浓香型 | D76: 38°泸州老窖百年60年窖龄500ml | E76: 500ml*6 | F76: 瓶 | G76: 101010297 | H76: 885 | I76: 240.7 | J76: 213020 | K76: 152046.83 | L76: 60973.175 | M76: 0.2862 | N76: 358 | O76: 65
B77: 白酒 | C77: 白酒-酱香型 | D77: 53°习酒金钻500ml | F77: 瓶 | G77: 101020093 | H77: 558 | I77: 376.4 | J77: 210032 | K77: 160250.03 | L77: 49781.973 | M77: 0.237 | N77: 272 | O77: 60
B78: 白酒 | C78: 白酒-浓香型 | D78: 46°牛栏山二锅头绿瓶500ml | E78: 500ml*12 | F78: 瓶 | G78: 101010276 | H78: 34282 | I78: 5.9 | J78: 202210.7 | K78: 185690.23 | L78: 16520.474 | M78: 0.0816 | N78: 9152 | O78: 80
B79: 白酒 | C79: 白酒-清香型 | D79: 48°汾酒乳白玻璃瓶酒475ml | E79: 475ml*12 | F79: 瓶 | G79: 101010328 | H79: 3680 | I79: 51.22 | J79: 188499 | K79: 128631.8 | L79: 59867.2 | M79: 0.3175 | N79: 1888 | O79: 78
B80: 白酒 | C80: 白酒-浓香型 | D80: 38°牛栏山百年红八年500ml | E80: 500ml*6 | F80: 瓶 | G80: 101010269 | H80: 3611 | I80: 51.66 | J80: 186541.4 | K80: 155077.08 | L80: 31464.316 | M80: 0.1686 | N80: 1507 | O80: 82
B81: 白酒 | C81: 白酒其它 | D81: 40°江小白100ml | E81: 100ml*24 | F81: 瓶 | G81: 101990007 | H81: 10287 | I81: 17.97 | J81: 184838 | K81: 114916.25 | L81: 69921.753 | M81: 0.3782 | N81: 3886 | O81: 82
B82: 白酒 | C82: 白酒-浓香型 | D82: 38°水井坊井台装500ml | E82: 500ml*6 | F82: 瓶 | G82: 101010262 | H82: 398 | I82: 449.22 | J82: 178788 | K82: 145824.31 | L82: 32963.689 | M82: 0.1843 | N82: 190 | O82: 51
B83: 白酒 | C83: 白酒-酱香型 | D83: 53°茅台迎宾酒500ml | E83: 500ml*6 | F83: 瓶 | G83: 101010217 | H83: 2246 | I83: 78.88 | J83: 177157 | K83: 135150.98 | L83: 42006.02 | M83: 0.2371 | N83: 1184 | O83: 74
B84: 白酒 | C84: 白酒-浓香型 | D84: 50°古井贡酒年份原浆5年500ml | E84: 500ml*6 | F84: 瓶 | G84: 101010422 | H84: 1017 | I84: 173.38 | J84: 176328 | K84: 109220.31 | L84: 67107.693 | M84: 0.3805 | N84: 464 | O84: 68
B85: 白酒 | C85: 白酒-清香型 | D85: 42°老白汾酒封坛十五年475ml | E85: 475ml*6 | F85: 瓶 | G85: 101010335 | H85: 963 | I85: 182.38 | J85: 175634 | K85: 125768.51 | L85: 49865.49 | M85: 0.2839 | N85: 424 | O85: 65
B86: 白酒 | C86: 白酒-清香型 | D86: 42°汾酒紫砂475ml | E86: 475ml*6 | F86: 瓶 | G86: 101010331 | H86: 1982 | I86: 87.66 | J86: 173745 | K86: 122104.43 | L86: 51640.565 | M86: 0.2972 | N86: 986 | O86: 73
B87: 白酒 | C87: 白酒-酱香型 | D87: 53°老习酒酱香型500ml | E87: 500ml*6 | F87: 瓶 | G87: 101020034 | H87: 1733 | I87: 99 | J87: 171567 | K87: 127928.39 | L87: 43638.605 | M87: 0.2543 | N87: 827 | O87: 72
B88: 白酒 | C88: 白酒-浓香型 | D88: 38°小糊涂仙500ml | E88: 500ml*12 | F88: 瓶 | G88: 101010258 | H88: 1285 | I88: 131.71 | J88: 169246 | K88: 139689.62 | L88: 29556.38 | M88: 0.1746 | N88: 654 | O88: 68
B89: 白酒 | C89: 白酒-酱香型 | D89: 53°飞天茅台酒2012年500ml | E89: 500ml*6 | F89: 瓶 | G89: 101020133 | H89: 48 | I89: 3300 | J89: 158400 | K89: 148800 | L89: 9600 | M89: 0.0606 | N89: 1 | O89: 1
B90: 白酒 | C90: 白酒-清香型 | D90: 52°牛栏山二十年珍品二锅头450ml | E90: 450ml*6 | F90: 瓶 | G90: 101010267 | H90: 2213 | I90: 69.06 | J90: 152822 | K90: 132516.19 | L90: 20305.806 | M90: 0.1328 | N90: 970 | O90: 77
B91: 白酒 | C91: 白酒-清香型 | D91: 53°红星蓝瓶八年陈酿750ml | F91: 瓶 | G91: 101030005 | H91: 4025 | I91: 37.42 | J91: 150598 | K91: 119718.42 | L91: 30879.578 | M91: 0.205 | N91: 1887 | O91: 71
B92: 白酒 | C92: 白酒-酱香型 | D92: 53°飞天茅台猴年500ml | F92: 瓶 | G92: 101020089 | H92: 30 | I92: 4928.27 | J92: 147848 | K92: 116766.91 | L92: 31081.086 | M92: 0.2102 | N92: 10 | O92: 7
B93: 白酒 | C93: 白酒-清香型 | D93: *43°红星蓝界酒500ml | E93: 500ml*12 | F93: 瓶 | G93: 101030016 | H93: 2059 | I93: 70.74 | J93: 145660 | K93: 76617.51 | L93: 69042.49 | M93: 0.4739 | N93: 954 | O93: 72
B94: 白酒 | C94: 白酒-清香型 | D94: 48°汾酒青花三十年500ml | E94: 500ml*6 | F94: 瓶 | G94: 101010330 | H94: 231 | I94: 620.78 | J94: 143401 | K94: 96658.139 | L94: 46742.861 | M94: 0.3259 | N94: 97 | O94: 39
B95: 白酒 | C95: 白酒-浓香型 | D95: 52°五粮液丁酉（鸡）年生肖纪念酒礼盒 | E95: 500ml*4*1 | F95: 盒 | G95: 101010524 | H95: 119 | I95: 1143.45 | J95: 136070 | K95: 81446.845 | L95: 54623.155 | M95: 0.4014 | N95: 53 | O95: 30
B96: 白酒 | C96: 白酒-酱香型 | D96: 53°飞天茅台金条50ml*5 | E96: 50ml*5 | F96: 盒 | G96: 101020099 | H96: 95 | I96: 1424.33 | J96: 135311 | K96: 120022.88 | L96: 15288.118 | M96: 0.1129 | N96: 25 | O96: 14
B97: 白酒 | C97: 白酒-清香型 | D97: *52°汾酒清香酒海475ml | E97: 475ml*6 | F97: 瓶 | G97: 101030015 | H97: 1802 | I97: 74.63 | J97: 134488.02 | K97: 77431.955 | L97: 57056.065 | M97: 0.4242 | N97: 481 | O97: 69
B98: 白酒 | C98: 白酒-清香型 | D98: 46°红星蓝花瓷珍品二锅头500ml | E98: 500ml*6 | F98: 瓶 | G98: 101010320 | H98: 705 | I98: 189.38 | J98: 133516 | K98: 92471.577 | L98: 41044.423 | M98: 0.3074 | N98: 322 | O98: 60
B99: 白酒 | C99: 白酒-浓香型 | D99: 42°牛栏山百年特酿红十二年500ml | E99: 500ml*6 | F99: 瓶 | G99: 101010473 | H99: 1292 | I99: 102.63 | J99: 132603 | K99: 90199.423 | L99: 42403.577 | M99: 0.3197 | N99: 524 | O99: 73
B100: 白酒 | C100: 白酒-浓香型 | D100: 52°泸州老窖头曲500ml | E100: 500ml*6 | F100: 瓶 | G100: 101010024 | H100: 2053 | I100: 61.43 | J100: 126122.8 | K100: 79750.16 | L100: 46372.64 | M100: 0.3676 | N100: 1056 | O100: 76
B101: 白酒 | C101: 白酒-酱香型 | D101: *53°国台酱酒1L | E101: 1L*4 | F101: 瓶 | G101: 101020040 | H101: 412 | I101: 299.07 | J101: 123217 | K101: 67822.049 | L101: 55394.951 | M101: 0.4495 | N101: 200 | O101: 55
B102: 白酒 | C102: 白酒-酱香型 | D102: 53°飞天茅台酒750ml | E102: 500ml*6 | F102: 瓶 | G102: 101020119 | H102: 36 | I102: 3388 | J102: 121968 | K102: 102636 | L102: 19332 | M102: 0.1585 | N102: 22 | O102: 18
B103: 白酒 | C103: 白酒-酱香型 | D103: 53°习酒窖藏1998（2016红）500ml | E103: 500ml*6 | F103: 瓶 | G103: 101020096 | H103: 332 | I103: 355.46 | J103: 118014 | K103: 101904.91 | L103: 16109.087 | M103: 0.1365 | N103: 149 | O103: 54
B104: 白酒 | C104: 白酒-浓香型 | D104: 38°泸州老窖泸州百年30年窖龄500ml | E104: 500ml*6 | F104: 瓶 | G104: 101010294 | H104: 585 | I104: 200.19 | J104: 117112 | K104: 79977.941 | L104: 37134.059 | M104: 0.317 | N104: 220 | O104: 61
B105: 白酒 | C105: 白酒其它 | D105: 52°洋河海之蓝480ml | E105: 480ml*6 | F105: 瓶 | G105: 101010098 | H105: 710 | I105: 159.07 | J105: 112938 | K105: 92481.473 | L105: 20456.527 | M105: 0.1811 | N105: 312 | O105: 73
B106: 白酒 | C106: 白酒-浓香型 | D106: 39°牛栏山百年十二年红龙500ml | F106: 瓶 | G106: 101010381 | H106: 870 | I106: 124.45 | J106: 108268 | K106: 92598.219 | L106: 15669.781 | M106: 0.1447 | N106: 329 | O106: 60
B107: 白酒 | C107: 白酒-浓香型 | D107: 52°五粮液国宾酒500ml | E107: 500ml*6 | F107: 瓶 | G107: 101010443 | H107: 546 | I107: 197.37 | J107: 107766 | K107: 70683.081 | L107: 37082.919 | M107: 0.3441 | N107: 246 | O107: 63
B108: 白酒 | C108: 白酒-浓香型 | D108: 42º牛栏山建厂特制酒1972年500ml | F108: 瓶 | G108: 101010386 | H108: 681 | I108: 156.11 | J108: 106308 | K108: 73315.545 | L108: 32992.455 | M108: 0.3103 | N108: 349 | O108: 59
B109: 白酒 | C109: 白酒-清香型 | D109: 53°红星蓝瓶八年陈酿500ml | E109: 500ml*12 | F109: 瓶 | G109: 101010311 | H109: 3764 | I109: 27.62 | J109: 103979.5 | K109: 82984.95 | L109: 20994.55 | M109: 0.2019 | N109: 1693 | O109: 72
B110: 白酒 | C110: 白酒-浓香型 | D110: 39°牛栏山金牛珍品陈酿500ml | E110: 500ml*8 | F110: 瓶 | G110: 101010275 | H110: 2771 | I110: 36.02 | J110: 99812 | K110: 77458.104 | L110: 22353.896 | M110: 0.2239 | N110: 1572 | O110: 75
B111: 白酒 | C111: 白酒-浓香型 | D111: 52°五粮液E60珍品酒 500ml | E111: 500ml*6 | F111: 瓶 | G111: 101020062 | H111: 917 | I111: 108.78 | J111: 99752 | K111: 50986.803 | L111: 48765.197 | M111: 0.4888 | N111: 346 | O111: 70
B112: 白酒 | C112: 白酒-浓香型 | D112: *52°孔府家酒朋自远方6 500ml | E112: 500ml*6 | F112: 瓶 | G112: 101010475 | H112: 530 | I112: 188 | J112: 99640 | K112: 32735.483 | L112: 66904.517 | M112: 0.6714 | N112: 245 | O112: 58
B113: 白酒 | C113: 白酒-酱香型 | D113: 53°飞天茅台酒3L | E113: 3L*2 | F113: 瓶 | G113: 101020116 | H113: 6 | I113: 15933 | J113: 95598 | K113: 88800 | L113: 6798 | M113: 0.0711 | N113: 6 | O113: 6
B114: 白酒 | C114: 白酒-清香型 | D114: 52°汾酒清香酒海品味475ml | E114: 475ml*6 | F114: 瓶 | G114: 101030042 | H114: 1138 | I114: 83.25 | J114: 94740 | K114: 45158.111 | L114: 49581.889 | M114: 0.5233 | N114: 364 | O114: 69
B115: 白酒 | C115: 白酒-浓香型 | D115: 50°古井贡酒年份原浆8年500ml | E115: 500ml*6 | F115: 瓶 | G115: 101010441 | H115: 308 | I115: 304.66 | J115: 93836 | K115: 62921.215 | L115: 30914.785 | M115: 0.3294 | N115: 132 | O115: 49
B116: 白酒 | C116: 白酒-浓香型 | D116: 50°古井贡酒幸福版500ml | E116: 500ml*6 | F116: 瓶 | G116: 101010455 | H116: 707 | I116: 131.32 | J116: 92840 | K116: 58108.399 | L116: 34731.601 | M116: 0.3741 | N116: 305 | O116: 64
B117: 白酒 | C117: 白酒-浓香型 | D117: 52°牛栏山金牛珍品陈酿500ml | E117: 500ml*8 | F117: 瓶 | G117: 101010266 | H117: 2333 | I117: 38.95 | J117: 90874 | K117: 69799.518 | L117: 21074.482 | M117: 0.2319 | N117: 1269 | O117: 75
B118: 白酒 | C118: 白酒-酱香型 | D118: 53°飞天茅台酒200ml | E118: 200ml*12 | F118: 瓶 | G118: 101020108 | H118: 98 | I118: 854.99 | J118: 83789 | K118: 76440 | L118: 7349 | M118: 0.0877 | N118: 21 | O118: 10
B119: 白酒 | C119: 白酒-浓香型 | D119: 52°洋河天之蓝480ml | E119: 480ml*6 | F119: 瓶 | G119: 101010004 | H119: 232 | I119: 359 | J119: 83288 | K119: 67280 | L119: 16008 | M119: 0.1922 | N119: 107 | O119: 45
B120: 白酒 | C120: 白酒-酱香型 | D120: 43°华都天安门庆典红500ml | E120: 500ml*6 | F120: 瓶 | G120: 101020050 | H120: 232 | I120: 358.07 | J120: 83072 | K120: 62061.308 | L120: 21010.692 | M120: 0.2529 | N120: 83 | O120: 40
... B124: 白酒 | C124: 白酒-酱香型 | D124: 53°珍品茅台500ml | E124: 500ml*6 | F124: 瓶 | G124: 101020049 | H124: 15 | I124: 4890.8 | J124: 73362 | K124: 57921.231 | L124: 15440.769 | M124: 0.2104 | N124: 8 | O124: 6
B125: 白酒 | C125: 白酒-浓香型 | D125: 35°牛栏山百年六年红龙500ml | F125: 瓶 | G125: 101010382 | H125: 1912 | I125: 37.99 | J125: 72642 | K125: 63094.612 | L125: 9547.3877 | M125: 0.1314 | N125: 896 | O125: 71
B126: 白酒 | C126: 白酒-凤香型 | D126: 52°西凤凤香醇500ml | F126: 瓶 | G126: 101050001 | H126: 589 | I126: 119.43 | J126: 70344 | K126: 41077.137 | L126: 29266.863 | M126: 0.416 | N126: 330 | O126: 66
B127: 白酒 | C127: 白酒-酱香型 | D127: 53°飞天茅台酒125ml | E127: 125ml*48 | F127: 瓶 | G127: 101020109 | H127: 111 | I127: 618 | J127: 68598 | K127: 56610 | L127: 11988 | M127: 0.1747 | N127: 17 | O127: 7
B128: 白酒 | C128: 白酒-浓香型 | D128: 50°古井贡原浆十六年500ml | E128: 500ml*6 | F128: 瓶 | G128: 101010409 | H128: 137 | I128: 490.38 | J128: 67182 | K128: 53875.28 | L128: 13306.72 | M128: 0.198 | N128: 62 | O128: 36
B129: 白酒 | C129: 白酒-清香型 | D129: 56°牛栏山二锅头白酒出口美国750ml | F129: 瓶 | G129: 101010380 | H129: 2007 | I129: 31.82 | J129: 63869.1 | K129: 46108.064 | L129: 17761.036 | M129: 0.278 | N129: 833 | O129: 70
B130: 白酒 | C130: 白酒-酱香型 | D130: 53°飞天茅台羊年500ml | F130: 瓶 | G130: 101020091 | H130: 3 | I130: 21200 | J130: 63600 | K130: 41114.103 | L130: 22485.897 | M130: 0.3535 | N130: 3 | O130: 3
B131: 白酒 | C131: 白酒-浓香型 | D131: *52°全兴古酿500ml | E131: 500ml*6 | F131: 瓶 | G131: 101010486 | H131: 338 | I131: 188 | J131: 63544 | K131: 32005.255 | L131: 31538.745 | M131: 0.4963 | N131: 193 | O131: 57
B132: 白酒 | C132: 白酒-浓香型 | D132: 42°洋河老窖青瓷500ml | E132: 500ml*6 | F132: 瓶 | G132: 101010257 | H132: 811 | I132: 77.42 | J132: 62784 | K132: 41861.695 | L132: 20922.305 | M132: 0.3332 | N132: 456 | O132: 67
B133: 白酒 | C133: 白酒-清香型 | D133: 42°北京二锅头酒（蓝色版）500ml | E133: 500ml*12 | F133: 瓶 | G133: 101030045 | H133: 2555 | I133: 24.45 | J133: 62468 | K133: 40750.234 | L133: 21717.766 | M133: 0.3476 | N133: 1237 | O133: 77
B134: 白酒 | C134: 白酒-浓香型 | D134: 38°泸州老窖特曲500ml | E134: 500ml*6 | F134: 瓶 | G134: 101010291 | H134: 343 | I134: 176.59 | J134: 60569 | K134: 47801.014 | L134: 12767.986 | M134: 0.2108 | N134: 182 | O134: 59
B135: 白酒 | C135: 白酒-清香型 | D135: 43°红星蓝瓶八年陈酿250ml | E135: 250ml*24 | F135: 瓶 | G135: 101010310 | H135: 4202 | I135: 13.73 | J135: 57677.9 | K135: 42976.226 | L135: 14701.674 | M135: 0.2548 | N135: 3266 | O135: 71
B136: 白酒 | C136: 白酒-酱香型 | D136: 53°飞天茅台酒1.5L | E136: 1.5L*4 | F136: 瓶 | G136: 101020103 | H136: 7 | I136: 8000 | J136: 56000 | K136: 49544.18 | L136: 6455.82 | M136: 0.1152 | N136: 6 | O136: 6
...

Sheet 西安
B2: 商品大类 | C2: 商品类别 | D2: 商品名称 | E2: 规格 | F2: 单位 | G2: 商品编码 | H2: 数量 | I2: 成交均价 | J2: 销售额 | K2: 成本 | L2: 毛利 | M2: 毛利率 | N2: 单品客流量 | O2: 销售门店数
H3: 103663 | I3: 312.32229 | J3: 32376266 | K3: 27803838 | L3: 4572427.9 | O3: 2541
B4: 白酒 | C4: 白酒-酱香型 | D4: 53°飞天茅台酒500ml | E4: 500ml*6 | F4: 瓶 | G4: 101010185 | H4: 4585 | I4: 1490.77 | J4: 6835178 | K4: 6275580.8 | L4: 559597.24 | M4: 0.0818 | N4: 883 | O4: 22
B5: 白酒 | C5: 白酒-浓香型 | D5: 52°五粮液普装500ml | E5: 500ml*6 | F5: 瓶 | G5: 101010001 | H5: 4867 | I5: 886.5 | J5: 4314601 | K5: 3956015 | L5: 358585.97 | M5: 0.0831 | N5: 1564 | O5: 23
B6: 白酒 | C6: 白酒-浓香型 | D6: 52°国窖1573 500ml | E6: 500ml*6 | F6: 瓶 | G6: 101010099 | H6: 3221 | I6: 822.69 | J6: 2649887 | K6: 2326537.4 | L6: 323349.59 | M6: 0.122 | N6: 813 | O6: 23
B7: 白酒 | C7: 白酒-酱香型 | D7: 53°茅台酒15年500ml礼盒装 | E7: 500ml*6 | F7: 盒 | G7: 101020023 | H7: 362 | I7: 5086.27 | J7: 1841228 | K7: 1708407 | L7: 132820.96 | M7: 0.0721 | N7: 158 | O7: 19
B8: 白酒 | C8: 白酒-凤香型 | D8: 45°西凤6年陈酿500ml | E8: 500ml*6 | F8: 瓶 | G8: 101010476 | H8: 10884 | I8: 149.99 | J8: 1632500 | K8: 1414734.2 | L8: 217765.81 | M8: 0.1333 | N8: 4633 | O8: 22
B9: 白酒 | C9: 白酒-浓香型 | D9: 52°剑南春普装500ml | E9: 500ml*6 | F9: 瓶 | G9: 101010002 | H9: 3614 | I9: 382.5 | J9: 1382338 | K9: 1244022.2 | L9: 138315.84 | M9: 0.1 | N9: 1290 | O9: 23
B10: 白酒 | C10: 白酒-浓香型 | D10: 52°五粮液1618 500ml | E10: 500ml*6 | F10: 瓶 | G10: 101010139 | H10: 1369 | I10: 907.65 | J10: 1242571 | K10: 1090896.9 | L10: 151674.11 | M10: 0.122 | N10: 451 | O10: 22
B11: 白酒 | C11: 白酒-凤香型 | D11: 45°西凤华山论剑20年500ml | E11: 500ml*6 | F11: 瓶 | G11: 101010479 | H11: 4160 | I11: 243.2 | J11: 1011722 | K11: 872179.06 | L11: 139542.94 | M11: 0.1379 | N11: 1621 | O11: 22
B12: 白酒 | C12: 白酒-酱香型 | D12: 43°飞天茅台500ml | E12: 500ml*6 | F12: 瓶 | G12: 101010290 | H12: 1148 | I12: 878.2 | J12: 1008170 | K12: 793903.26 | L12: 214266.74 | M12: 0.2125 | N12: 193 | O12: 22
B13: 白酒 | C13: 白酒-凤香型 | D13: 45°西凤华山论剑10年500ml | E13: 500ml*6 | F13: 瓶 | G13: 101010478 | H13: 4015 | I13: 137.13 | J13: 550559 | K13: 440800.04 | L13: 109758.96 | M13: 0.1993 | N13: 1902 | O13: 22
B14: 白酒 | C14: 白酒-酱香型 | D14: *53°飞天茅台三十年500ml | E14: 500ml*6 | F14: 瓶 | G14: 101010289 | H14: 48 | I14: 11363.58 | J14: 545452 | K14: 470665.74 | L14: 74786.263 | M14: 0.1371 | N14: 18 | O14: 8
B15: 白酒 | C15: 白酒-酱香型 | D15: 53°飞天茅台酒375ml | E15: 375ml*12 | F15: 瓶 | G15: 101020107 | H15: 360 | I15: 1499 | J15: 539640 | K15: 476400 | L15: 63240 | M15: 0.1171 | N15: 64 | O15: 14
... B23: 白酒 | C23: 白酒-浓香型 | D23: 52°百年泸州老窖酒窖龄60年500ml | E23: 500ml*6 | F23: 瓶 | G23: 101010115 | H23: 876 | I23: 273.45 | J23: 239538 | K23: 160260.37 | L23: 79277.631 | M23: 0.3309 | N23: 334 | O23: 21
B24: 白酒 | C24: 白酒-酱香型 | D24: 53°飞天茅台狗年500ml | F24: 瓶 | G24: 101020101 | H24: 54 | I24: 4377.78 | J24: 236400 | K24: 210870 | L24: 25530 | M24: 0.1079 | N24: 13 | O24: 3
B25: 白酒 | C25: 白酒-酱香型 | D25: 53°飞天茅台酒200ml | E25: 200ml*12 | F25: 瓶 | G25: 101020108 | H25: 211 | I25: 837.35 | J25: 176681 | K25: 158250 | L25: 18431 | M25: 0.1043 | N25: 51 | O25: 15
B26: 白酒 | C26: 白酒-凤香型 | D26: 55°西凤酒红西风500ml | E26: 500ml*4 | F26: 瓶 | G26: 101010483 | H26: 315 | I26: 557.75 | J26: 175692 | K26: 139395.06 | L26: 36296.935 | M26: 0.2065 | N26: 111 | O26: 19
B27: 白酒 | C27: 白酒-酱香型 | D27: 53°贵州茅台酒（澳门回归18年纪念）5L | E27: 5L*1 | F27: 盒 | G27: 101020131 | H27: 5 | I27: 35000 | J27: 175000 | K27: 165400 | L27: 9600 | M27: 0.0548 | N27: 1 | O27: 1
B28: 白酒 | C28: 白酒-酱香型 | D28: 53°贵州茅台酒（澳门回归18年纪念）陈酿5L | E28: 5L*1 | F28: 盒 | G28: 101020132 | H28: 5 | I28: 35000 | J28: 175000 | K28: 165400 | L28: 9600 | M28: 0.0548 | N28: 1 | O28: 1
B29: 白酒 | C29: 白酒-浓香型 | D29: 52°水井坊井台装500ml | E29: 500ml*6 | F29: 瓶 | G29: 101010006 | H29: 358 | I29: 476.06 | J29: 170431 | K29: 142265.95 | L29: 28165.048 | M29: 0.1652 | N29: 151 | O29: 19
B30: 白酒 | C30: 白酒-清香型 | D30: 53°汾酒475ml | E30: 475ml*12 | F30: 瓶 | G30: 999010016 | H30: 3853 | I30: 43.82 | J30: 168856 | K30: 122094.69 | L30: 46761.314 | M30: 0.2769 | N30: 2158 | O30: 22
B31: 白酒 | C31: 白酒-浓香型 | D31: *46°洋河海之蓝480ml | E31: 480ml*6 | F31: 瓶 | G31: 101010003 | H31: 1203 | I31: 137.59 | J31: 165526 | K31: 138198.05 | L31: 27327.95 | M31: 0.165 | N31: 600 | O31: 22
B32: 白酒 | C32: 白酒其它 | D32: 52°洋河梦之蓝M3 500ml | E32: 500ml*4 | F32: 瓶 | G32: 101010119 | H32: 285 | I32: 574.19 | J32: 163643 | K32: 112561.12 | L32: 51081.876 | M32: 0.3121 | N32: 125 | O32: 21
B33: 白酒 | C33: 白酒-清香型 | D33: 53°汾酒20年青花500ml | E33: 500ml*6 | F33: 瓶 | G33: 101010192 | H33: 395 | I33: 388.87 | J33: 153604 | K33: 143385.55 | L33: 10218.448 | M33: 0.0665 | N33: 155 | O33: 22
B34: 白酒 | C34: 白酒-浓香型 | D34: 52°百年泸州老窖酒窖龄30年500ml | E34: 500ml*6 | F34: 瓶 | G34: 101010114 | H34: 648 | I34: 204.38 | J34: 132441 | K34: 99922.282 | L34: 32518.718 | M34: 0.2455 | N34: 244 | O34: 22
B35: 白酒 | C35: 白酒-清香型 | D35: 53°老白汾酒封坛拾伍年475ml | E35: 475ml*6 | F35: 瓶 | G35: 101010113 | H35: 526 | I35: 232.56 | J35: 122329 | K35: 82412.19 | L35: 39916.81 | M35: 0.3263 | N35: 263 | O35: 22
B36: 白酒 | C36: 白酒-酱香型 | D36: 53°红花郎15年500ml | E36: 500ml*6 | F36: 瓶 | G36: 101010140 | H36: 230 | I36: 529.95 | J36: 121888 | K36: 100642.71 | L36: 21245.29 | M36: 0.1743 | N36: 85 | O36: 18
... B53: 白酒 | C53: 白酒-清香型 | D53: *52°汾酒清香酒海475ml | E53: 475ml*6 | F53: 瓶 | G53: 101030015 | H53: 1356 | I53: 61.27 | J53: 83078 | K53: 57501.57 | L53: 25576.43 | M53: 0.3078 | N53: 253 | O53: 20
B54: 白酒 | C54: 白酒-酱香型 | D54: 53°赖茅重沙500ml | F54: 瓶 | G54: 101020056 | H54: 286 | I54: 285.67 | J54: 81702 | K54: 44128.631 | L54: 37573.369 | M54: 0.4598 | N54: 165 | O54: 22
B55: 白酒 | C55: 白酒-凤香型 | D55: 45°西凤酒375ml | E55: 375ml*20 | F55: 瓶 | G55: 101010484 | H55: 3216 | I55: 24.26 | J55: 78035.5 | K55: 65398.249 | L55: 12637.251 | M55: 0.1619 | N55: 1462 | O55: 22
B56: 白酒 | C56: 白酒-浓香型 | D56: 52°泸州老窖头曲500ml | E56: 500ml*6 | F56: 瓶 | G56: 101010024 | H56: 1433 | I56: 54.37 | J56: 77914 | K56: 54113.372 | L56: 23800.627 | M56: 0.3054 | N56: 785 | O56: 22
B57: 白酒 | C57: 白酒-酱香型 | D57: 53°习酒红盒 500ml | E57: 500ml*6 | F57: 瓶 | G57: 101020006 | H57: 890 | I57: 80.57 | J57: 71706 | K57: 47100.45 | L57: 24605.55 | M57: 0.3431 | N57: 486 | O57: 22
B58: 白酒 | C58: 白酒-浓香型 | D58: 52°五粮液E60珍品酒 500ml | E58: 500ml*6 | F58: 瓶 | G58: 101020062 | H58: 744 | I58: 96.36 | J58: 71694 | K58: 40259.061 | L58: 31434.939 | M58: 0.4384 | N58: 197 | O58: 21
B59: 白酒 | C59: 白酒-浓香型 | D59: 52°五粮液(交杯牌)500ml | E59: 500ml*6 | F59: 瓶 | G59: 101010492 | H59: 58 | I59: 1154.55 | J59: 66964 | K59: 51379.779 | L59: 15584.221 | M59: 0.2327 | N59: 24 | O59: 12
B60: 白酒 | C60: 白酒-酱香型 | D60: 53°茅台迎宾酒500ml | E60: 500ml*6 | F60: 瓶 | G60: 101010217 | H60: 870 | I60: 73.87 | J60: 64271 | K60: 54674.4 | L60: 9596.6002 | M60: 0.1493 | N60: 376 | O60: 22
B61: 白酒 | C61: 白酒其它 | D61: 40°江小白100ml | E61: 100ml*24 | F61: 瓶 | G61: 101990007 | H61: 3439 | I61: 17.74 | J61: 61018 | K61: 39648.262 | L61: 21369.738 | M61: 0.3502 | N61: 1161 | O61: 22
B62: 白酒 | C62: 白酒-浓香型 | D62: *52°五粮液虎符令酒500ml | E62: 500ml*6 | F62: 瓶 | G62: 101010530 | H62: 54 | I62: 1075.41 | J62: 58072 | K62: 47597.23 | L62: 10474.77 | M62: 0.1803 | N62: 22 | O62: 14
B63: 白酒 | C63: 白酒-清香型 | D63: 53°汾酒紫砂陶475ml | E63: 475ml*6 | F63: 瓶 | G63: 101010070 | H63: 583 | I63: 96.95 | J63: 56519 | K63: 42417.994 | L63: 14101.006 | M63: 0.2494 | N63: 340 | O63: 22
B64: 白酒 | C64: 白酒-浓香型 | D64: 52°五粮液六和液盛典装500ml | E64: 500ml*6 | F64: 瓶 | G64: 101010138 | H64: 400 | I64: 139.88 | J64: 55952 | K64: 43701.39 | L64: 12250.61 | M64: 0.2189 | N64: 121 | O64: 22
B65: 白酒 | C65: 白酒-酱香型 | D65: 53°习酒窖藏1998 500ml | E65: 500ml*6 | F65: 瓶 | G65: 101020008 | H65: 133 | I65: 418.98 | J65: 55724 | K65: 41122.201 | L65: 14601.799 | M65: 0.262 | N65: 76 | O65: 19
B66: 白酒 | C66: 白酒-浓香型 | D66: 52°水井坊臻酿八号500ml | E66: 500ml*6 | F66: 瓶 | G66: 101010495 | H66: 159 | I66: 343.53 | J66: 54621 | K66: 44520 | L66: 10101 | M66: 0.1849 | N66: 81 | O66: 20
... B69: 白酒 | C69: 白酒-浓香型 | D69: 52°泸州老窖六年窖头曲450ml | E69: 450ml *6 | F69: 瓶 | G69: 101010405 | H69: 539 | I69: 89.18 | J69: 48070 | K69: 31755.487 | L69: 16314.513 | M69: 0.3393 | N69: 308 | O69: 22
B70: 白酒 | C70: 白酒-凤香型 | D70: 45°1956西凤酒日月藏500ml | F70: 瓶 | G70: 101050003 | H70: 459 | I70: 104.17 | J70: 47815 | K70: 35705.998 | L70: 12109.002 | M70: 0.2532 | N70: 213 | O70: 22
B71: 白酒 | C71: 白酒-酱香型 | D71: 53°习酒金典500ml | E71: 500ml*6 | F71: 瓶 | G71: 101020104 | H71: 157 | I71: 287.72 | J71: 45172 | K71: 30366.258 | L71: 14805.742 | M71: 0.3277 | N71: 71 | O71: 18
B72: 白酒 | C72: 白酒-浓香型 | D72: 45°老榆林十年500ml | F72: 瓶 | G72: 101010507 | H72: 273 | I72: 162.77 | J72: 44436 | K72: 29446.897 | L72: 14989.103 | M72: 0.3373 | N72: 139 | O72: 22
B73: 白酒 | C73: 白酒-浓香型 | D73: *52°孔府家酒朋自远方6 500ml | E73: 500ml*6 | F73: 瓶 | G73: 101010475 | H73: 393 | I73: 99.45 | J73: 39084 | K73: 24264.808 | L73: 14819.192 | M73: 0.3791 | N73: 125 | O73: 21
B74: 白酒 | C74: 白酒-酱香型 | D74: 53°飞天茅台玫瑰金版500ml | E74: 500ml*6 | F74: 瓶 | G74: 101020041 | H74: 18 | I74: 2111 | J74: 37998 | K74: 21742.664 | L74: 16255.336 | M74: 0.4277 | N74: 2 | O74: 1
B75: 白酒 | C75: 白酒-浓香型 | D75: 52°金剑南1号藏品500ml | E75: 500ml*6 | F75: 瓶 | G75: 101010465 | H75: 224 | I75: 159.8 | J75: 35796 | K75: 20982.877 | L75: 14813.123 | M75: 0.4138 | N75: 113 | O75: 21
B76: 白酒 | C76: 白酒-浓酱兼香型 | D76: 50°白云边五星陈酿500ml | E76: 500ml*6 | F76: 瓶 | G76: 101010203 | H76: 258 | I76: 136.4 | J76: 35190 | K76: 26382.396 | L76: 8807.6037 | M76: 0.2502 | N76: 138 | O76: 22
B77: 白酒 | C77: 白酒-浓香型 | D77: 52°尖庄曲酒300ml | E77: 300ml*20 | F77: 瓶 | G77: 101010449 | H77: 1626 | I77: 19.75 | J77: 32106 | K77: 21109.382 | L77: 10996.618 | M77: 0.3425 | N77: 876 | O77: 22
B78: 白酒 | C78: 白酒-浓香型 | D78: 42°牛栏山陈酿白酒500ml | E78: 500ml*12 | F78: 瓶 | G78: 101030011 | H78: 2140 | I78: 14.9 | J78: 31889.1 | K78: 22378.006 | L78: 9511.094 | M78: 0.2982 | N78: 1309 | O78: 23
B79: 白酒 | C79: 白酒-酱香型 | D79: 53°习酒窖藏1988 500ml | E79: 500ml*6 | F79: 瓶 | G79: 101020053 | H79: 43 | I79: 736.79 | J79: 31682 | K79: 23141.187 | L79: 8540.8128 | M79: 0.2695 | N79: 14 | O79: 10
B80: 白酒 | C80: 白酒其它 | D80: 52°酒鬼酒红坛500ml | E80: 500ml*6 | F80: 瓶 | G80: 101990022 | H80: 70 | I80: 451.49 | J80: 31604 | K80: 24950.344 | L80: 6653.6558 | M80: 0.2105 | N80: 27 | O80: 14
B81: 白酒 | C81: 白酒-浓香型 | D81: 52°五粮液丁酉（鸡）年生肖纪念酒礼盒 | E81: 500ml*4*1 | F81: 盒 | G81: 101010524 | H81: 27 | I81: 1150.74 | J81: 31070 | K81: 16158.974 | L81: 14911.026 | M81: 0.4799 | N81: 21 | O81: 15
B82: 白酒 | C82: 白酒-清香型 | D82: 42°汾阳王10年500ml | E82: 500ml*6 | F82: 瓶 | G82: 101030021 | H82: 510 | I82: 59.82 | J82: 30506 | K82: 17785.985 | L82: 12720.015 | M82: 0.4169 | N82: 210 | O82: 22
B83: 白酒 | C83: 白酒-浓香型 | D83: 53°国窖国韵1L | F83: 瓶 | G83: 101020063 | H83: 11 | I83: 2772.73 | J83: 30500 | K83: 22900.02 | L83: 7599.98 | M83: 0.2491 | N83: 8 | O83: 5
B84: 白酒 | C84: 白酒-清香型 | D84: 42°汾阳王5年500ml | E84: 500ml*6 | F84: 瓶 | G84: 101030020 | H84: 1217 | I84: 24.9 | J84: 30309 | K84: 18169.362 | L84: 12139.638 | M84: 0.4005 | N84: 294 | O84: 22
B85: 白酒 | C85: 白酒-凤香型 | D85: 45°西凤十五年珍藏酒500ml | E85: 500ml*6 | F85: 瓶 | G85: 101050013 | H85: 101 | I85: 285.82 | J85: 28868 | K85: 26260 | L85: 2608 | M85: 0.0903 | N85: 31 | O85: 15
B86: 白酒 | C86: 白酒-清香型 | D86: 53°红星八年陈酿蓝瓶二锅头500ml | E86: 500ml*12 | F86: 瓶 | G86: 101010169 | H86: 987 | I86: 29.04 | J86: 28659 | K86: 24635.237 | L86: 4023.7626 | M86: 0.1404 | N86: 608 | O86: 22
B87: 白酒 | C87: 白酒-凤香型 | D87: 45°西凤六年珍藏酒500ml | E87: 500ml*6 | F87: 瓶 | G87: 101050012 | H87: 154 | I87: 166.99 | J87: 25716 | K87: 22330 | L87: 3386 | M87: 0.1316 | N87: 99 | O87: 18
B88: 白酒 | C88: 白酒-浓香型 | D88: *52°全兴1963 500ml | E88: 500ml*12 | F88: 瓶 | G88: 101010454 | H88: 540 | I88: 47.23 | J88: 25506 | K88: 12923.968 | L88: 12582.032 | M88: 0.4932 | N88: 333 | O88: 22
B89: 白酒 | C89: 白酒-浓香型 | D89: 52°国窖1573曾娜大师鉴藏版500ml | F89: 瓶 | G89: 101010521 | H89: 26 | I89: 967 | J89: 25142 | K89: 19240 | L89: 5902 | M89: 0.2347 | N89: 14 | O89: 10
B90: 白酒 | C90: 白酒-浓香型 | D90: 52°小糊涂神500ml | E90: 500ml*12 | F90: 瓶 | G90: 101010097 | H90: 324 | I90: 77.3 | J90: 25046 | K90: 18731.973 | L90: 6314.0273 | M90: 0.252 | N90: 195 | O90: 22
B91: 白酒 | C91: 白酒-浓香型 | D91: *42°泸小二FOR ME（彩色）酒125ml | E91: 125ml*24 | F91: 瓶 | G91: 101010501 | H91: 1361 | I91: 17.75 | J91: 24153 | K91: 14909.424 | L91: 9243.5757 | M91: 0.3827 | N91: 548 | O91: 22
B92: 白酒 | C92: 白酒-浓香型 | D92: 52°绵竹大曲窖藏500ml | E92: 500ml*6 | F92: 瓶 | G92: 101010456 | H92: 753 | I92: 31.78 | J92: 23928 | K92: 14404.305 | L92: 9523.6955 | M92: 0.398 | N92: 228 | O92: 21
B93: 白酒 | C93: 白酒-浓香型 | D93: 52°尖庄曲酒500ml | E93: 500ml*6 | F93: 瓶 | G93: 101010100 | H93: 607 | I93: 38.47 | J93: 23353 | K93: 10895.227 | L93: 12457.773 | M93: 0.5334 | N93: 353 | O93: 21
B94: 白酒 | C94: 白酒其它 | D94: 45°竹叶青酒牧童475ml | E94: 475ml*6 | F94: 瓶 | G94: 101990006 | H94: 417 | I94: 51.46 | J94: 21459 | K94: 15741.197 | L94: 5717.8035 | M94: 0.2664 | N94: 280 | O94: 22
B95: 白酒 | C95: 白酒-浓香型 | D95: *52°全兴古酿500ml | E95: 500ml*6 | F95: 瓶 | G95: 101010486 | H95: 111 | I95: 188 | J95: 20868 | K95: 10527.907 | L95: 10340.093 | M95: 0.4954 | N95: 83 | O95: 20
B96: 白酒 | C96: 白酒-浓香型 | D96: 52°文君礼盒套装500ml+100ml | E96: 500ml+100ml*6 | F96: 盒 | G96: 101020004 | H96: 33 | I96: 623.03 | J96: 20560 | K96: 13562.182 | L96: 6997.8179 | M96: 0.3403 | N96: 26 | O96: 10
B97: 白酒 | C97: 白酒-清香型 | D97: 50°牛栏山二锅头清雅二十年475ml | E97: 475ml*6 | F97: 瓶 | G97: 101010117 | H97: 145 | I97: 139 | J97: 20155 | K97: 12264.543 | L97: 7890.4567 | M97: 0.3914 | N97: 88 | O97: 20
B98: 白酒 | C98: 白酒-浓酱兼香型 | D98: 53°白云边四星陈酿500ml | E98: 500ml*6 | F98: 瓶 | G98: 101010162 | H98: 242 | I98: 82.96 | J98: 20076 | K98: 13450.119 | L98: 6625.8812 | M98: 0.33 | N98: 158 | O98: 22
B99: 白酒 | C99: 白酒-浓香型 | D99: 45°五粮春500ml | E99: 500ml*12 | F99: 瓶 | G99: 101010259 | H99: 105 | I99: 184.3 | J99: 19352 | K99: 14417.938 | L99: 4934.0624 | M99: 0.2549 | N99: 67 | O99: 16
B100: 白酒 | C100: 白酒-清香型 | D100: 50°牛栏山特制精品二锅头450ml | E100: 450ml*6 | F100: 瓶 | G100: 101010093 | H100: 257 | I100: 72.74 | J100: 18695 | K100: 11784.815 | L100: 6910.1852 | M100: 0.3696 | N100: 178 | O100: 22
B101: 白酒 | C101: 白酒-浓香型 | D101: 52°孔府家酒高陶500ml | E101: 500ml*6 | F101: 瓶 | G101: 101010472 | H101: 457 | I101: 39.65 | J101: 18120 | K101: 9567.2776 | L101: 8552.7224 | M101: 0.472 | N101: 176 | O101: 22
... B111: 白酒 | C111: 白酒-浓香型 | D111: 52°泸州老窖中秋丁酉年节庆酒1L | E111: 1L*3 | F111: 瓶 | G111: 101020055 | H111: 31 | I111: 437.1 | J111: 13550 | K111: 8243.8632 | L111: 5306.1368 | M111: 0.3915 | N111: 16 | O111: 10
B112: 白酒 | C112: 白酒-浓香型 | D112: 52°剑南窖藏18 500ml | F112: 瓶 | G112: 101010517 | H112: 41 | I112: 298 | J112: 12218 | K112: 8792.9488 | L112: 3425.0512 | M112: 0.2803 | N112: 25 | O112: 15
B113: 白酒 | C113: 白酒-浓香型 | D113: 52°剑南窖藏9 500ml | F113: 瓶 | G113: 101010516 | H113: 62 | I113: 195.29 | J113: 12108 | K113: 8032.2224 | L113: 4075.7776 | M113: 0.3366 | N113: 32 | O113: 16
B114: 白酒 | C114: 白酒-浓香型 | D114: *52°泸州窖酒窖之绵500ml | E114: 500ml*6 | F114: 瓶 | G114: 101020020 | H114: 116 | I114: 99 | J114: 11484 | K114: 7867.0103 | L114: 3616.9897 | M114: 0.3149 | N114: 77 | O114: 19
B115: 白酒 | C115: 白酒-清香型 | D115: 53°红星八年陈酿蓝瓶二锅头250ml | E115: 250ml*24 | F115: 瓶 | G115: 101030010 | H115: 695 | I115: 16.05 | J115: 11158 | K115: 8130.3322 | L115: 3027.6678 | M115: 0.2713 | N115: 520 | O115: 21
B116: 白酒 | C116: 白酒-浓香型 | D116: 50°五粮醇红淡雅500ml | E116: 500ml*6 | F116: 瓶 | G116: 101010109 | H116: 156 | I116: 69 | J116: 10764 | K116: 9331.8528 | L116: 1432.1472 | M116: 0.133 | N116: 102 | O116: 17
B117: 白酒 | C117: 白酒-清香型 | D117: 45°杏花村福酒五(225ml*2) | E117: 225ml*2*6 | F117: 盒 | G117: 101010072 | H117: 185 | I117: 58.05 | J117: 10740 | K117: 6451.1614 | L117: 4288.8386 | M117: 0.3993 | N117: 131 | O117: 22
B118: 白酒 | C118: 白酒-浓香型 | D118: 50°五粮春500ml | E118: 500ml*6 | F118: 瓶 | G118: 101010494 | H118: 40 | I118: 268 | J118: 10720 | K118: 7463.3408 | L118: 3256.6592 | M118: 0.3037 | N118: 28 | O118: 13
B119: 白酒 | C119: 白酒-凤香型 | D119: 45°酒海窖龄西凤酒10年 500ml | E119: 500ml*6 | F119: 瓶 | G119: 101050015 | H119: 68 | I119: 152.72 | J119: 10385 | K119: 8024 | L119: 2361 | M119: 0.2273 | N119: 39 | O119: 17
B120: 白酒 | C120: 白酒-凤香型 | D120: 45°道远太白30年 500ml | E120: 500ml*6 | F120: 瓶 | G120: 101050011 | H120: 83 | I120: 122.23 | J120: 10145 | K120: 7421.456 | L120: 2723.544 | M120: 0.2684 | N120: 31 | O120: 16
B121: 白酒 | C121: 白酒-清香型 | D121: 52°红星青花瓷珍品二锅头750ml | E121: 750ml*6 | F121: 瓶 | G121: 101010321 | H121: 36 | I121: 280 | J121: 10080 | K121: 7560 | L121: 2520 | M121: 0.25 | N121: 1 | O121: 1
B122: 白酒 | C122: 白酒-清香型 | D122: 42°北京二锅头酒（出口型小方瓶）500ml | F122: 瓶 | G122: 101030036 | H122: 351 | I122: 28.02 | J122: 9834 | K122: 5478.4581 | L122: 4355.5419 | M122: 0.4429 | N122: 211 | O122: 20
B123: 白酒 | C123: 白酒-凤香型 | D123: 45°1956西凤酒玉石藏500ml | E123: 500ml*6 | F123: 瓶 | G123: 101050005 | H123: 55 | I123: 178 | J123: 9790 | K123: 6999.4757 | L123: 2790.5243 | M123: 0.285 | N123: 41 | O123: 17
B124: 白酒 | C124: 白酒-凤香型 | D124: 45°老陕西凤酒唐500ml | E124: 500ml*6 | F124: 瓶 | G124: 101050009 | H124: 52 | I124: 188 | J124: 9776 | K124: 6810.5109 | L124: 2965.4891 | M124: 0.3033 | N124: 41 | O124: 16
B125: 白酒 | C125: 白酒-酱香型 | D125: 53°仁怀酱香酒-仁之信500ml | E125: 500ml*6 | F125: 瓶 | G125: 101020111 | H125: 36 | I125: 269 | J125: 9684 | K125: 3672 | L125: 6012 | M125: 0.6208 | N125: 26 | O125: 18
B126: 白酒 | C126: 白酒-浓酱兼香型 | D126: 53°白云边三星500ml | E126: 500ml*6 | F126: 瓶 | G126: 101010037 | H126: 148 | I126: 65 | J126: 9620 | K126: 5796.7698 | L126: 3823.2302 | M126: 0.3974 | N126: 102 | O126: 17
B127: 白酒 | C127: 白酒-凤香型 | D127: 45°老陕西凤酒380ml | E127: 380*20 | F127: 瓶 | G127: 101050010 | H127: 275 | I127: 34.59 | J127: 9513 | K127: 6546.4626 | L127: 2966.5374 | M127: 0.3118 | N127: 133 | O127: 20
B128: 白酒 | C128: 白酒-浓香型 | D128: 46°双沟大曲500ml | E128: 500ml*6 | F128: 瓶 | G128: 101010084 | H128: 214 | I128: 42 | J128: 8988 | K128: 5860.0674 | L128: 3127.9326 | M128: 0.348 | N128: 163 | O128: 20
B129: 白酒 | C129: 白酒-清香型 | D129: 56°炸弹二锅头100ml | E129: 100ml*20 | F129: 瓶 | G129: 101010156 | H129: 1503 | I129: 5.9 | J129: 8867.3 | K129: 5690.5025 | L129: 3176.7975 | M129: 0.3582 | N129: 541 | O129: 22
B130: 白酒 | C130: 白酒-清香型 | D130: 42°北京二锅头酒（蓝色版）500ml | E130: 500ml*12 | F130: 瓶 | G130: 101030045 | H130: 353 | I130: 24.03 | J130: 8484 | K130: 5433.491 | L130: 3050.509 | M130: 0.3595 | N130: 217 | O130: 22
B131: 白酒 | C131: 白酒-浓香型 | D131: 52°金剑南鉴藏500ml | E131: 500ml*6 | F131: 瓶 | G131: 101010466 | H131: 37 | I131: 224.76 | J131: 8316 | K131: 5656.8268 | L131: 2659.1732 | M131: 0.3197 | N131: 23 | O131: 13
B132: 白酒 | C132: 白酒-凤香型 | D132: 45°老陕西凤酒秦500ml | E132: 500ml*6 | F132: 瓶 | G132: 101050008 | H132: 28 | I132: 294.14 | J132: 8236 | K132: 6533.415 | L132: 1702.585 | M132: 0.2067 | N132: 17 | O132: 11
B133: 白酒 | C133: 白酒-浓香型 | D133: 52°文君酒500ml | E133: 500ml*6 | F133: 瓶 | G133: 101010008 | H133: 15 | I133: 516 | J133: 7740 | K133: 5152.3217 | L133: 2587.6783 | M133: 0.3343 | N133: 5 | O133: 3
B134: 白酒 | C134: 白酒-浓香型 | D134: 46°剑小绵150ml | E134: 150ml*20 | F134: 瓶 | G134: 101010450 | H134: 1409 | I134: 5.34 | J134: 7519 | K134: 5773.3861 | L134: 1745.6139 | M134: 0.2321 | N134: 444 | O134: 22
... B145: 白酒 | C145: 白酒-酱香型 | D145: 53°仁怀酱香酒-仁之义500ml | E145: 500ml*6 | F145: 瓶 | G145: 101020113 | H145: 2 | I145: 599 | J145: 1198 | K145: 350 | L145: 848 | M145: 0.7078 | N145: 2 | O145: 2

Sheet 徐州
B2: 商品大类 | C2: 商品类别 | D2: 商品名称 | E2: 规格 | F2: 单位 | G2: 商品编码 | H2: 数量 | I2: 成交均价 | J2: 销售额 | K2: 成本 | L2: 毛利 | M2: 毛利率 | N2: 单品客流量 | O2: 销售门店数
H3: 27695 | I3: 159.6969 | J3: 4422805.6 | K3: 3871153.2 | L3: 551652.45 | O3: 755
B4: 白酒 | C4: 白酒-酱香型 | D4: 53°飞天茅台酒500ml | E4: 500ml*6 | F4: 瓶 | G4: 101010185 | H4: 750 | I4: 1535.8 | J4: 1151853 | K4: 1031076.1 | L4: 120776.91 | M4: 0.1048 | N4: 157 | O4: 8
B5: 白酒 | C5: 白酒-浓香型 | D5: 42°洋河蓝色经典海之蓝480ml | E5: 480ml*6 | F5: 瓶 | G5: 101010255 | H5: 3615 | I5: 121.45 | J5: 439031 | K5: 418252.33 | L5: 20778.669 | M5: 0.0473 | N5: 1126 | O5: 12
B6: 白酒 | C6: 白酒-浓香型 | D6: 52°五粮液普装500ml | E6: 500ml*6 | F6: 瓶 | G6: 101010001 | H6: 470 | I6: 867.72 | J6: 407828 | K6: 384679.32 | L6: 23148.684 | M6: 0.0567 | N6: 85 | O6: 9
B7: 白酒 | C7: 白酒 | D7: 42°国缘对开500ml | E7: 500ml*6 | F7: 瓶 | G7: 101020077 | H7: 762 | I7: 282.6 | J7: 215344 | K7: 198183.07 | L7: 17160.933 | M7: 0.0796 | N7: 222 | O7: 9
B8: 白酒 | C8: 白酒-浓香型 | D8: 42°洋河天之蓝480ml | F8: 瓶 | G8: 101020074 | H8: 613 | I8: 289.37 | J8: 177384 | K8: 167278.17 | L8: 10105.834 | M8: 0.0569 | N8: 178 | O8: 11
B9: 白酒 | C9: 白酒-浓香型 | D9: 52°五粮液1618 500ml | E9: 500ml*6 | F9: 瓶 | G9: 101010139 | H9: 179 | I9: 869.92 | J9: 155715 | K9: 145405.28 | L9: 10309.725 | M9: 0.0662 | N9: 19 | O9: 7
B10: 白酒 | C10: 白酒-浓香型 | D10: 41.8°+68°双沟珍宝坊君坊(480ml+20ml) | F10: 盒 | G10: 101020071 | H10: 1510 | I10: 89.21 | J10: 134708 | K10: 122867.24 | L10: 11840.765 | M10: 0.0878 | N10: 443 | O10: 12
B11: 白酒 | C11: 白酒-浓香型 | D11: 40.8°洋河梦之蓝M3 500ml | F11: 瓶 | G11: 101020073 | H11: 330 | I11: 393.72 | J11: 129929 | K11: 122972.21 | L11: 6956.7893 | M11: 0.0535 | N11: 105 | O11: 9
B12: 白酒 | C12: 白酒-浓香型 | D12: 52°水井坊臻酿八号500ml | E12: 500ml*6 | F12: 瓶 | G12: 101010495 | H12: 311 | I12: 317.11 | J12: 98621 | K12: 83322.827 | L12: 15298.173 | M12: 0.1551 | N12: 48 | O12: 8
B13: 白酒 | C13: 白酒-浓香型 | D13: 52°国窖1573 500ml | E13: 500ml*6 | F13: 瓶 | G13: 101010099 | H13: 113 | I13: 831.88 | J13: 94002 | K13: 83302.9 | L13: 10699.1 | M13: 0.1138 | N13: 19 | O13: 7
B14: 白酒 | C14: 白酒 | D14: 42°国缘四开500ml | F14: 瓶 | G14: 101020072 | H14: 216 | I14: 416.53 | J14: 89970 | K14: 83118.75 | L14: 6851.2505 | M14: 0.0761 | N14: 56 | O14: 8
B15: 白酒 | C15: 白酒-浓香型 | D15: 45°五粮春500ml | E15: 500ml*12 | F15: 瓶 | G15: 101010259 | H15: 499 | I15: 168 | J15: 83832 | K15: 78404.461 | L15: 5427.5395 | M15: 0.0647 | N15: 191 | O15: 11
B16: 白酒 | C16: 白酒其它 | D16: 40.8°洋河梦之蓝M6 500ml | E16: 500ml*6 | F16: 瓶 | G16: 101990013 | H16: 149 | I16: 523.97 | J16: 78071 | K16: 72504.49 | L16: 5566.5096 | M16: 0.0713 | N16: 45 | O16: 9
B17: 白酒 | C17: 白酒-清香型 | D17: 42°汾阳王10年500ml | E17: 500ml*6 | F17: 瓶 | G17: 101030021 | H17: 2162 | I17: 34.89 | J17: 75435 | K17: 54050 | L17: 21385 | M17: 0.2834 | N17: 512 | O17: 12
B18: 白酒 | C18: 白酒-浓香型 | D18: 52°剑南春普装500ml | E18: 500ml*6 | F18: 瓶 | G18: 101010002 | H18: 167 | I18: 387.87 | J18: 64774 | K18: 57323.026 | L18: 7450.9735 | M18: 0.115 | N18: 43 | O18: 6
B19: 白酒 | C19: 白酒-浓香型 | D19: 42°百年迎驾贡典藏450ml | E19: 450ml*4 | F19: 瓶 | G19: 101020083 | H19: 842 | I19: 63.07 | J19: 53108 | K19: 43660.386 | L19: 9447.6138 | M19: 0.1778 | N19: 335 | O19: 10
B20: 白酒 | C20: 白酒-酱香型 | D20: 40.8°口子窖五年400ml | E20: 400ml *6 | F20: 瓶 | G20: 101010299 | H20: 501 | I20: 90.38 | J20: 45282 | K20: 40536.327 | L20: 4745.673 | M20: 0.1048 | N20: 221 | O20: 10
B21: 白酒 | C21: 白酒-浓香型 | D21: 42°今世缘典藏10年500ml | F21: 瓶 | G21: 101020075 | H21: 447 | I21: 93.09 | J21: 41612 | K21: 37700.479 | L21: 3911.5206 | M21: 0.0939 | N21: 72 | O21: 8
B22: 白酒 | C22: 白酒-浓香型 | D22: 42°国缘淡雅500ml | E22: 500ml*6 | F22: 瓶 | G22: 101020128 | H22: 308 | I22: 126.86 | J22: 39072 | K22: 32648 | L22: 6424 | M22: 0.1644 | N22: 115 | O22: 9
B23: 白酒 | C23: 白酒-浓香型 | D23: 42°三星百年迎驾贡450ml | E23: 450ml*6 | F23: 瓶 | G23: 101020082 | H23: 751 | I23: 47.62 | J23: 35762 | K23: 31451.154 | L23: 4310.8458 | M23: 0.1205 | N23: 460 | O23: 11
B24: 白酒 | C24: 白酒-浓香型 | D24: 52°五粮液100年传奇柔和500ml | E24: 500ml*6 | F24: 瓶 | G24: 101010526 | H24: 621 | I24: 55.26 | J24: 34319 | K24: 20613.625 | L24: 13705.376 | M24: 0.3993 | N24: 128 | O24: 11
B25: 白酒 | C25: 白酒-清香型 | D25: 53°汾酒20年青花500ml | E25: 500ml*6 | F25: 瓶 | G25: 101010192 | H25: 88 | I25: 382.73 | J25: 33680 | K25: 30120.068 | L25: 3559.9317 | M25: 0.1056 | N25: 23 | O25: 6
B26: 白酒 | C26: 白酒-浓香型 | D26: 52°水井坊井台装500ml | E26: 500ml*6 | F26: 瓶 | G26: 101010006 | H26: 67 | I26: 473.15 | J26: 31701 | K26: 27749.682 | L26: 3951.3182 | M26: 0.1246 | N26: 16 | O26: 7
B27: 白酒 | C27: 白酒-浓香型 | D27: 52°五粮液戊戌（狗）年生肖纪念酒礼盒 | E27: 500ml*4*1 | F27: 盒 | G27: 101010523 | H27: 29 | I27: 1068.55 | J27: 30988 | K27: 20824.615 | L27: 10163.385 | M27: 0.3279 | N27: 19 | O27: 6
B28: 白酒 | C28: 白酒-浓香型 | D28: 52°泸州窖酒陶坛老酒500ml | E28: 500ml*6 | F28: 瓶 | G28: 101010421 | H28: 199 | I28: 153.23 | J28: 30492 | K28: 17826.923 | L28: 12665.077 | M28: 0.4153 | N28: 109 | O28: 8
B29: 白酒 | C29: 白酒-清香型 | D29: 53°汾酒30年青花500ml | E29: 500ml*6 | F29: 瓶 | G29: 101010068 | H29: 58 | I29: 515.31 | J29: 29888 | K29: 25812.071 | L29: 4075.9293 | M29: 0.1363 | N29: 6 | O29: 3
B30: 白酒 | C30: 白酒-浓香型 | D30: 52°绵竹大曲窖藏500ml | E30: 500ml*6 | F30: 瓶 | G30: 101010456 | H30: 981 | I30: 29.18 | J30: 28623 | K30: 19567.911 | L30: 9055.0895 | M30: 0.3163 | N30: 263 | O30: 10
B31: 白酒 | C31: 白酒-酱香型 | D31: 53°红花郎10年500ml | E31: 500ml*6 | F31: 瓶 | G31: 101010053 | H31: 85 | I31: 332.07 | J31: 28226 | K31: 23162.427 | L31: 5063.5732 | M31: 0.1793 | N31: 25 | O31: 6
B32: 白酒 | C32: 白酒-酱香型 | D32: 43°飞天茅台500ml | E32: 500ml*6 | F32: 瓶 | G32: 101010290 | H32: 28 | I32: 988.5 | J32: 27678 | K32: 18701.569 | L32: 8976.4308 | M32: 0.3243 | N32: 11 | O32: 6
B33: 白酒 | C33: 白酒其它 | D33: *52°酒鬼酒（天工开物/馥郁天成）1L | E33: 1L*6 | F33: 瓶 | G33: 101990008 | H33: 96 | I33: 285.96 | J33: 27452 | K33: 18077.13 | L33: 9374.8699 | M33: 0.3415 | N33: 40 | O33: 9
... B40: 白酒 | C40: 白酒-清香型 | D40: 53°老白汾酒特制十年475ml | E40: 475ml*6 | F40: 瓶 | G40: 101010071 | H40: 128 | I40: 139.06 | J40: 17800 | K40: 14034.308 | L40: 3765.6922 | M40: 0.2115 | N40: 47 | O40: 8
B41: 白酒 | C41: 白酒-浓香型 | D41: 42°习酒虹钻500ml | F41: 瓶 | G41: 101020065 | H41: 157 | I41: 113.34 | J41: 17795 | K41: 10861.368 | L41: 6933.6323 | M41: 0.3896 | N41: 39 | O41: 7
B42: 白酒 | C42: 白酒-浓香型 | D42: 50°五粮醇3D 500ml | E42: 500ml*6 | F42: 瓶 | G42: 101010108 | H42: 379 | I42: 45.92 | J42: 17405 | K42: 14469.806 | L42: 2935.1939 | M42: 0.1686 | N42: 141 | O42: 10
B43: 白酒 | C43: 白酒-清香型 | D43: *52°汾酒清香酒海475ml | E43: 475ml*6 | F43: 瓶 | G43: 101030015 | H43: 235 | I43: 66.94 | J43: 15731 | K43: 10046.935 | L43: 5684.0654 | M43: 0.3613 | N43: 65 | O43: 9
B44: 白酒 | C44: 白酒-浓香型 | D44: 50°五粮春500ml | E44: 500ml*6 | F44: 瓶 | G44: 101010494 | H44: 58 | I44: 214.28 | J44: 12428 | K44: 10490.435 | L44: 1937.5649 | M44: 0.1559 | N44: 25 | O44: 8
B45: 白酒 | C45: 白酒-浓香型 | D45: *52°全兴1963 500ml | E45: 500ml*12 | F45: 瓶 | G45: 101010454 | H45: 303 | I45: 40.63 | J45: 12311 | K45: 7441.693 | L45: 4869.307 | M45: 0.3955 | N45: 130 | O45: 9
B46: 白酒 | C46: 白酒-浓香型 | D46: 42°牛栏山陈酿白酒500ml | E46: 500ml*12 | F46: 瓶 | G46: 101030011 | H46: 926 | I46: 12.89 | J46: 11939.8 | K46: 9712.8327 | L46: 2226.9673 | M46: 0.1865 | N46: 458 | O46: 11
B47: 白酒 | C47: 白酒-浓香型 | D47: 52°舍得酒500ml（HN） | E47: 500ml*6 | F47: 瓶 | G47: 101010019 | H47: 26 | I47: 421.5 | J47: 10959 | K47: 9019.9041 | L47: 1939.0959 | M47: 0.1769 | N47: 12 | O47: 6
B48: 白酒 | C48: 白酒-酱香型 | D48: 53°习酒银质500ml | E48: 500ml*6 | F48: 瓶 | G48: 101020010 | H48: 87 | I48: 125.52 | J48: 10920 | K48: 6945.0246 | L48: 3974.9754 | M48: 0.364 | N48: 42 | O48: 11
B49: 白酒 | C49: 白酒-浓香型 | D49: 46°剑小绵150ml | E49: 150ml*20 | F49: 瓶 | G49: 101010450 | H49: 2047 | I49: 5.27 | J49: 10782 | K49: 8533.2261 | L49: 2248.7739 | M49: 0.2085 | N49: 349 | O49: 12
B50: 白酒 | C50: 白酒-浓香型 | D50: 50°古井贡酒年份原浆5年500ml | E50: 500ml*6 | F50: 瓶 | G50: 101010422 | H50: 72 | I50: 136.5 | J50: 9828 | K50: 8147.7428 | L50: 1680.2572 | M50: 0.1709 | N50: 32 | O50: 8
B51: 白酒 | C51: 白酒-浓香型 | D51: 52°泸州老窖头曲500ml | E51: 500ml*6 | F51: 瓶 | G51: 101010024 | H51: 139 | I51: 61.09 | J51: 8492 | K51: 5234.7051 | L51: 3257.2949 | M51: 0.3835 | N51: 69 | O51: 10
B52: 白酒 | C52: 白酒-酱香型 | D52: 53°茅台王子酒500ml | E52: 500ml*6 | F52: 瓶 | G52: 101010107 | H52: 72 | I52: 116.82 | J52: 8411 | K52: 6166.2734 | L52: 2244.7266 | M52: 0.2668 | N52: 15 | O52: 6
B53: 白酒 | C53: 白酒其它 | D53: 40°江小白100ml | E53: 100ml*24 | F53: 瓶 | G53: 101990007 | H53: 459 | I53: 17.94 | J53: 8236.5 | K53: 5285.2808 | L53: 2951.2192 | M53: 0.3583 | N53: 193 | O53: 10
... B57: 白酒 | C57: 白酒-浓香型 | D57: 52°五粮液丁酉（鸡）年生肖纪念酒礼盒 | E57: 500ml*4*1 | F57: 盒 | G57: 101010524 | H57: 8 | I57: 969.5 | J57: 7756 | K57: 4789.7436 | L57: 2966.2564 | M57: 0.3824 | N57: 7 | O57: 4
B58: 白酒 | C58: 白酒-浓香型 | D58: 41.8°今世缘典藏15年500ml | F58: 瓶 | G58: 101020076 | H58: 42 | I58: 176.48 | J58: 7412 | K58: 5864.3516 | L58: 1547.6484 | M58: 0.2088 | N58: 11 | O58: 7
B59: 白酒 | C59: 白酒-浓香型 | D59: 42°习酒铂钻500ml | F59: 瓶 | G59: 101020066 | H59: 26 | I59: 265.85 | J59: 6912 | K59: 3599.7314 | L59: 3312.2686 | M59: 0.4792 | N59: 14 | O59: 5
B60: 白酒 | C60: 白酒-浓酱兼香型 | D60: 41°六年口子窖450ml | E60: 450ml*6 | F60: 瓶 | G60: 101020084 | H60: 44 | I60: 155.55 | J60: 6844 | K60: 5035.4275 | L60: 1808.5725 | M60: 0.2642 | N60: 17 | O60: 8
B61: 白酒 | C61: 白酒-浓香型 | D61: 52°金剑南K6 500ml | E61: 500ml*6 | F61: 瓶 | G61: 101010227 | H61: 51 | I61: 125.18 | J61: 6384 | K61: 5373.3843 | L61: 1010.6157 | M61: 0.1583 | N61: 25 | O61: 8
B62: 白酒 | C62: 白酒-浓香型 | D62: 52°金剑南1号藏品500ml | E62: 500ml*6 | F62: 瓶 | G62: 101010465 | H62: 37 | I62: 160.3 | J62: 5931 | K62: 3054.6838 | L62: 2876.3162 | M62: 0.4849 | N62: 19 | O62: 7
B63: 白酒 | C63: 白酒-浓香型 | D63: 52°五粮特曲500ml | E63: 500ml*6 | F63: 瓶 | G63: 101010230 | H63: 31 | I63: 190.32 | J63: 5900 | K63: 4406.3681 | L63: 1493.6319 | M63: 0.2531 | N63: 11 | O63: 5
B64: 白酒 | C64: 白酒-浓香型 | D64: 52°百年泸州老窖酒窖龄60年500ml | E64: 500ml*6 | F64: 瓶 | G64: 101010115 | H64: 22 | I64: 268 | J64: 5896 | K64: 4389.744 | L64: 1506.256 | M64: 0.2554 | N64: 10 | O64: 4
B65: 白酒 | C65: 白酒-清香型 | D65: 53°汾酒蓝瓷475ml | E65: 475ml*6 | F65: 瓶 | G65: 101010069 | H65: 47 | I65: 125.43 | J65: 5895 | K65: 4641.7124 | L65: 1253.2876 | M65: 0.2126 | N65: 12 | O65: 5
B66: 白酒 | C66: 白酒其它 | D66: 54°湘泉盒优500ml | E66: 500ml*6 | F66: 瓶 | G66: 101010461 | H66: 166 | I66: 33.22 | J66: 5514 | K66: 3447.8266 | L66: 2066.1734 | M66: 0.3747 | N66: 60 | O66: 9
B67: 白酒 | C67: 白酒-浓香型 | D67: *52°全兴古酿500ml | E67: 500ml*6 | F67: 瓶 | G67: 101010486 | H67: 29 | I67: 188 | J67: 5452 | K67: 2738.7606 | L67: 2713.2394 | M67: 0.4976 | N67: 14 | O67: 5
B68: 白酒 | C68: 白酒-浓香型 | D68: *52°五粮液虎符令酒500ml | E68: 500ml*6 | F68: 瓶 | G68: 101010530 | H68: 4 | I68: 1324.5 | J68: 5298 | K68: 3509.7436 | L68: 1788.2564 | M68: 0.3375 | N68: 2 | O68: 2
B69: 白酒 | C69: 白酒-浓香型 | D69: 52°习酒天辰500ml | F69: 瓶 | G69: 101020067 | H69: 14 | I69: 363.71 | J69: 5092 | K69: 3043.1452 | L69: 2048.8548 | M69: 0.4023 | N69: 5 | O69: 2
B70: 白酒 | C70: 白酒-浓香型 | D70: 52°孔府家酒高陶500ml | E70: 500ml*6 | F70: 瓶 | G70: 101010472 | H70: 138 | I70: 36.3 | J70: 5010 | K70: 2883.1016 | L70: 2126.8984 | M70: 0.4245 | N70: 60 | O70: 9
B71: 白酒 | C71: 白酒-清香型 | D71: 50°牛栏山特制精品二锅头450ml | E71: 450ml*6 | F71: 瓶 | G71: 101010093 | H71: 63 | I71: 69.37 | J71: 4370 | K71: 2887.3764 | L71: 1482.6236 | M71: 0.3392 | N71: 27 | O71: 8
B72: 白酒 | C72: 白酒-清香型 | D72: 53°汾酒紫砂陶475ml | E72: 475ml*6 | F72: 瓶 | G72: 101010070 | H72: 41 | I72: 101.93 | J72: 4179 | K72: 2980.1609 | L72: 1198.8391 | M72: 0.2868 | N72: 29 | O72: 9
B73: 白酒 | C73: 白酒 | D73: 46°濉溪老口子450ml | E73: 450ml*6 | F73: 瓶 | G73: 101020086 | H73: 68 | I73: 55.04 | J73: 3743 | K73: 2705.2985 | L73: 1037.7015 | M73: 0.2772 | N73: 42 | O73: 9
B74: 白酒 | C74: 白酒-浓香型 | D74: 46°双沟大曲500ml | E74: 500ml*6 | F74: 瓶 | G74: 101010084 | H74: 84 | I74: 38.29 | J74: 3216 | K74: 2299.1258 | L74: 916.8742 | M74: 0.285 | N74: 41 | O74: 6
B75: 白酒 | C75: 白酒其它 | D75: 35°中国劲酒258ml | E75: 258ml*15 | F75: 瓶 | G75: 101010147 | H75: 139 | I75: 23.02 | J75: 3199.8 | K75: 2449.6192 | L75: 750.1808 | M75: 0.2344 | N75: 98 | O75: 8
B76: 白酒 | C76: 白酒-浓香型 | D76: 52°珍品级绵竹大曲蓝盒475ml | E76: 475ml*6 | F76: 瓶 | G76: 101010400 | H76: 58 | I76: 54.5 | J76: 3161 | K76: 1853.5385 | L76: 1307.4615 | M76: 0.4136 | N76: 23 | O76: 6
B77: 白酒 | C77: 白酒-酱香型 | D77: 53°习酒红盒 500ml | E77: 500ml*6 | F77: 瓶 | G77: 101020006 | H77: 38 | I77: 82.63 | J77: 3140 | K77: 2007.86 | L77: 1132.14 | M77: 0.3605 | N77: 21 | O77: 7
B78: 白酒 | C78: 白酒其它 | D78: 46°+70°仰韶彩陶坊人和(450m+50ml） | E78: (450ml+50ml)*6 | F78: 瓶 | G78: 101010105 | H78: 30 | I78: 102.47 | J78: 3074 | K78: 2640 | L78: 434 | M78: 0.1411 | N78: 13 | O78: 7
B79: 白酒 | C79: 白酒-酱香型 | D79: 53°飞天茅台酒375ml | E79: 375ml*12 | F79: 瓶 | G79: 101020107 | H79: 2 | I79: 1499 | J79: 2998 | K79: 2660 | L79: 338 | M79: 0.1127 | N79: 1 | O79: 1
B80: 白酒 | C80: 白酒-酱香型 | D80: 53°仁怀酱香酒-仁之义500ml | E80: 500ml*6 | F80: 瓶 | G80: 101020113 | H80: 5 | I80: 599 | J80: 2995 | K80: 875 | L80: 2120 | M80: 0.7078 | N80: 3 | O80: 3
B81: 白酒 | C81: 白酒-清香型 | D81: 56°牛栏山裸瓶500ml | E81: 500ml*12 | F81: 瓶 | G81: 101010154 | H81: 254 | I81: 11.5 | J81: 2922 | K81: 2217.279 | L81: 704.721 | M81: 0.2411 | N81: 133 | O81: 9
B82: 白酒 | C82: 白酒-清香型 | D82: 56°炸弹二锅头100ml | E82: 100ml*20 | F82: 瓶 | G82: 101010156 | H82: 487 | I82: 5.96 | J82: 2904.7 | K82: 1842.0894 | L82: 1062.6106 | M82: 0.3658 | N82: 125 | O82: 10
B83: 白酒 | C83: 白酒-浓香型 | D83: 42°迎驾贡酒大乐450ml | F83: 瓶 | G83: 101020069 | H83: 107 | I83: 24.82 | J83: 2656 | K83: 2021.4696 | L83: 634.5304 | M83: 0.2389 | N83: 68 | O83: 7
B84: 白酒 | C84: 白酒-浓香型 | D84: 52°百年泸州老窖酒窖龄30年500ml | E84: 500ml*6 | F84: 瓶 | G84: 101010114 | H84: 12 | I84: 218 | J84: 2616 | K84: 1970.1282 | L84: 645.8718 | M84: 0.2468 | N84: 6 | O84: 3
B85: 白酒 | C85: 白酒-浓香型 | D85: 52°习酒3年陈酿500ml | E85: 500ml*6 | F85: 瓶 | G85: 101010493 | H85: 28 | I85: 89.71 | J85: 2512 | K85: 888.889 | L85: 1623.111 | M85: 0.6461 | N85: 10 | O85: 6
B86: 白酒 | C86: 白酒-浓香型 | D86: 50°古井贡酒年份原浆8年500ml | E86: 500ml*6 | F86: 瓶 | G86: 101010441 | H86: 10 | I86: 238 | J86: 2380 | K86: 2054.614 | L86: 325.386 | M86: 0.1367 | N86: 4 | O86: 4
B87: 白酒 | C87: 白酒-浓香型 | D87: 52°吴窖银樽酒500ml | E87: 500ml*6 | F87: 瓶 | G87: 101010520 | H87: 9 | I87: 258 | J87: 2322 | K87: 1224 | L87: 1098 | M87: 0.4728 | N87: 5 | O87: 3
B88: 白酒 | C88: 白酒-浓香型 | D88: 35°中国劲酒125ml | E88: 125ml*24 | F88: 瓶 | G88: 101010111 | H88: 190 | I88: 12.05 | J88: 2289 | K88: 1651.879 | L88: 637.121 | M88: 0.2783 | N88: 131 | O88: 10
B89: 白酒 | C89: 白酒-清香型 | D89: 45°杏花村福酒五(225ml*2) | E89: 225ml*2*6 | F89: 盒 | G89: 101010072 | H89: 40 | I89: 56.4 | J89: 2255.8 | K89: 1393.9382 | L89: 861.8618 | M89: 0.382 | N89: 23 | O89: 8
B90: 白酒 | C90: 白酒-浓香型 | D90: 42°今世缘典藏5年500ml | F90: 瓶 | G90: 101020078 | H90: 27 | I90: 80 | J90: 2160 | K90: 1681.6239 | L90: 478.3761 | M90: 0.2214 | N90: 13 | O90: 6
B91: 白酒 | C91: 白酒其它 | D91: 45°竹叶青酒牧童475ml | E91: 475ml*6 | F91: 瓶 | G91: 101990006 | H91: 39 | I91: 52 | J91: 2028 | K91: 1485.4591 | L91: 542.5409 | M91: 0.2675 | N91: 29 | O91: 7
B92: 白酒 | C92: 白酒-清香型 | D92: 50°汾阳王青花10年500ml | E92: 500ml*6 | F92: 瓶 | G92: 101030018 | H92: 30 | I92: 65.87 | J92: 1976 | K92: 1045.513 | L92: 930.487 | M92: 0.4708 | N92: 12 | O92: 6
B93: 白酒 | C93: 白酒-清香型 | D93: 38°竹叶青酒金象500ml | E93: 500ml*6 | F93: 瓶 | G93: 101010075 | H93: 18 | I93: 95 | J93: 1710 | K93: 1068.0823 | L93: 641.9177 | M93: 0.3753 | N93: 14 | O93: 7
B94: 白酒 | C94: 白酒-浓香型 | D94: *52°孔府家酒朋自远方6 500ml | E94: 500ml*6 | F94: 瓶 | G94: 101010475 | H94: 9 | I94: 188 | J94: 1692 | K94: 556.4103 | L94: 1135.5897 | M94: 0.6711 | N94: 7 | O94: 5
B95: 白酒 | C95: 白酒-浓香型 | D95: 42°习酒双喜500ml | F95: 瓶 | G95: 101020068 | H95: 14 | I95: 118 | J95: 1652 | K95: 834.8718 | L95: 817.1282 | M95: 0.4946 | N95: 3 | O95: 2
B96: 白酒 | C96: 白酒-浓香型 | D96: 50°五粮醇红淡雅500ml | E96: 500ml*6 | F96: 瓶 | G96: 101010109 | H96: 22 | I96: 74.36 | J96: 1636 | K96: 1314.4754 | L96: 321.5246 | M96: 0.1965 | N96: 9 | O96: 5
B97: 白酒 | C97: 白酒-酱香型 | D97: 53°仁酒·和天下 500ml | E97: 500ml*6 | F97: 瓶 | G97: 101020125 | H97: 4 | I97: 388 | J97: 1552 | K97: 832 | L97: 720 | M97: 0.4639 | N97: 3 | O97: 2
B98: 白酒 | C98: 白酒-清香型 | D98: 52°牛栏山二锅头十八年陈酿500ml | E98: 500ml*6 | F98: 瓶 | G98: 101010094 | H98: 23 | I98: 65.7 | J98: 1511 | K98: 868.2957 | L98: 642.7043 | M98: 0.4253 | N98: 12 | O98: 7
B99: 白酒 | C99: 白酒-酱香型 | D99: 53°金沙大匠酒500ml | E99: 500ml*6 | F99: 瓶 | G99: 101010474 | H99: 3 | I99: 469.33 | J99: 1408 | K99: 598.2906 | L99: 809.7094 | M99: 0.575 | N99: 2 | O99: 2
B100: 白酒 | C100: 白酒其它 | D100: 46°+70°仰韶彩陶坊地利(450ml+50ml) | E100: (450ml+50ml)*6 | F100: 瓶 | G100: 101010104 | H100: 6 | I100: 200 | J100: 1200 | K100: 978 | L100: 222 | M100: 0.185 | N100: 1 | O100: 1
B101: 白酒 | C101: 白酒-清香型 | D101: 53°红星八年陈酿蓝瓶二锅头250ml | E101: 250ml*24 | F101: 瓶 | G101: 101030010 | H101: 56 | I101: 16.07 | J101: 900 | K101: 653.1805 | L101: 246.8195 | M101: 0.2742 | N101: 49 | O101: 7
B102: 白酒 | C102: 白酒-清香型 | D102: *43°红星蓝界酒500ml | E102: 500ml*12 | F102: 瓶 | G102: 101030016 | H102: 12 | I102: 68 | J102: 816 | K102: 464.6667 | L102: 351.3333 | M102: 0.4305 | N102: 9 | O102: 6
B103: 白酒 | C103: 白酒-浓香型 | D103: 42°迎驾贡酒小乐320ml | F103: 瓶 | G103: 101020070 | H103: 40 | I103: 20 | J103: 800 | K103: 556.4093 | L103: 243.5907 | M103: 0.3044 | N103: 37 | O103: 7
B104: 白酒 | C104: 白酒-清香型 | D104: 50°汾阳王15年500ml | E104: 500ml*6 | F104: 瓶 | G104: 101030024 | H104: 11 | I104: 70.91 | J104: 780 | K104: 550 | L104: 230 | M104: 0.2948 | N104: 4 | O104: 4
B105: 白酒 | C105: 白酒其它 | D105: 46°+70°仰韶彩陶坊献礼版（450ml+50ml） | E105: （450ml+50ml）*6 | F105: 瓶 | G105: 101990011 | H105: 8 | I105: 85 | J105: 680 | K105: 480 | L105: 200 | M105: 0.2941 | N105: 6 | O105: 4
B106: 白酒 | C106: 白酒-浓香型 | D106: *42°泸州老窖二曲白酒蓝瓶装 500ml | E106: 500ml*6 | F106: 瓶 | G106: 101010504 | H106: 21 | I106: 25 | J106: 525 | K106: 250.3586 | L106: 274.6414 | M106: 0.5231 | N106: 17 | O106: 5
B107: 白酒 | C107: 白酒-酱香型 | D107: 53°迎囍酒（银标）500ml | E107: 500ml*6 | F107: 瓶 | G107: 101020039 | H107: 6 | I107: 78 | J107: 468 | K107: 210 | L107: 258 | M107: 0.5512 | N107: 1 | O107: 1
B108: 白酒 | C108: 白酒-浓香型 | D108: 52°吴窖金樽酒500ml | E108: 500ml*6 | F108: 瓶 | G108: 101010519 | H108: 1 | I108: 458 | J108: 458 | K108: 223 | L108: 235 | M108: 0.5131 | N108: 1 | O108: 1
B109: 白酒 | C109: 白酒其它 | D109: 46°口子窖六年450ml | E109: 450ml *6 | F109: 瓶 | G109: 101010459 | H109: 0 | I109: 0 | J109: 0 | K109: 0 | L109: 0 | M109: 0 | N109: 1 | O109: 1
B110: 白酒 | C110: 白酒-酱香型 | D110: 53°迎囍酒（金标）500ml | E110: 500ml*6 | F110: 瓶 | G110: 101020038 | H110: 0 | I110: 0 | J110: 0 | K110: 0 | L110: 0 | M110: 0 | N110: 1 | O110: 1

Sheet 清洗
A1: 序号 | B1: 商品编码 | C1: 商品名称 | D1: 规格 | E1: 单价 | F1: 全年计划总量(瓶) | G1: 全年计划采购总金额 | H1: 成交价 | I1: 出库数量 | J1: 2017.11-2018.10出库金额 | K1: 出库数量 | L1: 2017.5-2017.10出库金额 | M1: 出库数量 | N1: 2018.5-2018.10出库金额 | O1: 地区
A2: 2 | B2: 101010099 | C2: 52°国窖1573 500ml | D2: 500ml*6 | E2: 740 | F2: 15600 | G2: 11544000 | H2: 830.06 | I2: 13122 | J2: 10892047 | K2: 5289 | L2: 4390187.3 | M2: 4995 | N2: 4146149.7 | O2: 河南
A3: 3 | B3: 101010114 | C3: *52°百年泸州老窖酒窖龄30年500ml | D3: 500ml*6 | E3: 165 | F3: 7812 | G3: 1288980 | H3: 210.82 | I3: 2770 | J3: 583971.4 | K3: 1131 | L3: 238437.42 | M3: 1269 | N3: 267530.58 | O3: 河南
A4: 4 | B4: 101010115 | C4: 52°百年泸州老窖酒窖龄60年500ml | D4: 500ml*6 | E4: 200 | F4: 15612 | G4: 3122400 | H4: 264.02 | I4: 5498 | J4: 1451582 | K4: 2544 | L4: 671666.88 | M4: 2334 | N4: 616222.68 | O4: 河南
A5: 7 | B5: 101010036 | C5: 52°泸州老窖特曲500ml | D5: 500ml*6 | E5: 168 | F5: 85020 | G5: 14283360 | H5: 203.03 | I5: 46072 | J5: 9353998.2 | K5: 21635 | L5: 4392554 | M5: 21280 | N5: 4320478.4 | O5: 河南
A6: 8 | B6: 101010024 | C6: 52°泸州老窖头曲500ml | D6: 500ml*6 | E6: 37.87 | F6: 39000 | G6: 1476930 | H6: 60.09 | I6: 21460 | J6: 1289531.4 | K6: 7817 | L6: 469723.53 | M6: 9236 | N6: 554991.24 | O6: 河南
A7: 9 | B7: 101010503 | C7: 52°泸州老窖精品头曲D9 500ml | D7: 500ml*6 | E7: 75 | F7: 7962 | G7: 597150 | H7: 144.86 | I7: 2772 | J7: 401551.92 | K7: 1804 | L7: 261327.44 | M7: 1505 | N7: 218014.3 | O7: 河南
A8: 10 | B8: 101010502 | C8: 52°泸州老窖精品头曲D6 500ml | D8: 500ml*6 | E8: 63 | F8: 15606 | G8: 983178 | H8: 94.45 | I8: 2731 | J8: 257942.95 | K8: 718 | L8: 67815.1 | M8: 1235 | N8: 116645.75 | O8: 河南
A9: 11 | B9: 101010501 | C9: *42°泸小二FOR ME（彩色）酒125ml | D9: 125ml*24 | E9: 11 | F9: 0 | G9: 0 | H9: 11.93 | I9: 6343 | J9: 75671.99 | K9: 3600 | L9: 42948 | M9: 1564 | N9: 18658.52 | O9: 河南
A10: 12 | B10: 101010504 | C10: 42°泸州老窖二曲白酒蓝瓶装 500ml | D10: 500ml*6 | E10: 12 | F10: 0 | G10: 0 | H10: 19.93 | I10: 1986 | J10: 39580.98 | K10: 743 | L10: 14807.99 | M10: 767 | N10: 15286.31 | O10: 河南
A11: 13 | B11: 101010521 | C11: 52°国窖1573曾娜大师鉴藏版500ml | D11: 500ml*6 | E11: 740 | F11: 0 | G11: 0 | H11: 928.61 | I11: 201 | J11: 186650.61 | M11: 82 | N11: 76146.02 | O11: 河南
A12: 14 | B12: 101010525 | C12: 52°泸州老窖2018农历戊戌年金狗佑财1.088L | D12: 1.088L*3 | E12: 468 | F12: 0 | G12: 0 | H12: 408.05 | I12: 112 | J12: 45701.6 | M12: 25 | N12: 10201.25 | O12: 河南
A13: 15 | B13: 101020055 | C13: 52°泸州老窖中秋丁酉年节庆酒1L | D13: 1L*3 | E13: 268 | F13: 0 | G13: 0 | H13: 88.85 | I13: 261 | J13: 23189.85 | K13: 769 | L13: 68325.65 | M13: 46 | N13: 4087.1 | O13: 河南
A14: 16 | B14: 101020063 | C14: 53°国窖国韵1L | D14: 1L*1 | E14: 2220 | F14: 0 | G14: 0 | H14: 2536.98 | I14: 53 | J14: 134459.94 | M14: 49 | N14: 124312.02 | O14: 河南
A15: 竞品信息 | B15: 101010002 | C15: 52°剑南春普装500ml | D15: 500ml*6 | H15: =VLOOKUP(B15,河南!G:I,3,0) -> 379.66 | I15: 145885 | J15: =H15*I15 -> 55386699 | K15: 64698 | L15: 24563243 | M15: 66934 | N15: 25412162 | O15: 河南
A16: 竞品信息 | B16: 101010001 | C16: 52°五粮液普装500ml | D16: 500ml*6 | H16: =VLOOKUP(B16,河南!G:I,3,0) -> 879.83 | I16: 62803 | J16: =H16*I16 -> 55255963 | K16: 29753 | L16: 26177582 | M16: 27101 | N16: 23844273 | O16: 河南
A17: 竞品信息 | B17: 101010004 | C17: 52°洋河天之蓝480ml | D17: 480ml*6 | H17: =VLOOKUP(B17,河南!G:I,3,0) -> 346.05 | I17: 15225 | J17: =H17*I17 -> 5268611.2 | K17: 6887 | L17: 2383246.4 | M17: 7096 | N17: 2455570.8 | O17: 河南
A18: 竞品信息 | B18: 101010098 | C18: 52°洋河海之蓝480ml | D18: 480ml*6 | H18: =VLOOKUP(B18,河南!G:I,3,0) -> 145.4 | I18: 106074 | J18: =H18*I18 -> 15423160 | K18: 50409 | L18: =H18*K18 -> 7329468.6 | M18: 47800 | N18: =H18*M18 -> 6950120 | O18: 河南
A19: 1 | B19: 104020590 | C19: 舒富红葡萄酒750ml | D19: 750ml*6 | E19: 40.91 | F19: 53298 | G19: 2398410 | H19: 90.42 | I19: 56585 | J19: =E19*I19 -> 2314892.3 | K19: 3133 | L19: 283285.86 | M19: 19866 | N19: 1796283.7 | O19: 河南
A20: 2 | B20: 104020591 | C20: 希拉谷西拉红葡萄酒750ml | D20: 750ml*6 | E20: 90 | F20: 10008 | G20: 900720 | H20: 161.46 | I20: 14256 | J20: =E20*I20 -> 1283040 | K20: 1601 | L20: 258497.46 | M20: 10846 | N20: 1751195.2 | O20: 河南
A21: 3 | B21: 104020592 | C21: 希拉谷庄园西拉红葡萄酒750ml | D21: 750ml*6 | E21: 149 | F21: 7800 | G21: 1162200 | H21: 381.29 | I21: 794 | J21: =E21*I21 -> 118306 | K21: 790 | L21: 301219.1 | M21: 523 | N21: 199414.67 | O21: 河南
A22: 1 | B22: 101010397 | C22: 38°国窖1573 500ml | D22: 500ml*6 | E22: 530 | F22: 2880 | G22: 1526400 | H22: 654.03 | I22: 1628 | J22: 1064760.8 | K22: 1174 | L22: 767831.22 | M22: 1121 | N22: 733167.63 | O22: 北京
A23: 2 | B23: 101010099 | C23: 52°国窖1573 500ml | D23: 500ml*6 | E23: 740 | F23: 4890 | G23: 3618600 | H23: 824.19 | I23: 6445 | J23: 5311904.6 | K23: 1976 | L23: 1628599.4 | M23: 3602 | N23: 2968732.4 | O23: 北京
A24: 3 | B24: 101010114 | C24: *52°百年泸州老窖酒窖龄30年500ml | D24: 500ml*6 | E24: 165 | F24: 1140 | G24: 188100 | H24: 224.39 | I24: 1115 | J24: 250194.85 | K24: 241 | L24: 54077.99 | M24: 656 | N24: 147199.84 | O24: 北京
A25: 4 | B25: 101010115 | C25: 52°百年泸州老窖酒窖龄60年500ml | D25: 500ml*6 | E25: 200 | F25: 2640 | G25: 528000 | H25: 260.79 | I25: 2949 | J25: 769069.71 | K25: 782 | L25: 203937.78 | M25: 1387 | N25: 361715.73 | O25: 北京
A26: 5 | B26: 101010294 | C26: 38°泸州老窖泸州百年30年窖龄500ml | D26: 500ml*6 | E26: 145 | F26: 780 | G26: 113100 | H26: 200.19 | I26: 616 | J26: 123317.04 | K26: 353 | L26: 70667.07 | M26: 329 | N26: 65862.51 | O26: 北京
A27: 6 | B27: 101010297 | C27: 38°泸州老窖百年60年窖龄500ml | D27: 500ml*6 | E27: 180 | F27: 750 | G27: 135000 | H27: 240.7 | I27: 900 | J27: 216630 | K27: 359 | L27: 86411.3 | M27: 442 | N27: 106389.4 | O27: 北京
A28: 7 | B28: 101010036 | C28: 52°泸州老窖特曲500ml | D28: 500ml*6 | E28: 168 | F28: 3180 | G28: 534240 | H28: 210.81 | I28: 2451 | J28: 516695.31 | K28: 824 | L28: 173707.44 | M28: 1270 | N28: 267728.7 | O28: 北京
A29: 8 | B29: 101010024 | C29: 52°泸州老窖头曲500ml | D29: 500ml*6 | E29: 37.87 | F29: 1860 | G29: 70438.2 | H29: 61.43 | I29: 2092 | J29: 128511.56 | K29: 685 | L29: 42079.55 | M29: 1034 | N29: 63518.62 | O29: 北京
A30: 11 | B30: 101010501 | C30: *42°泸小二FOR ME（彩色）酒125ml | D30: 125ml*24 | E30: 11 | F30: 0 | G30: 0 | H30: 23.48 | I30: 1009 | J30: 23691.32 | K30: 526 | L30: 12350.48 | M30: 446 | N30: 10472.08 | O30: 北京
A31: 13 | B31: 101010521 | C31: 52°国窖1573曾娜大师鉴藏版500ml | D31: 500ml*6 | E31: 740 | F31: 0 | G31: 0 | H31: 952.33 | I31: 47 | J31: 44759.51 | M31: 47 | N31: 44759.51 | O31: 北京
A32: 15 | B32: 101020055 | C32: 52°泸州老窖中秋丁酉年节庆酒1L | D32: 1L*3 | E32: 268 | F32: 0 | G32: 0 | H32: 376.39 | I32: 32 | J32: 12044.48 | K32: 241 | L32: 90709.99 | M32: 14 | N32: 5269.46 | O32: 北京
A33: 16 | B33: 101020063 | C33: 53°国窖国韵1L | D33: 1L*1 | E33: 2220 | F33: 0 | G33: 0 | H33: 2918.67 | I33: 3 | J33: 8756.01 | M33: 3 | N33: 8756.01 | O33: 北京
A34: 竞品信息 | B34: 101010001 | C34: 52°五粮液普装500ml | D34: 500ml*6 | H34: 920.84 | I34: 10594 | J34: 9755379 | K34: 3578 | L34: 3294765.5 | M34: 5622 | N34: 5176962.5 | O34: 北京
A35: 竞品信息 | B35: 101010002 | C35: 52°剑南春普装500ml | D35: 500ml*6 | H35: 405.69 | I35: 8195 | J35: 3324629.5 | K35: 3662 | L35: 1485636.8 | M35: 4481 | N35: 1817896.9 | O35: 北京
A36: 竞品信息 | B36: 101010004 | C36: 52°洋河天之蓝480ml | D36: 480ml*6 | H36: 359 | I36: 286 | J36: 102674 | M36: 286 | N36: 102674 | O36: 北京
A37: 1 | B37: 104020590 | C37: 舒富红葡萄酒750ml | D37: 750ml*6 | E37: 40.91 | F37: 2400 | G37: 108000 | H37: 98.98 | I37: 7708 | J37: 762937.84 | K37: 200 | L37: 19796 | M37: 4509 | N37: 446300.82 | O37: 北京
A38: 2 | B38: 104020591 | C38: 希拉谷西拉红葡萄酒750ml | D38: 750ml*6 | E38: 90 | F38: 780 | G38: 70200 | H38: 230 | I38: 357 | J38: 82110 | K38: 15 | L38: 3450 | M38: 215 | N38: 49450 | O38: 北京
A39: 3 | B39: 104020592 | C39: 希拉谷庄园西拉红葡萄酒750ml | D39: 750ml*6 | E39: 149 | F39: 480 | G39: 71520 | H39: 396.43 | I39: 114 | J39: 45193.02 | K39: 10 | L39: 3964.3 | M39: 75 | N39: 29732.25 | O39: 北京
A40: 2 | B40: 101010099 | C40: 52°国窖1573 500ml | D40: 500ml*6 | E40: 740 | F40: 2760 | G40: 2042400 | H40: 822.69 | I40: 3297 | J40: =H40*I40 -> 2712408.9 | K40: 713 | L40: 586577.97 | M40: 1781 | N40: 1465210.9 | O40: 西安
A41: 3 | B41: 101010114 | C41: *52°百年泸州老窖酒窖龄30年500ml | D41: 500ml*6 | E41: 165 | F41: 1830 | G41: 301950 | H41: 204.38 | I41: 665 | J41: =H41*I41 -> 135912.7 | K41: 292 | L41: 59678.96 | M41: 313 | N41: 63970.94 | O41: 西安
A42: 4 | B42: 101010115 | C42: 52°百年泸州老窖酒窖龄60年500ml | D42: 500ml*6 | E42: 200 | F42: 1140 | G42: 228000 | H42: 273.45 | I42: 894 | J42: =H42*I42 -> 244464.3 | K42: 158 | L42: 43205.1 | M42: 404 | N42: 110473.8 | O42: 西安
A43: 7 | B43: 101010036 | C43: 52°泸州老窖特曲500ml | D43: 500ml*6 | E43: 168 | F43: 1620 | G43: 272160 | H43: 200.27 | I43: 1581 | J43: =H43*I43 -> 316626.87 | K43: 368 | L43: 73699.36 | M43: 965 | N43: 193260.55 | O43: 西安
A44: 8 | B44: 101010024 | C44: 52°泸州老窖头曲500ml | D44: 500ml*6 | E44: 37.87 | F44: 990 | G44: 37491.3 | H44: 54.37 | I44: 1476 | J44: =H44*I44 -> 80250.12 | K44: 149 | L44: 8101.13 | M44: 1169 | N44: 63558.53 | O44: 西安
A45: 11 | B45: 101010501 | C45: *42°泸小二FOR ME（彩色）酒125ml | D45: 125ml*24 | E45: 11 | F45: 0 | G45: 0 | H45: 17.75 | I45: 1366 | J45: =H45*I45 -> 24246.5 | K45: 306 | L45: 5431.5 | M45: 660 | N45: 11715 | O45: 西安
A46: 13 | B46: 101010521 | C46: 52°国窖1573曾娜大师鉴藏版500ml | D46: 500ml*6 | E46: 740 | F46: 0 | G46: 0 | H46: 967 | I46: 28 | J46: =H46*I46 -> 27076 | L46: 0 | M46: 28 | N46: 27076 | O46: 西安
A47: 15 | B47: 101020055 | C47: 52°泸州老窖中秋丁酉年节庆酒1L | D47: 1L*3 | E47: 268 | F47: 0 | G47: 0 | H47: 437.1 | I47: 32 | J47: =H47*I47 -> 13987.2 | K47: 77 | L47: 33656.7 | M47: 29 | N47: 12675.9 | O47: 西安
A48: 16 | B48: 101020063 | C48: 53°国窖国韵1L | D48: 1L*1 | E48: 2220 | F48: 0 | G48: 0 | H48: 2772.73 | I48: 11 | J48: =H48*I48 -> 30500.03 | M48: 11 | N48: 30500.03 | O48: 西安
A49: 竞品信息 | B49: 101010001 | C49: 52°五粮液普装500ml | D49: 500ml*6 | H49: 886.5 | I49: 5000 | J49: =H49*I49 -> 4432500 | K49: 961 | L49: 851926.5 | M49: 2603 | N49: 2307559.5 | O49: 西安
A50: 竞品信息 | B50: 101010002 | C50: 52°剑南春普装500ml | D50: 500ml*6 | H50: 382.5 | I50: 3699 | J50: =H50*I50 -> 1414867.5 | K50: 1089 | L50: 416542.5 | M50: 1685 | N50: 644512.5 | O50: 西安
A51: 竞品信息 | B51: 101010003 | C51: *46°洋河海之蓝480ml | D51: 480ml*6 | H51: 137.59 | I51: 1237 | J51: =H51*I51 -> 170198.83 | K51: 147 | L51: 20225.73 | M51: 651 | N51: 89571.09 | O51: 西安
A52: 1 | B52: 104020590 | C52: 舒富红葡萄酒750ml | D52: 750ml*6 | E52: 40.91 | F52: 2400 | G52: 108000 | H52: 91.83 | I52: 3923 | J52: =H52*I52 -> 360249.09 | K52: 24 | L52: 2203.92 | M52: 2624 | N52: 240961.92 | O52: 西安
A53: 2 | B53: 104020591 | C53: 希拉谷西拉红葡萄酒750ml | D53: 750ml*6 | E53: 90 | F53: 780 | G53: 70200 | H53: 147.25 | I53: 685 | J53: =H53*I53 -> 100866.25 | K53: 12 | L53: 1767 | M53: 583 | N53: 85846.75 | O53: 西安
A54: 3 | B54: 104020592 | C54: 希拉谷庄园西拉红葡萄酒750ml | D54: 750ml*6 | E54: 149 | F54: 480 | G54: 71520 | H54: 329.41 | I54: 78 | J54: =H54*I54 -> 25693.98 | K54: 8 | L54: 2635.28 | M54: 32 | N54: 10541.12 | O54: 西安
A55: 2 | B55: 101010099 | C55: 52°国窖1573 500ml | D55: 500ml*6 | E55: 740 | H55: 831.88 | I55: 113 | J55: =I55*H55 -> 94002.44 | M55: 75 | N55: 62391 | O55: 徐州
A56: 3 | B56: 101010114 | C56: *52°百年泸州老窖酒窖龄30年500ml | D56: 500ml*6 | E56: 165 | H56: 218 | I56: 12 | J56: =I56*H56 -> 2616 | M56: 7 | N56: 1526 | O56: 徐州
A57: 4 | B57: 101010115 | C57: 52°百年泸州老窖酒窖龄60年500ml | D57: 500ml*6 | E57: 200 | H57: 268 | I57: 28 | J57: =I57*H57 -> 7504 | M57: 12 | N57: 3216 | O57: 徐州
A58: 7 | B58: 101010036 | C58: 52°泸州老窖特曲500ml | D58: 500ml*6 | E58: 168 | H58: 209.95 | I58: 126 | J58: =I58*H58 -> 26453.7 | M58: 82 | N58: 17215.9 | O58: 徐州
A59: 8 | B59: 101010024 | C59: 52°泸州老窖头曲500ml | D59: 500ml*6 | E59: 37.87 | H59: 61.09 | I59: 144 | J59: =I59*H59 -> 8796.96 | M59: 94 | N59: 5742.46 | O59: 徐州
A60: 12 | B60: 101010504 | C60: 42°泸州老窖二曲白酒蓝瓶装 500ml | D60: 500ml*6 | E60: 12 | H60: 25 | I60: 22 | J60: =I60*H60 -> 550 | K60: 1 | L60: 25 | M60: 17 | N60: 425 | O60: 徐州
A61: 竞品信息 | B61: 101010001 | C61: 52°五粮液普装500ml | D61: 500ml*6 | H61: 867.72 | I61: 494 | J61: =I61*H61 -> 428653.68 | K61: 8 | L61: 6941.76 | M61: 333 | N61: 288950.76 | O61: 徐州
A62: 竞品信息 | B62: 101010255 | C62: 42°洋河蓝色经典海之蓝480ml | D62: 480ml*6 | H62: 121.45 | I62: 3680 | J62: =I62*H62 -> 446936 | K62: 2 | L62: 242.9 | M62: 2424 | N62: 294394.8 | O62: 徐州
A63: 竞品信息 | B63: 101010002 | C63: 52°剑南春普装500ml | D63: 500ml*6 | H63: 387.87 | I63: 167 | J63: =I63*H63 -> 64774.29 | M63: 100 | N63: 38787 | O63: 徐州
A64: 1 | B64: 104020590 | C64: 舒富红葡萄酒750ml | D64: 750ml*6 | E64: 40.91 | F64: 2400 | G64: 108000 | H64: 98.73 | I64: 410 | J64: =I64*H64 -> 40479.3 | M64: 351 | N64: 34654.23 | O64: 徐州

Sheet 透视表
C3: 数据
A4: 商品名称 | B4: 地区 | C4: 求和项:2017.11-2018.10出库金额 | D4: 求和项:2017.5-2017.10出库金额 | E4: 求和项:2018.5-2018.10出库金额
A5: *42°泸小二FOR ME（彩色）酒125ml | B5: 北京 | C5: 23691.32 | D5: 12350.48 | E5: 10472.08
A6: *42°泸小二FOR ME（彩色）酒125ml | B6: 河南 | C6: 75671.99 | D6: 42948 | E6: 18658.52
A7: *42°泸小二FOR ME（彩色）酒125ml | B7: 西安 | C7: 24246.5 | D7: 5431.5 | E7: 11715
A8: *46°洋河海之蓝480ml | B8: 西安 | C8: 170198.83 | D8: 20225.73 | E8: 89571.09
A9: *52°百年泸州老窖酒窖龄30年500ml | B9: 北京 | C9: 250194.85 | D9: 54077.99 | E9: 147199.84
A10: *52°百年泸州老窖酒窖龄30年500ml | B10: 河南 | C10: 583971.4 | D10: 238437.42 | E10: 267530.58
A11: *52°百年泸州老窖酒窖龄30年500ml | B11: 西安 | C11: 135912.7 | D11: 59678.96 | E11: 63970.94
A12: *52°百年泸州老窖酒窖龄30年500ml | B12: 徐州 | C12: 2616 | E12: 1526
A13: 38°国窖1573 500ml | B13: 北京 | C13: 1064760.8 | D13: 767831.22 | E13: 733167.63
A14: 38°泸州老窖百年60年窖龄500ml | B14: 北京 | C14: 216630 | D14: 86411.3 | E14: 106389.4
A15: 38°泸州老窖泸州百年30年窖龄500ml | B15: 北京 | C15: 123317.04 | D15: 70667.07 | E15: 65862.51
A16: 42°泸州老窖二曲白酒蓝瓶装 500ml | B16: 河南 | C16: 39580.98 | D16: 14807.99 | E16: 15286.31
A17: 42°泸州老窖二曲白酒蓝瓶装 500ml | B17: 徐州 | C17: 550 | D17: 25 | E17: 425
A18: 42°洋河蓝色经典海之蓝480ml | B18: 徐州 | C18: 446936 | D18: 242.9 | E18: 294394.8
A19: 52°百年泸州老窖酒窖龄60年500ml | B19: 北京 | C19: 769069.71 | D19: 203937.78 | E19: 361715.73
A20: 52°百年泸州老窖酒窖龄60年500ml | B20: 河南 | C20: 1451582 | D20: 671666.88 | E20: 616222.68
A21: 52°百年泸州老窖酒窖龄60年500ml | B21: 西安 | C21: 244464.3 | D21: 43205.1 | E21: 110473.8
A22: 52°百年泸州老窖酒窖龄60年500ml | B22: 徐州 | C22: 7504 | E22: 3216
A23: 52°国窖1573 500ml | B23: 北京 | C23: 5311904.6 | D23: 1628599.4 | E23: 2968732.4
A24: 52°国窖1573 500ml | B24: 河南 | C24: 10892047 | D24: 4390187.3 | E24: 4146149.7
A25: 52°国窖1573 500ml | B25: 西安 | C25: 2712408.9 | D25: 586577.97 | E25: 1465210.9
A26: 52°国窖1573 500ml | B26: 徐州 | C26: 94002.44 | E26: 62391
A27: 52°国窖1573曾娜大师鉴藏版500ml | B27: 北京 | C27: 44759.51 | E27: 44759.51
A28: 52°国窖1573曾娜大师鉴藏版500ml | B28: 河南 | C28: 186650.61 | E28: 76146.02
A29: 52°国窖1573曾娜大师鉴藏版500ml | B29: 西安 | C29: 27076 | D29: 0 | E29: 27076
A30: 52°剑南春普装500ml | B30: 北京 | C30: 3324629.5 | D30: 1485636.8 | E30: 1817896.9
A31: 52°剑南春普装500ml | B31: 河南 | C31: 55386699 | D31: 24563243 | E31: 25412162
A32: 52°剑南春普装500ml | B32: 西安 | C32: 1414867.5 | D32: 416542.5 | E32: 644512.5
A33: 52°剑南春普装500ml | B33: 徐州 | C33: 64774.29 | E33: 38787
A34: 52°泸州老窖2018农历戊戌年金狗佑财1.088L | B34: 河南 | C34: 45701.6 | E34: 10201.25
A35: 52°泸州老窖精品头曲D6 500ml | B35: 河南 | C35: 257942.95 | D35: 67815.1 | E35: 116645.75
A36: 52°泸州老窖精品头曲D9 500ml | B36: 河南 | C36: 401551.92 | D36: 261327.44 | E36: 218014.3
A37: 52°泸州老窖特曲500ml | B37: 北京 | C37: 516695.31 | D37: 173707.44 | E37: 267728.7
A38: 52°泸州老窖特曲500ml | B38: 河南 | C38: 9353998.2 | D38: 4392554 | E38: 4320478.4
A39: 52°泸州老窖特曲500ml | B39: 西安 | C39: 316626.87 | D39: 73699.36 | E39: 193260.55
A40: 52°泸州老窖特曲500ml | B40: 徐州 | C40: 26453.7 | E40: 17215.9
A41: 52°泸州老窖头曲500ml | B41: 北京 | C41: 128511.56 | D41: 42079.55 | E41: 63518.62
A42: 52°泸州老窖头曲500ml | B42: 河南 | C42: 1289531.4 | D42: 469723.53 | E42: 554991.24
A43: 52°泸州老窖头曲500ml | B43: 西安 | C43: 80250.12 | D43: 8101.13 | E43: 63558.53
A44: 52°泸州老窖头曲500ml | B44: 徐州 | C44: 8796.96 | E44: 5742.46
A45: 52°泸州老窖中秋丁酉年节庆酒1L | B45: 北京 | C45: 12044.48 | D45: 90709.99 | E45: 5269.46
A46: 52°泸州老窖中秋丁酉年节庆酒1L | B46: 河南 | C46: 23189.85 | D46: 68325.65 | E46: 4087.1
A47: 52°泸州老窖中秋丁酉年节庆酒1L | B47: 西安 | C47: 13987.2 | D47: 33656.7 | E47: 12675.9
A48: 52°五粮液普装500ml | B48: 北京 | C48: 9755379 | D48: 3294765.5 | E48: 5176962.5
A49: 52°五粮液普装500ml | B49: 河南 | C49: 55255963 | D49: 26177582 | E49: 23844273
A50: 52°五粮液普装500ml | B50: 西安 | C50: 4432500 | D50: 851926.5 | E50: 2307559.5
A51: 52°五粮液普装500ml | B51: 徐州 | C51: 428653.68 | D51: 6941.76 | E51: 288950.76
A52: 52°洋河海之蓝480ml | B52: 河南 | C52: 15423160 | D52: 7329468.6 | E52: 6950120
A53: 52°洋河天之蓝480ml | B53: 北京 | C53: 102674 | E53: 102674
A54: 52°洋河天之蓝480ml | B54: 河南 | C54: 5268611.2 | D54: 2383246.4 | E54: 2455570.8
A55: 53°国窖国韵1L | B55: 北京 | C55: 8756.01 | E55: 8756.01
A56: 53°国窖国韵1L | B56: 河南 | C56: 134459.94 | E56: 124312.02
A57: 53°国窖国韵1L | B57: 西安 | C57: 30500.03 | E57: 30500.03
A58: 舒富红葡萄酒750ml | B58: 北京 | C58: 762937.84 | D58: 19796 | E58: 446300.82
A59: 舒富红葡萄酒750ml | B59: 河南 | C59: 2314892.3 | D59: 283285.86 | E59: 1796283.7
A60: 舒富红葡萄酒750ml | B60: 西安 | C60: 360249.09 | D60: 2203.92 | E60: 240961.92
A61: 舒富红葡萄酒750ml | B61: 徐州 | C61: 40479.3 | E61: 34654.23
A62: 希拉谷西拉红葡萄酒750ml | B62: 北京 | C62: 82110 | D62: 3450 | E62: 49450
A63: 希拉谷西拉红葡萄酒750ml | B63: 河南 | C63: 1283040 | D63: 258497.46 | E63: 1751195.2
A64: 希拉谷西拉红葡萄酒750ml | B64: 西安 | C64: 100866.25 | D64: 1767 | E64: 85846.75
A65: 希拉谷庄园西拉红葡萄酒750ml | B65: 北京 | C65: 45193.02 | D65: 3964.3 | E65: 29732.25
A66: 希拉谷庄园西拉红葡萄酒750ml | B66: 河南 | C66: 118306 | D66: 301219.1 | E66: 199414.67
A67: 希拉谷庄园西拉红葡萄酒750ml | B67: 西安 | C67: 25693.98 | D67: 2635.28 | E67: 10541.12

Sheet 过渡表
C3: 数据
A4: 商品名称 | B4: 地区 | C4: 求和项:2017.11-2018.10出库金额 | D4: 求和项:2017.5-2017.10出库金额 | E4: 求和项:2018.5-2018.10出库金额
A5: *42°泸小二FOR ME（彩色）酒125ml | B5: 北京 | C5: 23691.32 | D5: 12350.48 | E5: 10472.08
A6: *42°泸小二FOR ME（彩色）酒125ml | B6: 河南 | C6: 75671.99 | D6: 42948 | E6: 18658.52
A7: *42°泸小二FOR ME（彩色）酒125ml | B7: 西安 | C7: 24246.5 | D7: 5431.5 | E7: 11715
A8: *46°洋河海之蓝480ml | B8: 西安 | C8: 170198.83 | D8: 20225.73 | E8: 89571.09
A9: *52°百年泸州老窖酒窖龄30年500ml | B9: 北京 | C9: 250194.85 | D9: 54077.99 | E9: 147199.84
A10: *52°百年泸州老窖酒窖龄30年500ml | B10: 河南 | C10: 583971.4 | D10: 238437.42 | E10: 267530.58
A11: *52°百年泸州老窖酒窖龄30年500ml | B11: 西安 | C11: 135912.7 | D11: 59678.96 | E11: 63970.94
A12: *52°百年泸州老窖酒窖龄30年500ml | B12: 徐州 | C12: 2616 | E12: 1526
A13: 38°国窖1573 500ml | B13: 北京 | C13: 1064760.8 | D13: 767831.22 | E13: 733167.63
A14: 38°泸州老窖百年60年窖龄500ml | B14: 北京 | C14: 216630 | D14: 86411.3 | E14: 106389.4
A15: 38°泸州老窖泸州百年30年窖龄500ml | B15: 北京 | C15: 123317.04 | D15: 70667.07 | E15: 65862.51
A16: 42°泸州老窖二曲白酒蓝瓶装 500ml | B16: 河南 | C16: 39580.98 | D16: 14807.99 | E16: 15286.31
A17: 42°泸州老窖二曲白酒蓝瓶装 500ml | B17: 徐州 | C17: 550 | D17: 25 | E17: 425
A18: 42°洋河蓝色经典海之蓝480ml | B18: 徐州 | C18: 446936 | D18: 242.9 | E18: 294394.8
A19: 52°百年泸州老窖酒窖龄60年500ml | B19: 北京 | C19: 769069.71 | D19: 203937.78 | E19: 361715.73
A20: 52°百年泸州老窖酒窖龄60年500ml | B20: 河南 | C20: 1451582 | D20: 671666.88 | E20: 616222.68
A21: 52°百年泸州老窖酒窖龄60年500ml | B21: 西安 | C21: 244464.3 | D21: 43205.1 | E21: 110473.8
A22: 52°百年泸州老窖酒窖龄60年500ml | B22: 徐州 | C22: 7504 | E22: 3216
A23: 52°国窖1573 500ml | B23: 北京 | C23: 5311904.6 | D23: 1628599.4 | E23: 2968732.4
A24: 52°国窖1573 500ml | B24: 河南 | C24: 10892047 | D24: 4390187.3 | E24: 4146149.7
A25: 52°国窖1573 500ml | B25: 西安 | C25: 2712408.9 | D25: 586577.97 | E25: 1465210.9
A26: 52°国窖1573 500ml | B26: 徐州 | C26: 94002.44 | E26: 62391
A27: 52°国窖1573曾娜大师鉴藏版500ml | B27: 北京 | C27: 44759.51 | E27: 44759.51
A28: 52°国窖1573曾娜大师鉴藏版500ml | B28: 河南 | C28: 186650.61 | E28: 76146.02
A29: 52°国窖1573曾娜大师鉴藏版500ml | B29: 西安 | C29: 27076 | D29: 0 | E29: 27076
A30: 52°剑南春普装500ml | B30: 北京 | C30: 3324629.5 | D30: 1485636.8 | E30: 1817896.9
A31: 52°剑南春普装500ml | B31: 河南 | C31: 55386699 | D31: 24563243 | E31: 25412162
A32: 52°剑南春普装500ml | B32: 西安 | C32: 1414867.5 | D32: 416542.5 | E32: 644512.5
A33: 52°剑南春普装500ml | B33: 徐州 | C33: 64774.29 | E33: 38787
A34: 52°泸州老窖2018农历戊戌年金狗佑财1.088L | B34: 河南 | C34: 45701.6 | E34: 10201.25
A35: 52°泸州老窖精品头曲D6 500ml | B35: 河南 | C35: 257942.95 | D35: 67815.1 | E35: 116645.75
A36: 52°泸州老窖精品头曲D9 500ml | B36: 河南 | C36: 401551.92 | D36: 261327.44 | E36: 218014.3
A37: 52°泸州老窖特曲500ml | B37: 北京 | C37: 516695.31 | D37: 173707.44 | E37: 267728.7
A38: 52°泸州老窖特曲500ml | B38: 河南 | C38: 9353998.2 | D38: 4392554 | E38: 4320478.4
A39: 52°泸州老窖特曲500ml | B39: 西安 | C39: 316626.87 | D39: 73699.36 | E39: 193260.55
A40: 52°泸州老窖特曲500ml | B40: 徐州 | C40: 26453.7 | E40: 17215.9
A41: 52°泸州老窖头曲500ml | B41: 北京 | C41: 128511.56 | D41: 42079.55 | E41: 63518.62
A42: 52°泸州老窖头曲500ml | B42: 河南 | C42: 1289531.4 | D42: 469723.53 | E42: 554991.24
A43: 52°泸州老窖头曲500ml | B43: 西安 | C43: 80250.12 | D43: 8101.13 | E43: 63558.53
A44: 52°泸州老窖头曲500ml | B44: 徐州 | C44: 8796.96 | E44: 5742.46
A45: 52°泸州老窖中秋丁酉年节庆酒1L | B45: 北京 | C45: 12044.48 | D45: 90709.99 | E45: 5269.46
A46: 52°泸州老窖中秋丁酉年节庆酒1L | B46: 河南 | C46: 23189.85 | D46: 68325.65 | E46: 4087.1
A47: 52°泸州老窖中秋丁酉年节庆酒1L | B47: 西安 | C47: 13987.2 | D47: 33656.7 | E47: 12675.9
A48: 52°五粮液普装500ml | B48: 北京 | C48: 9755379 | D48: 3294765.5 | E48: 5176962.5
A49: 52°五粮液普装500ml | B49: 河南 | C49: 55255963 | D49: 26177582 | E49: 23844273
A50: 52°五粮液普装500ml | B50: 西安 | C50: 4432500 | D50: 851926.5 | E50: 2307559.5
A51: 52°五粮液普装500ml | B51: 徐州 | C51: 428653.68 | D51: 6941.76 | E51: 288950.76
A52: 52°洋河海之蓝480ml | B52: 河南 | C52: 15423160 | D52: 7329468.6 | E52: 6950120
A53: 52°洋河天之蓝480ml | B53: 北京 | C53: 102674 | E53: 102674
A54: 52°洋河天之蓝480ml | B54: 河南 | C54: 5268611.2 | D54: 2383246.4 | E54: 2455570.8
A55: 53°国窖国韵1L | B55: 北京 | C55: 8756.01 | E55: 8756.01
A56: 53°国窖国韵1L | B56: 河南 | C56: 134459.94 | E56: 124312.02
A57: 53°国窖国韵1L | B57: 西安 | C57: 30500.03 | E57: 30500.03
A58: 舒富红葡萄酒750ml | B58: 北京 | C58: 762937.84 | D58: 19796 | E58: 446300.82
A59: 舒富红葡萄酒750ml | B59: 河南 | C59: 2314892.3 | D59: 283285.86 | E59: 1796283.7
A60: 舒富红葡萄酒750ml | B60: 西安 | C60: 360249.09 | D60: 2203.92 | E60: 240961.92
A61: 舒富红葡萄酒750ml | B61: 徐州 | C61: 40479.3 | E61: 34654.23
A62: 希拉谷西拉红葡萄酒750ml | B62: 北京 | C62: 82110 | D62: 3450 | E62: 49450
A63: 希拉谷西拉红葡萄酒750ml | B63: 河南 | C63: 1283040 | D63: 258497.46 | E63: 1751195.2
A64: 希拉谷西拉红葡萄酒750ml | B64: 西安 | C64: 100866.25 | D64: 1767 | E64: 85846.75
A65: 希拉谷庄园西拉红葡萄酒750ml | B65: 北京 | C65: 45193.02 | D65: 3964.3 | E65: 29732.25
A66: 希拉谷庄园西拉红葡萄酒750ml | B66: 河南 | C66: 118306 | D66: 301219.1 | E66: 199414.67
A67: 希拉谷庄园西拉红葡萄酒750ml | B67: 西安 | C67: 25693.98 | D67: 2635.28 | E67: 10541.12
B69: 北京 | C69: =SUMIF($B$5:$B$67,$B69,C$5:C$67) -> 22543259 | D69: =SUMIF($B$5:$B$67,$B69,D$5:D$67) -> 7937984.9 | E69: =SUMIF($B$5:$B$67,$B69,E$5:E$67) -> 12406588
B70: 河南 | C70: =SUMIF($B$5:$B$67,$B70,C$5:C$67) -> 1.5978655e+08 | D70: =SUMIF($B$5:$B$67,$B70,D$5:D$67) -> 71914335 | E70: =SUMIF($B$5:$B$67,$B70,E$5:E$67) -> 72897743
B71: 西安 | C71: =SUMIF($B$5:$B$67,$B71,C$5:C$67) -> 10089848 | D71: =SUMIF($B$5:$B$67,$B71,D$5:D$67) -> 2105651.6 | E71: =SUMIF($B$5:$B$67,$B71,E$5:E$67) -> 5357434.5
B72: 徐州 | C72: =SUMIF($B$5:$B$67,$B72,C$5:C$67) -> 1120766.4 | D72: =SUMIF($B$5:$B$67,$B72,D$5:D$67) -> 7209.66 | E72: =SUMIF($B$5:$B$67,$B72,E$5:E$67) -> 747303.15

Sheet 整理后数据
C2: 地区 | D2: 2017年11月 至2018年10月 | E2: 2017年5月 至2017年10月 | F2: 2018年5月 至2018年10月
B3: 国窖1573 | C3: 北京 | D3: =SUMPRODUCT((透视表!$B$5:$B$67=整理后数据!$C3)*(透视表!C$5:C$67)*ISNUMBER(FIND(整理后数据!$B3,透视表!$A$5:$A$67))) -> 6421424.9 | E3: =SUMPRODUCT((透视表!$B$5:$B$67=整理后数据!$C3)*(透视表!D$5:D$67)*ISNUMBER(FIND(整理后数据!$B3,透视表!$A$5:$A$67))) -> 2396430.7 | F3: =SUMPRODUCT((透视表!$B$5:$B$67=整理后数据!$C3)*(透视表!E$5:E$67)*ISNUMBER(FIND(整理后数据!$B3,透视表!$A$5:$A$67))) -> 3746659.5
B4: 国窖1573 | C4: 河南 | D4: =SUMPRODUCT((透视表!$B$5:$B$67=整理后数据!$C4)*(透视表!C$5:C$67)*ISNUMBER(FIND(整理后数据!$B4,透视表!$A$5:$A$67))) -> 11078698 | E4: =SUMPRODUCT((透视表!$B$5:$B$67=整理后数据!$C4)*(透视表!D$5:D$67)*ISNUMBER(FIND(整理后数据!$B4,透视表!$A$5:$A$67))) -> 4390187.3 | F4: =SUMPRODUCT((透视表!$B$5:$B$67=整理后数据!$C4)*(透视表!E$5:E$67)*ISNUMBER(FIND(整理后数据!$B4,透视表!$A$5:$A$67))) -> 4222295.7
B5: 国窖1573 | C5: 西安 | D5: =SUMPRODUCT((透视表!$B$5:$B$67=整理后数据!$C5)*(透视表!C$5:C$67)*ISNUMBER(FIND(整理后数据!$B5,透视表!$A$5:$A$67))) -> 2739484.9 | E5: =SUMPRODUCT((透视表!$B$5:$B$67=整理后数据!$C5)*(透视表!D$5:D$67)*ISNUMBER(FIND(整理后数据!$B5,透视表!$A$5:$A$67))) -> 586577.97 | F5: =SUMPRODUCT((透视表!$B$5:$B$67=整理后数据!$C5)*(透视表!E$5:E$67)*ISNUMBER(FIND(整理后数据!$B5,透视表!$A$5:$A$67))) -> 1492286.9
B6: 国窖1573 | C6: 徐州 | D6: =SUMPRODUCT((透视表!$B$5:$B$67=整理后数据!$C6)*(透视表!C$5:C$67)*ISNUMBER(FIND(整理后数据!$B6,透视表!$A$5:$A$67))) -> 94002.44 | E6: =SUMPRODUCT((透视表!$B$5:$B$67=整理后数据!$C6)*(透视表!D$5:D$67)*ISNUMBER(FIND(整理后数据!$B6,透视表!$A$5:$A$67))) -> 0 | F6: =SUMPRODUCT((透视表!$B$5:$B$67=整理后数据!$C6)*(透视表!E$5:E$67)*ISNUMBER(FIND(整理后数据!$B6,透视表!$A$5:$A$67))) -> 62391
B7: 窖龄 | C7: 北京 | D7: =SUMPRODUCT((透视表!$B$5:$B$67=整理后数据!$C7)*(透视表!C$5:C$67)*ISNUMBER(FIND(整理后数据!$B7,透视表!$A$5:$A$67))) -> 1359211.6 | E7: =SUMPRODUCT((透视表!$B$5:$B$67=整理后数据!$C7)*(透视表!D$5:D$67)*ISNUMBER(FIND(整理后数据!$B7,透视表!$A$5:$A$67))) -> 415094.14 | F7: =SUMPRODUCT((透视表!$B$5:$B$67=整理后数据!$C7)*(透视表!E$5:E$67)*ISNUMBER(FIND(整理后数据!$B7,透视表!$A$5:$A$67))) -> 681167.48
B8: 窖龄 | C8: 河南 | D8: =SUMPRODUCT((透视表!$B$5:$B$67=整理后数据!$C8)*(透视表!C$5:C$67)*ISNUMBER(FIND(整理后数据!$B8,透视表!$A$5:$A$67))) -> 2035553.4 | E8: =SUMPRODUCT((透视表!$B$5:$B$67=整理后数据!$C8)*(透视表!D$5:D$67)*ISNUMBER(FIND(整理后数据!$B8,透视表!$A$5:$A$67))) -> 910104.3 | F8: =SUMPRODUCT((透视表!$B$5:$B$67=整理后数据!$C8)*(透视表!E$5:E$67)*ISNUMBER(FIND(整理后数据!$B8,透视表!$A$5:$A$67))) -> 883753.26
B9: 窖龄 | C9: 西安 | D9: =SUMPRODUCT((透视表!$B$5:$B$67=整理后数据!$C9)*(透视表!C$5:C$67)*ISNUMBER(FIND(整理后数据!$B9,透视表!$A$5:$A$67))) -> 380377 | E9: =SUMPRODUCT((透视表!$B$5:$B$67=整理后数据!$C9)*(透视表!D$5:D$67)*ISNUMBER(FIND(整理后数据!$B9,透视表!$A$5:$A$67))) -> 102884.06 | F9: =SUMPRODUCT((透视表!$B$5:$B$67=整理后数据!$C9)*(透视表!E$5:E$67)*ISNUMBER(FIND(整理后数据!$B9,透视表!$A$5:$A$67))) -> 174444.74
B10: 窖龄 | C10: 徐州 | D10: =SUMPRODUCT((透视表!$B$5:$B$67=整理后数据!$C10)*(透视表!C$5:C$67)*ISNUMBER(FIND(整理后数据!$B10,透视表!$A$5:$A$67))) -> 10120 | E10: =SUMPRODUCT((透视表!$B$5:$B$67=整理后数据!$C10)*(透视表!D$5:D$67)*ISNUMBER(FIND(整理后数据!$B10,透视表!$A$5:$A$67))) -> 0 | F10: =SUMPRODUCT((透视表!$B$5:$B$67=整理后数据!$C10)*(透视表!E$5:E$67)*ISNUMBER(FIND(整理后数据!$B10,透视表!$A$5:$A$67))) -> 4742
B11: 特曲 | C11: 北京 | D11: =SUMPRODUCT((透视表!$B$5:$B$67=整理后数据!$C11)*(透视表!C$5:C$67)*ISNUMBER(FIND(整理后数据!$B11,透视表!$A$5:$A$67))) -> 516695.31 | E11: =SUMPRODUCT((透视表!$B$5:$B$67=整理后数据!$C11)*(透视表!D$5:D$67)*ISNUMBER(FIND(整理后数据!$B11,透视表!$A$5:$A$67))) -> 173707.44 | F11: =SUMPRODUCT((透视表!$B$5:$B$67=整理后数据!$C11)*(透视表!E$5:E$67)*ISNUMBER(FIND(整理后数据!$B11,透视表!$A$5:$A$67))) -> 267728.7
B12: 特曲 | C12: 河南 | D12: =SUMPRODUCT((透视表!$B$5:$B$67=整理后数据!$C12)*(透视表!C$5:C$67)*ISNUMBER(FIND(整理后数据!$B12,透视表!$A$5:$A$67))) -> 9353998.2 | E12: =SUMPRODUCT((透视表!$B$5:$B$67=整理后数据!$C12)*(透视表!D$5:D$67)*ISNUMBER(FIND(整理后数据!$B12,透视表!$A$5:$A$67))) -> 4392554 | F12: =SUMPRODUCT((透视表!$B$5:$B$67=整理后数据!$C12)*(透视表!E$5:E$67)*ISNUMBER(FIND(整理后数据!$B12,透视表!$A$5:$A$67))) -> 4320478.4
B13: 特曲 | C13: 西安 | D13: =SUMPRODUCT((透视表!$B$5:$B$67=整理后数据!$C13)*(透视表!C$5:C$67)*ISNUMBER(FIND(整理后数据!$B13,透视表!$A$5:$A$67))) -> 316626.87 | E13: =SUMPRODUCT((透视表!$B$5:$B$67=整理后数据!$C13)*(透视表!D$5:D$67)*ISNUMBER(FIND(整理后数据!$B13,透视表!$A$5:$A$67))) -> 73699.36 | F13: =SUMPRODUCT((透视表!$B$5:$B$67=整理后数据!$C13)*(透视表!E$5:E$67)*ISNUMBER(FIND(整理后数据!$B13,透视表!$A$5:$A$67))) -> 193260.55
B14: 特曲 | C14: 徐州 | D14: =SUMPRODUCT((透视表!$B$5:$B$67=整理后数据!$C14)*(透视表!C$5:C$67)*ISNUMBER(FIND(整理后数据!$B14,透视表!$A$5:$A$67))) -> 26453.7 | E14: =SUMPRODUCT((透视表!$B$5:$B$67=整理后数据!$C14)*(透视表!D$5:D$67)*ISNUMBER(FIND(整理后数据!$B14,透视表!$A$5:$A$67))) -> 0 | F14: =SUMPRODUCT((透视表!$B$5:$B$67=整理后数据!$C14)*(透视表!E$5:E$67)*ISNUMBER(FIND(整理后数据!$B14,透视表!$A$5:$A$67))) -> 17215.9
... B34: 洋河 | C34: 徐州 | D34: =SUMPRODUCT((透视表!$B$5:$B$67=整理后数据!$C34)*(透视表!C$5:C$67)*ISNUMBER(FIND(整理后数据!$B34,透视表!$A$5:$A$67))) -> 446936 | E34: =SUMPRODUCT((透视表!$B$5:$B$67=整理后数据!$C34)*(透视表!D$5:D$67)*ISNUMBER(FIND(整理后数据!$B34,透视表!$A$5:$A$67))) -> 242.9 | F34: =SUMPRODUCT((透视表!$B$5:$B$67=整理后数据!$C34)*(透视表!E$5:E$67)*ISNUMBER(FIND(整理后数据!$B34,透视表!$A$5:$A$67))) -> 294394.8
B35: 其它 | C35: 北京 | D35: =D40-SUMIF($C$3:$C$34,$C35,D$3:D$34) -> 934732.67 | E35: =E40-SUMIF($C$3:$C$34,$C35,E$3:E$34) -> 130270.77 | F35: =F40-SUMIF($C$3:$C$34,$C35,F$3:F$34) -> 549980.62
B36: 其它 | C36: 河南 | D36: =D41-SUMIF($C$3:$C$34,$C36,D$3:D$34) -> 3995261.7 | E36: =E41-SUMIF($C$3:$C$34,$C36,E$3:E$34) -> 954276.07 | F36: =F41-SUMIF($C$3:$C$34,$C36,F$3:F$34) -> 3904152.4
B37: 其它 | C37: 西安 | D37: =D42-SUMIF($C$3:$C$34,$C37,D$3:D$34) -> 555543.05 | E37: =E42-SUMIF($C$3:$C$34,$C37,E$3:E$34) -> 45694.4 | F37: =F42-SUMIF($C$3:$C$34,$C37,F$3:F$34) -> 392240.72
B38: 其它 | C38: 徐州 | D38: =D43-SUMIF($C$3:$C$34,$C38,D$3:D$34) -> 40479.3 | E38: =E43-SUMIF($C$3:$C$34,$C38,E$3:E$34) -> 0 | F38: =F43-SUMIF($C$3:$C$34,$C38,F$3:F$34) -> 34654.23
B40: 辅助区域 | C40: 北京 | D40: 22543259 | E40: 7937984.9 | F40: 12406588
C41: 河南 | D41: 1.5978655e+08 | E41: 71914335 | F41: 72897743
C42: 西安 | D42: 10089848 | E42: 2105651.6 | F42: 5357434.5
C43: 徐州 | D43: 1120766.4 | E43: 7209.66 | F43: 747303.15

Sheet 图表
C2: 地区 | D2: 2017年11月 至2018年10月 | E2: 2017年5月 至2017年10月 | F2: 2018年5月 至2018年10月
B3: 国窖1573 | C3: 北京 | D3: 6421424.9 | E3: 2396430.7 | F3: 3746659.5
C4: 河南 | D4: 11078698 | E4: 4390187.3 | F4: 4222295.7
C5: 西安 | D5: 2739484.9 | E5: 586577.97 | F5: 1492286.9
C6: 徐州 | D6: 94002.44 | E6: 0 | F6: 62391
B7: 窖龄 | C7: 北京 | D7: 1359211.6 | E7: 415094.14 | F7: 681167.48
C8: 河南 | D8: 2035553.4 | E8: 910104.3 | F8: 883753.26
C9: 西安 | D9: 380377 | E9: 102884.06 | F9: 174444.74
C10: 徐州 | D10: 10120 | E10: 0 | F10: 4742
B11: 特曲 | C11: 北京 | D11: 516695.31 | E11: 173707.44 | F11: 267728.7
C12: 河南 | D12: 9353998.2 | E12: 4392554 | F12: 4320478.4
C13: 西安 | D13: 316626.87 | E13: 73699.36 | F13: 193260.55
C14: 徐州 | D14: 26453.7 | E14: 0 | F14: 17215.9
B15: 头曲 | C15: 北京 | D15: 128511.56 | E15: 42079.55 | F15: 63518.62
C16: 河南 | D16: 1949026.3 | E16: 798866.07 | F16: 889651.29
C17: 西安 | D17: 80250.12 | E17: 8101.13 | F17: 63558.53
C18: 徐州 | D18: 8796.96 | E18: 0 | F18: 5742.46
B19: 二曲 | C19: 北京 | D19: 0 | E19: 0 | F19: 0
C20: 河南 | D20: 39580.98 | E20: 14807.99 | F20: 15286.31
C21: 西安 | D21: 0 | E21: 0 | F21: 0
C22: 徐州 | D22: 550 | E22: 25 | F22: 425
B23: 五粮液 | C23: 北京 | D23: 9755379 | E23: 3294765.5 | F23: 5176962.5
C24: 河南 | D24: 55255963 | E24: 26177582 | F24: 23844273
C25: 西安 | D25: 4432500 | E25: 851926.5 | F25: 2307559.5
C26: 徐州 | D26: 428653.68 | E26: 6941.76 | F26: 288950.76
B27: 剑南春 | C27: 北京 | D27: 3324629.5 | E27: 1485636.8 | F27: 1817896.9
C28: 河南 | D28: 55386699 | E28: 24563243 | F28: 25412162
C29: 西安 | D29: 1414867.5 | E29: 416542.5 | F29: 644512.5
C30: 徐州 | D30: 64774.29 | E30: 0 | F30: 38787
B31: 洋河 | C31: 北京 | D31: 102674 | E31: 0 | F31: 102674
C32: 河南 | D32: 20691771 | E32: 9712715 | F32: 9405690.8
C33: 西安 | D33: 170198.83 | E33: 20225.73 | F33: 89571.09
C34: 徐州 | D34: 446936 | E34: 242.9 | F34: 294394.8
B35: 其它 | C35: 北京 | D35: 934732.67 | E35: 130270.77 | F35: 549980.62
C36: 河南 | D36: 3995261.7 | E36: 954276.07 | F36: 3904152.4
C37: 西安 | D37: 555543.05 | E37: 45694.4 | F37: 392240.72
C38: 徐州 | D38: 40479.3 | E38: 0 | F38: 34654.23
